Workbook
Name Timeline_Date: #N/A
Name Timeline_Date1: #N/A

Sheet DASHBOARD
A1: Learning and Development Dash Board
Z6: Participation rate
B7: Total Programs | D7: Training Days | F7: Total Participants | H7: Training Hours | L7: NPS Overall Score | N7: Facilitators Performance | Q7: Knowledge Relevance | T7: Activity Effectivness | W7: Logistics Effectivness | Z7: =F8/192 -> 0.66666667 | AA7: Customised | AB7: ='Program Pivots'!B23 -> 0.53125
B8: =GETPIVOTDATA("[Measures].[Distinct Count of Program Name 2]",'Program Pivots'!$S$3) -> 24 | D8: =GETPIVOTDATA("[Measures].[Sum of No.of sessions 2]",'Program Pivots'!$P$3) -> 40 | F8: =GETPIVOTDATA("[Measures].[Distinct Count of Name 2]",'Program Pivots'!$G$3) -> 128 | H8: ='Program Pivots'!B5 -> 130.5 | L8: =GETPIVOTDATA("[Measures].[Average of NPS]",'Evaluation Pivots'!$D$3) -> 0.92727273 | O8: =GETPIVOTDATA("[Measures].[Average of FACILITATOR PERFORMANCE]",'Evaluation Pivots'!$A$3) -> 1 | Q8: =GETPIVOTDATA("[Measures].[Average of KNOWLEDGE RELVEANCE 2]",'Evaluation Pivots'!$D$3) -> 1 | T8: =GETPIVOTDATA("[Measures].[Average of ACTIVITY EFFECTIVNESS]",'Evaluation Pivots'!$D$3) -> 0.98181818 | W8: =GETPIVOTDATA("[Measures].[Average of LOGISTICS EFFECTIVNESS]",'Evaluation Pivots'!$D$3) -> 0.96363636 | AA8: Public Calender | AB8: ='Program Pivots'!B19 -> 0.33854167

Sheet Program Pivots
B1: HC | C1: 192 | J1: Date | K1: All
A2: Main L&D Data (YTD) | D2: Internal vs External Training | G2: Participation per Program | J2: Participation per Sector | M2: Training Hours | P2: Training Days | S2: Monthly Track | X2: Trainer Profile | AC2: Enrollment vs Participation per Program | AG2: Unique User count | AJ2: Learning Hours per Participant | AM2: PC vs Customised | AR2: Customised Track
A3: No.of Programs | B3: =GETPIVOTDATA("[Measures].[Distinct Count of Program Name 2]",$D$3) -> 25 | D3: Row Labels | E3: Distinct Count of Program Name | G3: Row Labels | H3: Distinct Count of Name | J3: Row Labels | K3: Distinct Count of Name | M3: Row Labels | N3: Sum of Program Duration/hrs | P3: Row Labels | Q3: Sum of No.of sessions | S3: Row Labels | T3: Training Days | U3: Participation | V3: No. of Programs | X3: Row Labels | Y3: Training Days | Z3: Programs | AC3: Row Labels | AD3: Participation | AE3: Enrollments | AG3: Row Labels | AH3: Distinct Count of Name | AJ3: Row Labels | AK3: Sum of Learning Hrs | AM3: Row Labels | AN3: Distinct Count of Name | AO3: Sum of No.of sessions | AP3: Sum of Learning Hrs | AR3: Row Labels | AS3: Count of Program Name
A4: No. of Participants | B4: =GETPIVOTDATA("[Measures].[Distinct Count of Name 2]",$G$3) -> 128 | D4: External | E4: 3 | G4: Ai 4 Marq - AI Foundations - Wave 2 | H4: 5 | J4: #N/A | K4: 2 | M4: Ai 4 Marq - AI Foundations - Wave 2 | N4: 2 | P4: Ai 4 Marq - AI Foundations - Wave 2 | Q4: 1 | S4: Feb | T4: 7 | U4: 18 | V4: 6 | X4: Ahmed Elshiaty | Y4: 10 | Z4: 5 | AC4: Ai 4 Marq - AI Foundations - Wave 2 | AD4: 5 | AE4: 17 | AG4: Abdelaziz Youssef Abo El Wafa Mohamed | AH4: 1 | AJ4: Abdelaziz Youssef Abo El Wafa Mohamed | AK4: 15 | AM4: Customised | AN4: 102 | AO4: 19 | AP4: 867.5 | AR4: Customised
A5: Training Hrs | B5: =GETPIVOTDATA("[Measures].[Sum of Program Duration/hrs]",$M$3) -> 130.5 | D5: Internal | E5: 22 | G5: Ai 4 Marq - Level 1 | H5: 17 | J5: CCE | K5: 3 | M5: Ai 4 Marq - Level 1 | N5: 2 | P5: Ai 4 Marq - Level 1 | Q5: 1 | S5: Mar | T5: 3 | U5: 16 | V5: 3 | X5: Ahmed Magdi | Y5: 2 | Z5: 1 | AC5: Ai 4 Marq - Level 1 | AD5: 17 | AE5: 26 | AG5: Abdelrahman Ismail Abdallah Elshahat | AH5: 1 | AJ5: Abdelrahman Ismail Abdallah Elshahat | AK5: 6 | AM5: Public Calender | AN5: 65 | AO5: 21 | AP5: 518.5 | AR5: CCE | AS5: 2
A6: Training Days | B6: =GETPIVOTDATA("[Measures].[Sum of No.of sessions 2]",$P$3) -> 40 | D6: Grand Total | E6: 25 | G6: AI for real estate (Projects-D&I) | H6: 23 | J6: Commercial | K6: 21 | M6: AI for real estate (Projects-D&I) | N6: 8 | P6: AI for real estate (Projects-D&I) | Q6: 2 | S6: Apr | T6: 3 | U6: 24 | V6: 2 | X6: Amr Alaa | Y6: 11 | Z6: 8 | AC6: AI for real estate (Projects-D&I) | AD6: 23 | AE6: 46 | AG6: Abdelrahman Khaled Saber Mohamed | AH6: 1 | AJ6: Abdelrahman Khaled Saber Mohamed | AK6: 16 | AM6: Grand Total | AN6: 128 | AO6: 40 | AP6: 1386 | AR6: Finance | AS6: 2
A7: Participation Rate | B7: =GETPIVOTDATA("[Measures].[Distinct Count of Name 2]",$G$3)/192 -> 0.66666667 | G7: Customer Focus | H7: 10 | J7: Communities & Clients Excellence | K7: 29 | M7: Customer Focus | N7: 9 | P7: Customer Focus | Q7: 2 | S7: May | T7: 6 | U7: 48 | V7: 4 | X7: Aya Sameh | Y7: 8 | Z7: 6 | AC7: Customer Focus | AD7: 10 | AE7: 10 | AG7: Abdelrahman Mohamed Saad Ahmed | AH7: 1 | AJ7: Abdelrahman Mohamed Saad Ahmed | AK7: 16.5 | AR7: I&D | AS7: 1
A8: Internal % | B8: =((GETPIVOTDATA("[Measures].[Distinct Count of Program Name 2]",$D$3,"[Range].[Internal/External]","[Range].[Internal/External].&[Internal]")/GETPIVOTDATA("[Measures].[Distinct Count of Program Name 2]",$D$3))) -> 0.88 | G8: Customer XP Cycle-CCE ONLY | H8: 13 | J8: Development & Innovation | K8: 18 | M8: Customer XP Cycle-CCE ONLY | N8: 6 | P8: Customer XP Cycle-CCE ONLY | Q8: 2 | S8: Jun | T8: 12 | U8: 64 | V8: 6 | X8: Belton Academy | Y8: 2 | Z8: 1 | AC8: Customer XP Cycle-CCE ONLY | AD8: 13 | AE8: 15 | AG8: Ahmad Mohamed Ahmad Mohamed Mansour | AH8: 1 | AJ8: Ahmad Mohamed Ahmad Mohamed Mansour | AK8: 5 | AR8: L&D | AS8: 1
A9: Compiled Participation | B9: 98 | G9: Excel 101 | H9: 11 | J9: Finance | K9: 14 | M9: Excel 101 | N9: 13.5 | P9: Excel 101 | Q9: 4 | S9: Jul | T9: 7 | U9: 41 | V9: 4 | X9: Moaataz | Y9: 4 | Z9: 1 | AC9: Excel 101 | AD9: 11 | AE9: 14 | AG9: Ahmed Abdel Hakim | AH9: 1 | AJ9: Ahmed Abdel Hakim | AK9: 5 | AR9: Projects | AS9: 2
A10: Linked In | B10: 12 | D10: Programs per Focus | G10: Goal Setting &Building Habits -HS | H10: 9 | J10: HR Business Partner | K10: 2 | M10: Goal Setting &Building Habits -HS | N10: 5 | P10: Goal Setting &Building Habits -HS | Q10: 1 | S10: Grand Total | T10: 38 | U10: 128 | V10: 24 | X10: Omar Ali | Y10: 2 | Z10: 2 | AC10: Goal Setting &Building Habits -HS | AD10: 9 | AE10: 12 | AG10: Ahmed elsayed elsayed elshiaty | AH10: 1 | AJ10: Ahmed elsayed elsayed elshiaty | AK10: 5 | AR10: Sales | AS10: 5
D11: Row Labels | E11: Count of Program Name | G11: Hard Talks | H11: 5 | J11: Human Resources | K11: 9 | M11: Hard Talks | N11: 6 | P11: Hard Talks | Q11: 2 | X11: Yehia Maklad | Y11: 1 | Z11: 1 | AC11: Hard Talks | AD11: 5 | AE11: 14 | AG11: Ahmed Gamal Mostafa Kamel | AH11: 1 | AJ11: Ahmed Gamal Mostafa Kamel | AK11: 23 | AR11: Public Calender
D12: Customised | E12: 13 | G12: HPI | H12: 6 | J12: Investment | K12: 2 | M12: HPI | N12: 5 | P12: HPI | Q12: 1 | X12: Grand Total | Y12: 40 | Z12: 25 | AC12: HPI | AD12: 6 | AE12: 6 | AG12: Ahmed kamal El Din Hassan El Khateeb | AH12: 1 | AJ12: Ahmed kamal El Din Hassan El Khateeb | AK12: 11 | AR12: (blank) | AS12: 12
D13: Public Calender | E13: 12 | G13: inside out | H13: 6 | J13: Marketing | K13: 1 | M13: inside out | N13: 6 | P13: inside out | Q13: 2 | AC13: inside out | AD13: 6 | AE13: 6 | AG13: Ahmed Khaled Kamal Ibrahim | AH13: 1 | AJ13: Ahmed Khaled Kamal Ibrahim | AK13: 15 | AR13: Grand Total | AS13: 25
D14: Grand Total | E14: 25 | G14: Island of Seacrets-(Finance Dept) | H14: 11 | J14: Marketing & PR | K14: 6 | M14: Island of Seacrets-(Finance Dept) | N14: 2.5 | P14: Island of Seacrets-(Finance Dept) | Q14: 1 | AC14: Island of Seacrets-(Finance Dept) | AD14: 11 | AE14: 16 | AG14: Ahmed Magdy Fekry Elhagaa | AH14: 1 | AJ14: Ahmed Magdy Fekry Elhagaa | AK14: 5
G15: LinkedIn Learning Kick-Off Session | H15: 16 | J15: Projects | K15: 21 | M15: LinkedIn Learning Kick-Off Session | N15: 1 | P15: LinkedIn Learning Kick-Off Session | Q15: 1 | AC15: LinkedIn Learning Kick-Off Session | AD15: 16 | AE15: 23 | AG15: Ahmed Medhat Sayed Baioumy el Atbany | AH15: 1 | AJ15: Ahmed Medhat Sayed Baioumy el Atbany | AK15: 14
G16: Master The Shift | H16: 10 | J16: Treasury | K16: 7 | M16: Master The Shift | N16: 4.5 | P16: Master The Shift | Q16: 2 | AC16: Master The Shift | AD16: 10 | AE16: 13 | AG16: Ahmed mohamed AboelMagd Eldardiri | AH16: 1 | AJ16: Ahmed mohamed AboelMagd Eldardiri | AK16: 9
G17: Parenting 101 | H17: 9 | J17: Grand Total | K17: 128 | M17: Parenting 101 | N17: 4 | P17: Parenting 101 | Q17: 1 | AC17: Parenting 101 | AD17: 9 | AE17: 10 | AG17: Ahmed Mohamed Ahmed Salem | AH17: 1 | AJ17: Ahmed Mohamed Ahmed Salem | AK17: 9
A18: Public Calender | G18: Presentation Skills-HS | H18: 7 | M18: Presentation Skills-HS | N18: 5 | P18: Presentation Skills-HS | Q18: 1 | AC18: Presentation Skills-HS | AD18: 7 | AE18: 12 | AG18: Ahmed Mohamed Gamal Mohamed Mohamed Youssef Elbehery | AH18: 1 | AJ18: Ahmed Mohamed Gamal Mohamed Mohamed Youssef Elbehery | AK18: 1
A19: Participation Rate | B19: =GETPIVOTDATA("[Measures].[Distinct Count of Name 2]",$D$20,"[Range].[Participation PC/Cust]","[Range].[Participation PC/Cust].&[Public Calender]")/C1 -> 0.33854167 | D19: Participation per Focus | G19: Sales Skills 1-HS | H19: 9 | M19: Sales Skills 1-HS | N19: 5 | P19: Sales Skills 1-HS | Q19: 1 | AC19: Sales Skills 1-HS | AD19: 9 | AE19: 12 | AG19: Ahmed Raouf Abdel Menaam Hanafy | AH19: 1 | AJ19: Ahmed Raouf Abdel Menaam Hanafy | AK19: 8
A20: No.of Public Calender Topics | B20: =GETPIVOTDATA("[Measures].[Count of Program Name 2]",$D$11,"[Range].[PC/Cust (Per Topic)]","[Range].[PC/Cust (Per Topic)].&[Public Calender]") -> 12 | D20: Row Labels | E20: Distinct Count of Name | G20: Sales Skills 2-HS | H20: 9 | M20: Sales Skills 2-HS | N20: 5 | P20: Sales Skills 2-HS | Q20: 1 | AC20: Sales Skills 2-HS | AD20: 9 | AE20: 12 | AG20: Ahmed Saber Abdelrady Mohamed | AH20: 1 | AJ20: Ahmed Saber Abdelrady Mohamed | AK20: 20
D21: Customised | E21: 102 | G21: Self Discovery Lab | H21: 6 | M21: Self Discovery Lab | N21: 4 | P21: Self Discovery Lab | Q21: 2 | AC21: Self Discovery Lab | AD21: 6 | AE21: 10 | AG21: Ahmed Samir Galal Elelemy Ahmed | AH21: 1 | AJ21: Ahmed Samir Galal Elelemy Ahmed | AK21: 30
A22: Customised | D22: Public Calender | E22: 65 | G22: Slide Design | H22: 1 | M22: Slide Design | N22: 6 | P22: Slide Design | Q22: 2 | AC22: Slide Design | AD22: 1 | AE22: 8 | AG22: Ahmed Shawky Abdo El Bastawisy El Sahy | AH22: 1 | AJ22: Ahmed Shawky Abdo El Bastawisy El Sahy | AK22: 7
A23: Participation Rate | B23: =GETPIVOTDATA("[Measures].[Distinct Count of Name 2]",$D$20,"[Range].[Participation PC/Cust]","[Range].[Participation PC/Cust].&[Customised]")/C1 -> 0.53125 | D23: Grand Total | E23: 128 | G23: Story Craft | H23: 13 | M23: Story Craft | N23: 4 | P23: Story Craft | Q23: 2 | AC23: Story Craft | AD23: 13 | AE23: 20 | AG23: Ahmed Sobhy Mohamed Bayoumi | AH23: 1 | AJ23: Ahmed Sobhy Mohamed Bayoumi | AK23: 9
A24: No.of Cust Programs | B24: =GETPIVOTDATA("[Measures].[Count of Program Name 2]",$D$11,"[Range].[PC/Cust (Per Topic)]","[Range].[PC/Cust (Per Topic)].&[Customised]") -> 13 | G24: The Connected Leader | H24: 23 | M24: The Connected Leader | N24: 6 | P24: The Connected Leader | Q24: 2 | AC24: The Connected Leader | AD24: 23 | AE24: 34 | AG24: Aida Fouad Mohamed Kamal | AH24: 1 | AJ24: Aida Fouad Mohamed Kamal | AK24: 2
G25: The Influence Map | H25: 21 | M25: The Influence Map | N25: 6 | P25: The Influence Map | Q25: 2 | AC25: The Influence Map | AD25: 21 | AE25: 25 | AG25: Alaa Essam Mohamed Ibrahim | AH25: 1 | AJ25: Alaa Essam Mohamed Ibrahim | AK25: 9
G26: The Influence Map (Projects) | H26: 20 | M26: The Influence Map (Projects) | N26: 6 | P26: The Influence Map (Projects) | Q26: 2 | AC26: The Influence Map (Projects) | AD26: 20 | AE26: 27 | AG26: Amira Tarek Mohamed Abdelmutaal Ali El Sherkawy | AH26: 1 | AJ26: Amira Tarek Mohamed Abdelmutaal Ali El Sherkawy | AK26: 15
G27: Think Human | H27: 3 | M27: Think Human | N27: 4 | P27: Think Human | Q27: 1 | AC27: Think Human | AD27: 3 | AE27: 9 | AG27: Amr Alaa Eldin Maged Ahmed | AH27: 1 | AJ27: Amr Alaa Eldin Maged Ahmed | AK27: 5
G28: Time &Self Management -HS | H28: 6 | M28: Time &Self Management -HS | N28: 5 | P28: Time &Self Management -HS | Q28: 1 | AC28: Time &Self Management -HS | AD28: 6 | AE28: 12 | AG28: Amr Ali Abdelwahab Sobh | AH28: 1 | AJ28: Amr Ali Abdelwahab Sobh | AK28: 14.5
G29: Grand Total | H29: 128 | M29: Grand Total | N29: 130.5 | P29: Grand Total | Q29: 40 | AC29: Grand Total | AD29: 128 | AE29: 409 | AG29: Amr Ali Mahmoud Elhanbaly | AH29: 1 | AJ29: Amr Ali Mahmoud Elhanbaly | AK29: 25
AG30: Amr Hani Mohamed Abdel Latif | AH30: 1 | AJ30: Amr Hani Mohamed Abdel Latif | AK30: 14.5
AG31: Amr Hussein Hassan Mohamed Ali | AH31: 1 | AJ31: Amr Hussein Hassan Mohamed Ali | AK31: 5
AG32: Aya Khaled Naeem Elkhawaga | AH32: 1 | AJ32: Aya Khaled Naeem Elkhawaga | AK32: 12
AG33: Aya Sameh Hassan Ibrahim | AH33: 1 | AJ33: Aya Sameh Hassan Ibrahim | AK33: 5
AG34: Aya Tarek Mossad Abdelaziz | AH34: 1 | AJ34: Aya Tarek Mossad Abdelaziz | AK34: 10
AG35: Ayman Mousa Haneen Mokbel | AH35: 1 | AJ35: Ayman Mousa Haneen Mokbel | AK35: 2
AG36: Baher Saeed Khamis Mahmoud Elshamy | AH36: 1 | AJ36: Baher Saeed Khamis Mahmoud Elshamy | AK36: 9
AG37: Diana Hossam Abdelrahman Osman | AH37: 1 | AJ37: Diana Hossam Abdelrahman Osman | AK37: 21
AG38: Eleonora Christo Paraskevas Vostanis | AH38: 1 | AJ38: Eleonora Christo Paraskevas Vostanis | AK38: 14
AG39: eslam fathy abdelhamid mohamed | AH39: 1 | AJ39: eslam fathy abdelhamid mohamed | AK39: 15.5
AG40: Farouk Mohamed Farouk Soliman | AH40: 1 | AJ40: Farouk Mohamed Farouk Soliman | AK40: 1
AG41: Gehad Badr El Sayed Bayoumi | AH41: 1 | AJ41: Gehad Badr El Sayed Bayoumi | AK41: 19.5
... AG132: Grand Total | AH132: 128 | AJ132: Grand Total | AK132: 1386

Sheet Top Learner
A2: Learner | B2: Learning Hrs | C2: Department | D2: Linkedin hours | E2: Position | F2: Trophy
A3: Ahmed Gamal Mostafa Kamel | B3: 23 | C3: =VLOOKUP(A3,'Head Count 212'!B:L,11,0) -> MEP | E3: =VLOOKUP('Top Learner'!$A3,[1]Sheet1!$A:$F,6,0) -> MEP Design Section Head | F3: TL 1 | G3: 1500
A4: Shereen walaa mohamed askar | B4: 23 | C4: =VLOOKUP(A4,'Head Count 212'!B:L,11,0) -> Architecture | E4: =VLOOKUP('Top Learner'!$A4,[1]Sheet1!$A:$F,6,0) -> Design Management Section Head | F4: TM | G4: 2000
A5: Khadija Mohamed Ahmed Zayed | B5: 22 | C5: =VLOOKUP(A5,'Head Count 212'!B:L,11,0) -> Call Center | D5: 0.5 | E5: =VLOOKUP('Top Learner'!$A5,[1]Sheet1!$A:$F,6,0) -> Communication Center Representative | F5: TL 2 | G5: 1200
A6: Diana Hossam Abdelrahman Osman | B6: 21 | C6: =VLOOKUP(A6,'Head Count 212'!B:L,11,0) -> Design Management | E6: =VLOOKUP('Top Learner'!$A6,[1]Sheet1!$A:$F,6,0) -> Design Management Section Head | F6: TL 3 | G6: 900
A9: Row Labels | B9: Actual | C9: Planned
A10: Customised
A11: CCE | B11: 2
A12: Finance | B12: 2
A13: I&D | B13: 1
A14: L&D | B14: 1
A15: Projects | B15: 2
A16: Sales | B16: 5
A17: Public Calender
A18: (blank) | B18: 12
A19: Grand Total | B19: 25

Sheet Evaluation Pivots
D1: Completion Time | E1: (Multiple Items)
A3: Row Labels | B3: Average of FACILITATOR PERFORMANCE | D3: Row Labels | E3: Average of NPS | F3: Average of KNOWLEDGE RELVEANCE | G3: Average of LOGISTICS EFFECTIVNESS | H3: Average of ACTIVITY EFFECTIVNESS
A4: Ahmed ElShiaty | B4: 1 | D4: Hard Talks | E4: 1 | F4: 1 | G4: 1 | H4: 1
A5: Amr Alaa | B5: 1 | D5: Island of Seacrets-(Finance Dept) | E5: 1 | F5: 1 | G5: 1 | H5: 1
A6: Aya Sameh | B6: 1 | D6: Master The Shift | E6: 0.75 | F6: 1 | G6: 1 | H6: 1
A7: Grand Total | B7: 1 | D7: Parenting 101 | E7: 1 | F7: 1 | G7: 1 | H7: 1
D8: Self Discovery Lab | E8: 1 | F8: 1 | G8: 1 | H8: 1
D9: Story Craft | E9: 1 | F9: 1 | G9: 1 | H9: 1
D10: The Connected Leader | E10: 1 | F10: 1 | G10: 0.83333333 | H10: 0.91666667
D11: The Influence Map | E11: 0.72727273 | F11: 1 | G11: 1 | H11: 1
D12: Think Human | E12: 1 | F12: 1 | G12: 1 | H12: 1
D13: Grand Total | E13: 0.92727273 | F13: 1 | G13: 0.96363636 | H13: 0.98181818

Sheet Attendance Master Sheet
A1: # | B1: Enrollments | C1: Participation PC/Cust | D1: PC/Cust (Per Topic) | E1: Customised (Dept) | F1: Program Name | G1: Trainer Name | H1: Program Duration/hrs | I1: Learning Hrs | J1: No.of sessions | K1: Name | L1: Phone Number | M1: Email | N1: Department | O1: Job Title | P1: Employee Code | Q1: Date | R1: Internal/External | S1: Sector
A2: 1 | B2: 10 | C2: Public Calender | D2: Public Calender | F2: Self Discovery Lab | G2: Ahmed Magdi | H2: 2 | I2: 2 | J2: 2 | K2: Eleonora Christo Paraskevas Vostanis | L2: 01001483748 | M2: eleonora.christo@themarq.com.eg | N2: Content Writing | O2: Junior Content Writer | P2: TM4-16669 | Q2: 46076 | R2: Internal | S2: Marketing & PR
A3: 2 | C3: Public Calender | F3: Self Discovery Lab | G3: Ahmed Magdi | I3: 2 | K3: Aya Tarek Mossad Abdelaziz | L3: 01148322683 | M3: aya.tarek@themarq.com.eg | N3: Call Center | O3: Communication Center Representative | P3: TM4-21925 | Q3: 46076 | R3: Internal | S3: Communities & Clients Excellence
A4: 3 | C4: Public Calender | F4: Self Discovery Lab | G4: Ahmed Magdi | I4: 2 | K4: Mohamed Ahmed Abdallah Ahmed Sharaf | L4: 01285727056 | M4: mohamed.abdullah@themarq.com.eg | N4: Call Center | O4: Communication Center Representative | P4: TM4-32401 | Q4: 46076 | R4: Internal | S4: Communities & Clients Excellence
A5: 4 | C5: Public Calender | F5: Self Discovery Lab | G5: Ahmed Magdi | I5: 2 | K5: Khadija Mohamed Ahmed Zayed | L5: 1099170090 | M5: khadija.zayed@themarq.com.eg | N5: Call Center | O5: Communication Center Representative | P5: TM4-31843 | Q5: 46076 | R5: Internal | S5: Communities & Clients Excellence
A6: 5 | C6: Public Calender | F6: Self Discovery Lab | G6: Ahmed Magdi | H6: 2 | I6: 2 | K6: Mohamed Ahmed Abdallah Ahmed Sharaf | L6: 01285727056 | M6: mohamed.abdullah@themarq.com.eg | N6: Call Center | O6: Communication Center Representative | P6: TM4-32401 | Q6: 46077 | R6: Internal | S6: Communities & Clients Excellence
A7: 6 | C7: Public Calender | F7: Self Discovery Lab | G7: Ahmed Magdi | I7: 2 | K7: Aya Khaled Naeem Elkhawaga | L7: 01111879328 | M7: aya.elkhawaga@themarq.com.eg | N7: HR Business Partner | O7: HR Business Partner Supervisor | P7: TM4-32448 | Q7: 46077 | R7: Internal | S7: Human Resources
A8: 7 | C8: Public Calender | F8: Self Discovery Lab | G8: Ahmed Magdi | I8: 2 | K8: Mariam Ibrahim Mohamed Ibrahim | L8: 01007512970 | M8: mariam.ibrahim@themarq.com.eg | N8: HR Business Partner | O8: HR Business Partner Supervisor | P8: TM4-22886 | Q8: 46077 | R8: Internal | S8: Human Resources | W8: Row Labels | X8: Count of Name
A9: 8 | C9: Public Calender | F9: Self Discovery Lab | G9: Ahmed Magdi | I9: 2 | K9: Eleonora Christo Paraskevas Vostanis | L9: 01001483748 | M9: eleonora.christo@themarq.com.eg | N9: Content Writing | O9: Junior Content Writer | P9: TM4-16669 | Q9: 46077 | R9: Internal | S9: Marketing & PR | W9: Ai 4 Marq - AI Foundations - Wave 2 | X9: 5
A10: 9 | B10: 6 | C10: Customised | D10: Customised | E10: L&D | F10: HPI | G10: Yehia Maklad | H10: 5 | I10: 5 | J10: 1 | K10: Ahmed elsayed elsayed elshiaty | L10: 01006856836 | M10: ahmed.elshiaty@themarq.com.eg | N10: Learning & Development | O10: Learning & Development Director | P10: TM4-17746 | Q10: 46090 | R10: External | S10: Human Resources | W10: Ai 4 Marq - Level 1 | X10: 17
A11: 10 | C11: Customised | F11: HPI | G11: Yehia Maklad | I11: 5 | K11: Passant Magdy Abdel Razek Eliwa | L11: 01099691693 | M11: passant.magdy@themarq.com.eg | N11: Organization Development & Talent Management | O11: OD & Talent Management Director | P11: TM4-14720 | Q11: 46090 | R11: External | S11: Human Resources | W11: AI for real estate (Projects-D&I) | X11: 46
A12: 11 | C12: Customised | F12: HPI | G12: Yehia Maklad | I12: 5 | K12: Ahmed Magdy Fekry Elhagaa | L12: 01024642618 | M12: a.magdi@themarq.com.eg | N12: Learning & Development | O12: Learning & Development Manager | P12: TM4-21123 | Q12: 46090 | R12: External | S12: Human Resources | W12: Customer Focus | X12: 20
A13: 12 | C13: Customised | F13: HPI | G13: Yehia Maklad | I13: 5 | K13: Amr Alaa Eldin Maged Ahmed | L13: 01002527457 | M13: a.alaa@themarq.com.eg | N13: Learning & Development | O13: Learning & Development Manager | P13: TM4-21124 | Q13: 46090 | R13: External | S13: Human Resources | W13: Customer XP Cycle-CCE ONLY | X13: 26
A14: 13 | C14: Customised | F14: HPI | G14: Yehia Maklad | I14: 5 | K14: Aya Sameh Hassan Ibrahim | L14: 01015101500 | M14: aya.sameh@themarq.com.eg | N14: Learning & Development | O14: Learning & Development Manager | P14: TM4-27684 | Q14: 46090 | R14: External | S14: Human Resources | W14: Excel 101 | X14: 40
A15: 14 | C15: Customised | F15: HPI | G15: Yehia Maklad | I15: 5 | K15: Ahmad Mohamed Ahmad Mohamed Mansour | L15: 01115455761 | M15: ahmad.mansour@themarq.com.eg | N15: Organization Development & Talent Management | O15: Associate OD & Talent Management Manager | P15: TMC-33188 | Q15: 46090 | R15: External | S15: Human Resources | W15: Goal Setting &Building Habits -HS | X15: 9
A16: 15 | B16: 9 | C16: Public Calender | D16: Public Calender | F16: Think Human | G16: Aya Sameh | H16: 4 | I16: 4 | J16: 1 | K16: Mohamed Mabrouk Ismail Mohamed | L16: 01099262847 | M16: mohamed.mabrouk@themarq.com.eg | N16: Accounts Receivable | O16: Associate Accounts Receivable Manager | P16: TM4-8006 | Q16: 46097 | R16: Internal | S16: Finance | W16: Hard Talks | X16: 8
A17: 16 | C17: Public Calender | F17: Think Human | G17: Aya Sameh | I17: 4 | K17: Mohamed Hussein Yaqoub Mohamed | L17: 01093124080 | M17: mohamed.husien@themarq.com.eg | N17: Call Center | O17: Senior Communication Center Representative | P17: TM4-21494 | Q17: 46097 | R17: Internal | S17: Communities & Clients Excellence | W17: HPI | X17: 6
A18: 17 | C18: Public Calender | F18: Think Human | G18: Aya Sameh | I18: 4 | K18: MennatAllah Yahya Mohamed Tawfik Ahmed Abdul Aziz | L18: 01005397775 | M18: menna.yahya@themarq.com.eg | N18: Business Development | O18: Business Development Director | P18: TM4-15460 | Q18: 46097 | R18: Internal | S18: Commercial | W18: inside out | X18: 11
A19: 18 | B19: 10 | C19: Public Calender | D19: Public Calender | F19: Parenting 101 | G19: Aya Sameh | H19: 4 | I19: 4 | J19: 1 | K19: Aya Khaled Naeem Elkhawaga | L19: 01111879328 | M19: aya.elkhawaga@themarq.com.eg | N19: HR Business Partner | O19: HR Business Partner Supervisor | P19: TM4-32448 | Q19: 46112 | R19: Internal | S19: Human Resources | W19: Island of Seacrets-(Finance Dept) | X19: 11
A20: 19 | C20: Public Calender | F20: Parenting 101 | G20: Aya Sameh | I20: 4 | K20: Gehad Badr El Sayed Bayoumi | L20: 01277237484 | M20: gehad.badr@themarq.com.eg | N20: Accounts Receivable | O20: Accounts Receivable Supervisor | P20: TM4-8010 | Q20: 46112 | R20: Internal | S20: Finance | W20: LinkedIn Learning Kick-Off Session | X20: 16
A21: 20 | C21: Public Calender | F21: Parenting 101 | G21: Aya Sameh | I21: 4 | K21: Mohamed Mabrouk Ismail Mohamed | L21: 01099262847 | M21: mohamed.mabrouk@themarq.com.eg | N21: Accounts Receivable | O21: Associate Accounts Receivable Manager | P21: TM4-8006 | Q21: 46112 | R21: Internal | S21: Finance | W21: Master The Shift | X21: 17
A22: 21 | C22: Public Calender | F22: Parenting 101 | G22: Aya Sameh | I22: 4 | K22: Diana Hossam Abdelrahman Osman | L22: 01117139927 | M22: diana.elsehemy@themarq.com.eg | N22: Design Management | O22: Design Management Section Head | P22: TM4-19302 | Q22: 46112 | R22: Internal | S22: Development & Innovation | W22: Parenting 101 | X22: 9
A23: 22 | C23: Public Calender | F23: Parenting 101 | G23: Aya Sameh | I23: 4 | K23: Shereen walaa mohamed askar | L23: 01008039820 | M23: shereen.walaa@themarq.com.eg | N23: Architecture | O23: Architecture Design Review Section Head | P23: TM4-27126 | Q23: 46112 | R23: Internal | S23: Development & Innovation | W23: Presentation Skills-HS | X23: 7
A24: 23 | C24: Public Calender | F24: Parenting 101 | G24: Aya Sameh | I24: 4 | K24: Ahmed Gamal Mostafa Kamel | L24: 01102078925 | M24: ahmed.gamal@themarq.com.eg | N24: MEP | O24: MEP Design Review Section Head | P24: TM4-31608 | Q24: 46112 | R24: Internal | S24: Development & Innovation | W24: Sales Skills 1-HS | X24: 9
A25: 24 | C25: Public Calender | F25: Parenting 101 | G25: Aya Sameh | I25: 4 | K25: Mohamed Adel mohamed khader | L25: 01007764944 | M25: mohamed.khafaga@themarq.com.eg | N25: Call Center | O25: Communication Center Manager | P25: TM4-22654 | Q25: 46112 | R25: Internal | S25: Communities & Clients Excellence | W25: Sales Skills 2-HS | X25: 9
A26: 25 | C26: Public Calender | F26: Parenting 101 | G26: Aya Sameh | I26: 4 | K26: Nourhan yasser Hamed Elmoaz | L26: 01000461636 | M26: nourhan.yasser@themarq.com.eg | N26: Business Development | O26: Business Development Supervisor | P26: TM4-12569 | Q26: 46112 | R26: Internal | S26: Commercial | W26: Self Discovery Lab | X26: 8
A27: 26 | C27: Public Calender | F27: Parenting 101 | G27: Aya Sameh | I27: 4 | K27: MennatAllah Yahya Mohamed Tawfik Ahmed Abdul Aziz | L27: 01005397775 | M27: menna.yahya@themarq.com.eg | N27: Business Development | O27: Business Development Director | P27: TM4-15460 | Q27: 46112 | R27: Internal | S27: Commercial | W27: Slide Design | X27: 2
A28: 27 | B28: 12 | C28: Customised | D28: Customised | E28: Sales | F28: Goal Setting &Building Habits -HS | G28: Amr Alaa | H28: 5 | I28: 5 | J28: 1 | K28: Abdelaziz Youssef Abo El Wafa Mohamed | L28: 1023388233 | M28: abdelaziz.youssef@themarq.com.eg | N28: Sales | O28: Senior Property Consultant | P28: TM4-2456 | Q28: 46061 | R28: Internal | S28: Commercial | W28: Story Craft | X28: 17
A29: 28 | C29: Customised | F29: Goal Setting &Building Habits -HS | G29: Amr Alaa | I29: 5 | K29: Ahmed Khaled Kamal Ibrahim | L29: 1027108060 | M29: ahmed.kamal@themarq.com.eg | N29: Sales | O29: Senior Property Consultant | P29: TM4-14995 | Q29: 46061 | R29: Internal | S29: Commercial | W29: The Connected Leader | X29: 38
A30: 29 | C30: Customised | F30: Goal Setting &Building Habits -HS | G30: Amr Alaa | I30: 5 | K30: Ahmed Saber Abdelrady Mohamed | L30: 1005406501 | M30: ahmed.saber@themarq.com.eg | N30: Sales | O30: Senior Property Consultant | P30: N/A | Q30: 46061 | R30: Internal | S30: Commercial | W30: The Influence Map | X30: 35
A31: 30 | C31: Customised | F31: Goal Setting &Building Habits -HS | G31: Amr Alaa | I31: 5 | K31: Ahmed Samir Galal Elelemy Ahmed | L31: 1118099906 | M31: ahmed.jalal@themarq.com.eg | N31: Sales | O31: Property Consultant | P31: N/A | Q31: 46061 | R31: Internal | S31: Commercial | W31: The Influence Map (Projects) | X31: 40
A32: 31 | C32: Customised | F32: Goal Setting &Building Habits -HS | G32: Amr Alaa | I32: 5 | K32: Amr Ali Mahmoud Elhanbaly | L32: 1007939202 | M32: amr.elhanbaly@themarq.com.eg | N32: Sales | O32: Sales Supervisor | P32: N/A | Q32: 46061 | R32: Internal | S32: Commercial | W32: Think Human | X32: 3
A33: 32 | C33: Customised | F33: Goal Setting &Building Habits -HS | G33: Amr Alaa | I33: 5 | K33: Amr Hussein Hassan Mohamed Ali | L33: 1008910521 | M33: amr.hussien@themarq.com.eg | N33: Sales | O33: Sales Supervisor | P33: N/A | Q33: 46061 | R33: Internal | S33: Commercial | W33: Time &Self Management -HS | X33: 6
A34: 33 | C34: Customised | F34: Goal Setting &Building Habits -HS | G34: Amr Alaa | I34: 5 | K34: Tarnem Mohamed Mohamed El sherbini | L34: 1027390399 | M34: Tarneem.mohamed@themarq.com.eg | N34: Sales | O34: Sales Supervisor | P34: N/A | Q34: 46061 | R34: Internal | S34: Commercial | W34: Grand Total | X34: 415
A35: 34 | C35: Customised | F35: Goal Setting &Building Habits -HS | G35: Amr Alaa | I35: 5 | K35: Mahmoud Walid | L35: 1200028027 | M35: New Hire | N35: Sales | O35: Property Consultant | P35: N/A | Q35: 46061 | R35: Internal | S35: Commercial
A36: 35 | C36: Customised | F36: Goal Setting &Building Habits -HS | G36: Amr Alaa | I36: 5 | K36: Passant El Ghandour | L36: 1092254432 | M36: New Hire | N36: Sales | O36: Senior Property Consultant | P36: N/A | Q36: 46061 | R36: Internal | S36: Commercial
A37: 36 | B37: 12 | C37: Customised | D37: Customised | E37: Sales | F37: Sales Skills 1-HS | G37: Amr Alaa | H37: 5 | I37: 5 | J37: 1 | K37: Abdelaziz Youssef Abo El Wafa Mohamed | L37: 1023388233 | M37: abdelaziz.youssef@themarq.com.eg | N37: Sales | O37: Senior Property Consultant | P37: N/A | Q37: 46062 | R37: Internal | S37: Commercial
A38: 37 | C38: Customised | F38: Sales Skills 1-HS | G38: Amr Alaa | I38: 5 | K38: Ahmed Khaled Kamal Ibrahim | L38: 1027108060 | M38: ahmed.kamal@themarq.com.eg | N38: Sales | O38: Senior Property Consultant | P38: N/A | Q38: 46062 | R38: Internal | S38: Commercial
A39: 38 | C39: Customised | F39: Sales Skills 1-HS | G39: Amr Alaa | I39: 5 | K39: Ahmed Saber Abdelrady Mohamed | L39: 1005406501 | M39: ahmed.saber@themarq.com.eg | N39: Sales | O39: Senior Property Consultant | P39: N/A | Q39: 46062 | R39: Internal | S39: Commercial
A40: 39 | C40: Customised | F40: Sales Skills 1-HS | G40: Amr Alaa | I40: 5 | K40: Ahmed Samir Galal Elelemy Ahmed | L40: 1118099906 | M40: ahmed.jalal@themarq.com.eg | N40: Sales | O40: Property Consultant | P40: N/A | Q40: 46062 | R40: Internal | S40: Commercial
A41: 40 | C41: Customised | F41: Sales Skills 1-HS | G41: Amr Alaa | I41: 5 | K41: Amira Tarek Mohamed Abdelmutaal Ali El Sherkawy | L41: 1005353396 | M41: amira.tareq@themarq.com.eg | N41: Sales | O41: Senior Property Consultant | P41: N/A | Q41: 46062 | R41: Internal | S41: Commercial
A42: 41 | C42: Customised | F42: Sales Skills 1-HS | G42: Amr Alaa | I42: 5 | K42: Amr Ali Mahmoud Elhanbaly | L42: 1007939202 | M42: amr.elhanbaly@themarq.com.eg | N42: Sales | O42: Sales Supervisor | P42: N/A | Q42: 46062 | R42: Internal | S42: Commercial
A43: 42 | C43: Customised | F43: Sales Skills 1-HS | G43: Amr Alaa | I43: 5 | K43: Tarnem Mohamed Mohamed El sherbini | L43: 1027390399 | M43: Tarneem.mohamed@themarq.com.eg | N43: Sales | O43: Sales Supervisor | P43: N/A | Q43: 46062 | R43: Internal | S43: Commercial
A44: 43 | C44: Customised | F44: Sales Skills 1-HS | G44: Amr Alaa | I44: 5 | K44: Mahmoud Walid | L44: 1200028027 | M44: New Hire | N44: Sales | O44: Property Consultant | P44: N/A | Q44: 46062 | R44: Internal | S44: Commercial
A45: 44 | C45: Customised | F45: Sales Skills 1-HS | G45: Amr Alaa | I45: 5 | K45: Passant El Ghandour | L45: 1092254432 | M45: New Hire | N45: Sales | O45: Senior Property Consultant | P45: N/A | Q45: 46062 | R45: Internal | S45: Commercial
A46: 45 | B46: 12 | C46: Customised | D46: Customised | E46: Sales | F46: Sales Skills 2-HS | G46: Amr Alaa | H46: 5 | I46: 5 | J46: 1 | K46: Abdelaziz Youssef Abo El Wafa Mohamed | L46: 1023388233 | M46: abdelaziz.youssef@themarq.com.eg | N46: Sales | O46: Senior Property Consultant | P46: N/A | Q46: 46063 | R46: Internal | S46: Commercial
A47: 46 | C47: Customised | F47: Sales Skills 2-HS | G47: Amr Alaa | I47: 5 | K47: Ahmed Khaled Kamal Ibrahim | L47: 1027108060 | M47: ahmed.kamal@themarq.com.eg | N47: Sales | O47: Senior Property Consultant | P47: N/A | Q47: 46063 | R47: Internal | S47: Commercial
A48: 47 | C48: Customised | F48: Sales Skills 2-HS | G48: Amr Alaa | I48: 5 | K48: Ahmed Saber Abdelrady Mohamed | L48: 1005406501 | M48: ahmed.saber@themarq.com.eg | N48: Sales | O48: Senior Property Consultant | P48: N/A | Q48: 46063 | R48: Internal | S48: Commercial
A49: 48 | C49: Customised | F49: Sales Skills 2-HS | G49: Amr Alaa | I49: 5 | K49: Ahmed Samir Galal Elelemy Ahmed | L49: 1118099906 | M49: ahmed.jalal@themarq.com.eg | N49: Sales | O49: Property Consultant | P49: N/A | Q49: 46063 | R49: Internal | S49: Commercial
A50: 49 | C50: Customised | F50: Sales Skills 2-HS | G50: Amr Alaa | I50: 5 | K50: Amr Ali Mahmoud Elhanbaly | L50: 1007939202 | M50: amr.elhanbaly@themarq.com.eg | N50: Sales | O50: Sales Supervisor | P50: N/A | Q50: 46063 | R50: Internal | S50: Commercial
A51: 50 | C51: Customised | F51: Sales Skills 2-HS | G51: Amr Alaa | I51: 5 | K51: Mahmoud Walid | L51: 1200028027 | M51: New Hire | N51: Sales | O51: Property Consultant | P51: N/A | Q51: 46063 | R51: Internal | S51: Commercial
A52: 51 | C52: Customised | F52: Sales Skills 2-HS | G52: Amr Alaa | I52: 5 | K52: Passant El Ghandour | L52: 1092254432 | M52: New Hire | N52: Sales | O52: Senior Property Consultant | P52: N/A | Q52: 46063 | R52: Internal | S52: Commercial
A53: 52 | C53: Customised | F53: Sales Skills 2-HS | G53: Amr Alaa | I53: 5 | K53: Marwan Yackout | L53: 1142056756 | M53: New Hire | N53: Sales | O53: Senior Property Consultant | P53: N/A | Q53: 46063 | R53: Internal | S53: Commercial
A54: 53 | C54: Customised | F54: Sales Skills 2-HS | G54: Amr Alaa | I54: 5 | K54: Ahmed Abdel Hakim | L54: N/A | M54: New Hire | N54: Sales | O54: #REF! | P54: N/A | Q54: 46063 | R54: Internal | S54: Commercial
A55: 54 | B55: 12 | C55: Customised | D55: Customised | E55: Sales | F55: Time &Self Management -HS | G55: Amr Alaa | H55: 5 | I55: 5 | J55: 1 | K55: Ahmed Samir Galal Elelemy Ahmed | L55: 1118099906 | M55: ahmed.jalal@themarq.com.eg | N55: Sales | O55: Property Consultant | P55: N/A | Q55: 46070 | R55: Internal | S55: Commercial
A56: 55 | C56: Customised | F56: Time &Self Management -HS | G56: Amr Alaa | I56: 5 | K56: Amira Tarek Mohamed Abdelmutaal Ali El Sherkawy | L56: 1005353396 | M56: amira.tareq@themarq.com.eg | N56: Sales | O56: Senior Property Consultant | P56: N/A | Q56: 46070 | R56: Internal | S56: Commercial
A57: 56 | C57: Customised | F57: Time &Self Management -HS | G57: Amr Alaa | I57: 5 | K57: Amr Ali Mahmoud Elhanbaly | L57: 1007939202 | M57: amr.elhanbaly@themarq.com.eg | N57: Sales | O57: Sales Supervisor | P57: N/A | Q57: 46070 | R57: Internal | S57: Commercial
A58: 57 | C58: Customised | F58: Time &Self Management -HS | G58: Amr Alaa | I58: 5 | K58: Mahmoud Walid | L58: 1200028027 | M58: New Hire | N58: Sales | O58: Property Consultant | P58: N/A | Q58: 46070 | R58: Internal | S58: Commercial
A59: 58 | C59: Customised | F59: Time &Self Management -HS | G59: Amr Alaa | I59: 5 | K59: Passant El Ghandour | L59: 1092254432 | M59: New Hire | N59: Sales | O59: Senior Property Consultant | P59: N/A | Q59: 46070 | R59: Internal | S59: Commercial
A60: 59 | C60: Customised | F60: Time &Self Management -HS | G60: Amr Alaa | I60: 5 | K60: Marwan Yackout | L60: 1142056756 | M60: New Hire | N60: Sales | O60: Senior Property Consultant | P60: N/A | Q60: 46070 | R60: Internal | S60: Commercial
A61: 60 | B61: 12 | C61: Customised | D61: Customised | E61: Sales | F61: Presentation Skills-HS | G61: Aya Sameh | H61: 5 | I61: 5 | J61: 1 | K61: Ahmed Saber Abdelrady Mohamed | L61: 1005406501 | M61: ahmed.saber@themarq.com.eg | N61: Sales | O61: Senior Property Consultant | P61: N/A | Q61: 46071 | R61: Internal | S61: Commercial
A62: 61 | C62: Customised | F62: Presentation Skills-HS | G62: Aya Sameh | I62: 5 | K62: Ahmed Samir Galal Elelemy Ahmed | L62: 1118099906 | M62: ahmed.jalal@themarq.com.eg | N62: Sales | O62: Property Consultant | P62: N/A | Q62: 46071 | R62: Internal | S62: Commercial
A63: 62 | C63: Customised | F63: Presentation Skills-HS | G63: Aya Sameh | I63: 5 | K63: Amira Tarek Mohamed Abdelmutaal Ali El Sherkawy | L63: 1005353396 | M63: amira.tareq@themarq.com.eg | N63: Sales | O63: Senior Property Consultant | P63: N/A | Q63: 46071 | R63: Internal | S63: Commercial
A64: 63 | C64: Customised | F64: Presentation Skills-HS | G64: Aya Sameh | I64: 5 | K64: Amr Ali Mahmoud Elhanbaly | L64: 1007939202 | M64: amr.elhanbaly@themarq.com.eg | N64: Sales | O64: Sales Supervisor | P64: N/A | Q64: 46071 | R64: Internal | S64: Commercial
A65: 64 | C65: Customised | F65: Presentation Skills-HS | G65: Aya Sameh | I65: 5 | K65: Mahmoud Walid | L65: 1200028027 | M65: New Hire | N65: Sales | O65: Property Consultant | P65: N/A | Q65: 46071 | R65: Internal | S65: Commercial
A66: 65 | C66: Customised | F66: Presentation Skills-HS | G66: Aya Sameh | I66: 5 | K66: Passant El Ghandour | L66: 1092254432 | M66: New Hire | N66: Sales | O66: Senior Property Consultant | P66: N/A | Q66: 46071 | R66: Internal | S66: Commercial
A67: 66 | C67: Customised | F67: Presentation Skills-HS | G67: Aya Sameh | I67: 5 | K67: Marwan Yackout | L67: 1142056756 | M67: New Hire | N67: Sales | O67: Senior Property Consultant | P67: N/A | Q67: 46071 | R67: Internal | S67: Commercial
A68: 78 | B68: 23 | C68: Public Calender | D68: Public Calender | F68: LinkedIn Learning Kick-Off Session | G68: Amr Alaa | H68: 1 | I68: 1 | J68: 1 | K68: eslam fathy abdelhamid mohamed | L68: 1090348691 | M68: eslam.fathyy@themarq.com.eg | N68: Accounts Receivable | O68: Accounts Receivable Supervisor | P68: TM4-16864 | Q68: 46121 | R68: Internal | S68: Finance
A69: 79 | C69: Public Calender | F69: LinkedIn Learning Kick-Off Session | G69: Amr Alaa | I69: 1 | K69: Ahmed Shawky Abdo El Bastawisy El Sahy | L69: 1228776636 | M69: ahmed.elsahy@themarq.com.eg | N69: Sales | O69: Senior Sales Manager | P69: TM4-28515 | Q69: 46121 | R69: Internal | S69: Commercial
A70: 80 | C70: Public Calender | F70: LinkedIn Learning Kick-Off Session | G70: Amr Alaa | I70: 1 | K70: Farouk Mohamed Farouk Soliman | L70: 1119755538 | M70: farouk.soliman@themarq.com.eg | N70: Sales | O70: Senior Property Consultant | P70: TM4-31899 | Q70: 46121 | R70: Internal | S70: Commercial
A71: 81 | C71: Public Calender | F71: LinkedIn Learning Kick-Off Session | G71: Amr Alaa | I71: 1 | K71: Mohamed Mabrouk Ismail Mohamed | L71: 1099262847 | M71: mohamed.mabrouk@themarq.com.eg | N71: Accounts Receivable | O71: Associate Accounts Receivable Manager | P71: TM4-8006 | Q71: 46121 | R71: Internal | S71: Finance
A72: 82 | C72: Public Calender | F72: LinkedIn Learning Kick-Off Session | G72: Amr Alaa | I72: 1 | K72: Ahmed Samir Galal Elelemy Ahmed | L72: 1118099906 | M72: ahmed.jalal@themarq.com.eg | N72: Sales | O72: Property Consultant | P72: TM4-32315 | Q72: 46121 | R72: Internal | S72: Commercial
A73: 83 | C73: Public Calender | F73: LinkedIn Learning Kick-Off Session | G73: Amr Alaa | I73: 1 | K73: Hany Refaat Abdallah Mohamed | L73: 1156170952 | M73: hany.refaat@themarq.com.eg | N73: Accounts Receivable | O73: Accounts Receivable Teamleader | P73: TM4-11403 | Q73: 46121 | R73: Internal | S73: Finance
A74: 84 | C74: Public Calender | F74: LinkedIn Learning Kick-Off Session | G74: Amr Alaa | I74: 1 | K74: Mahmoud Alaa Eldin Elsayed Abdelmaged | L74: 1147760466 | M74: mahmoud.alaa@themarq.com.eg | N74: Accounts Payable | O74: Accounts Payable Teamleader | P74: TM4-26340 | Q74: 46121 | R74: Internal | S74: Finance
A75: 85 | C75: Public Calender | F75: LinkedIn Learning Kick-Off Session | G75: Amr Alaa | I75: 1 | K75: Ahmed Mohamed Gamal Mohamed Mohamed Youssef Elbehery | L75: 1111229326 | M75: ahmed.elbehery@themarq.com.eg | N75: Accounts Payable | O75: Accounts Payable Teamleader | P75: TM4-29847 | Q75: 46121 | R75: Internal | S75: Finance
A76: 86 | C76: Public Calender | F76: LinkedIn Learning Kick-Off Session | G76: Amr Alaa | I76: 1 | K76: Sondos Abdelaziz Mohamed Abdelaziz | L76: 1100797081 | M76: sondos.abdelaziz@themarq.com.eg | N76: Graphic Design | O76: Senior Graphic designer | P76: TM4-20303 | Q76: 46121 | R76: Internal | S76: Marketing & PR
A77: 87 | C77: Public Calender | F77: LinkedIn Learning Kick-Off Session | G77: Amr Alaa | I77: 1 | K77: Ahmed kamal El Din Hassan El Khateeb | L77: 1110005077 | M77: Tarneem.mohamed@themarq.com.eg | N77: Sales | O77: Associate Sales Manager | P77: TM4-3227 | Q77: 46121 | R77: Internal | S77: Commercial
A78: 88 | C78: Public Calender | F78: LinkedIn Learning Kick-Off Session | G78: Amr Alaa | I78: 1 | K78: Omar Amr Mohamed Adel | L78: 1140535256 | M78: omar.amr@themarq.com.eg | N78: Sales | O78: Sales Supervisor | P78: TM4-10185 | Q78: 46121 | R78: Internal | S78: Commercial
A79: 89 | C79: Public Calender | F79: LinkedIn Learning Kick-Off Session | G79: Amr Alaa | I79: 1 | K79: Nourhan yasser Hamed Elmoaz | L79: 1000461636 | M79: nourhan.yasser@themarq.com.eg | N79: Business Development | O79: Business Development Supervisor | P79: TM4-12569 | Q79: 46121 | R79: Internal | S79: Commercial
A80: 90 | C80: Public Calender | F80: LinkedIn Learning Kick-Off Session | G80: Amr Alaa | I80: 1 | K80: Mahmoud Gamal Mahmoud Aboulila | L80: 1125565819 | M80: mahmoud.abulila@themarq.com.eg | N80: General | O80: Accounting Teamleader | P80: TM4-29016 | Q80: 46121 | R80: Internal | S80: Finance
... A83: 93 | C83: Public Calender | F83: LinkedIn Learning Kick-Off Session | G83: Amr Alaa | I83: 1 | K83: heba ashraf youssef ibrahim | L83: 1204105555 | M83: heba.ashraf@themarq.com.eg | N83: Brand Strategy | O83: Senior Marketing Specialist | P83: TM4-16641 | Q83: 46121 | R83: Internal | S83: Marketing & PR
A84: 94 | B84: 13 | C84: Public Calender | D84: Public Calender | F84: Master The Shift | G84: Aya Sameh | H84: 4.5 | I84: 4.5 | J84: 2 | K84: Nour Eldin Fathy Mohamed Khaky | L84: 1029867676 | M84: nour.fathy@themarq.com.eg | N84: Urban | O84: Associate Urban Design Manager | P84: TM4-13328 | Q84: 46133 | R84: Internal | S84: Development & Innovation
A85: 95 | C85: Public Calender | F85: Master The Shift | G85: Aya Sameh | I85: 4.5 | K85: Youssef Ehab Kamal AbdelHady Ahmed | L85: 1094298431 | M85: youssef.eldairy@themarq.com.eg | N85: Design Management | O85: Senior Design Management Engineer | P85: TM4-3009 | Q85: 46133 | R85: Internal | S85: Development & Innovation
A86: 96 | C86: Public Calender | F86: Master The Shift | G86: Aya Sameh | I86: 4.5 | K86: Alaa Essam Mohamed Ibrahim | L86: 1117559150 | M86: alaa.omar@themarq.com.eg | N86: Urban | O86: Urban Design Teamleader | P86: TM4-11401 | Q86: 46133 | R86: Internal | S86: Development & Innovation
A87: 97 | C87: Public Calender | F87: Master The Shift | G87: Aya Sameh | I87: 4.5 | K87: Amr Hani Mohamed Abdel Latif | L87: 1062540976 | M87: amr.hany@themarq.com.eg | N87: Design Management | O87: Senior Design Management Manager | P87: TM4-8016 | Q87: 46133 | R87: Internal | S87: Development & Innovation
A88: 98 | C88: Public Calender | F88: Master The Shift | G88: Aya Sameh | I88: 4.5 | K88: Shereen walaa mohamed askar | L88: 1008039820 | M88: shereen.walaa@themarq.com.eg | N88: Design Management | O88: Design Management Section Head | P88: TM4-27126 | Q88: 46133 | R88: Internal | S88: Development & Innovation
A89: 99 | C89: Public Calender | F89: Master The Shift | G89: Aya Sameh | I89: 4.5 | K89: Diana Hossam Abdelrahman Osman | L89: 1117139927 | M89: diana.elsehemy@themarq.com.eg | N89: Design Management | O89: Design Management Section Head | P89: TM4-19302 | Q89: 46133 | R89: Internal | S89: Development & Innovation
A90: 100 | C90: Public Calender | F90: Master The Shift | G90: Aya Sameh | I90: 4.5 | K90: Ahmed Gamal Mostafa Kamel | L90: 1102078925 | M90: ahmed.gamal@themarq.com.eg | N90: MEP | O90: MEP Design Section Head | P90: TM4-31608 | Q90: 46133 | R90: Internal | S90: Development & Innovation
A91: 101 | C91: Public Calender | F91: Master The Shift | G91: Aya Sameh | I91: 4.5 | K91: Nourhan yasser Hamed Elmoaz | L91: 1000461636 | M91: nourhan.yasser@themarq.com.eg | N91: Business Development | O91: Business Development Supervisor | P91: TM4-12569 | Q91: 46133 | R91: Internal | S91: Commercial
A92: 102 | C92: Public Calender | F92: Master The Shift | G92: Aya Sameh | I92: 4.5 | K92: Hany Refaat Abdallah Mohamed | L92: 1156170952 | M92: hany.refaat@themarq.com.eg | N92: Accounts Receivable | O92: Accounts Receivable Teamleader | P92: TM4-11403 | Q92: 46133 | R92: Internal | S92: Finance
A93: 103 | C93: Public Calender | F93: Master The Shift | G93: Aya Sameh | I93: 4.5 | K93: Amr Ali Abdelwahab Sobh | L93: 1092832193 | M93: amr.ali@themarq.com.eg | N93: Urban | O93: Urban Design Section Head | P93: TM4-8047 | Q93: 46133 | R93: Internal | S93: Development & Innovation
A94: 104 | C94: Public Calender | F94: Master The Shift | G94: Aya Sameh | I94: 4.5 | K94: Diana Hossam Abdelrahman Osman | L94: 1117139927 | M94: diana.elsehemy@themarq.com.eg | N94: Design Management | O94: Design Management Section Head | P94: TM4-19302 | Q94: 46133 | R94: Internal | S94: Development & Innovation
A95: 105 | C95: Public Calender | F95: Master The Shift | G95: Aya Sameh | I95: 4.5 | K95: Youssef Ehab Kamal AbdelHady Ahmed | L95: 1094298431 | M95: youssef.eldairy@themarq.com.eg | N95: Design Management | O95: Senior Design Management Engineer | P95: TM4-3009 | Q95: 46133 | R95: Internal | S95: Development & Innovation
A96: 106 | C96: Public Calender | F96: Master The Shift | G96: Aya Sameh | I96: 4.5 | K96: Nour Eldin Fathy Mohamed Khaky | L96: 1029867676 | M96: nour.fathy@themarq.com.eg | N96: Urban | O96: Associate Urban Design Manager | P96: TM4-13328 | Q96: 46133 | R96: Internal | S96: Development & Innovation
... A100: 110 | C100: Public Calender | F100: Master The Shift | G100: Aya Sameh | I100: 4.5 | K100: Nourhan yasser Hamed Elmoaz | L100: 1000461636 | M100: Tarneem.mohamed@themarq.com.eg | N100: Business Development | O100: Business Development Supervisor | P100: TM4-12569 | Q100: 46133 | R100: Internal | S100: Commercial
A101: 126 | B101: 25 | C101: Customised | D101: Customised | E101: Finance | F101: The Influence Map | G101: Ahmed Elshiaty | H101: 3 | I101: 3 | J101: 2 | K101: Mohanad Tamer Hussein Elsayed Ibrahim | L101: 1124339090 | M101: mohanad.tamer@themarq.com.eg | N101: Financial Planning & Analysis | O101: Senior FP&A Analyst | P101: TM4-32929 | Q101: 46153 | R101: Internal | S101: Finance
A102: 126 | C102: Customised | F102: The Influence Map | G102: Ahmed Elshiaty | I102: 3 | K102: Mosaad Abd El hameed Mohamed Abd elhameed | L102: 1222750776 | M102: mosaad.abdelhameed@themarq.com.eg | N102: Accounting | O102: Accounting Director | P102: TM4-24634 | Q102: 46153 | R102: Internal | S102: Finance
A103: 126 | C103: Customised | F103: The Influence Map | G103: Ahmed Elshiaty | I103: 3 | K103: Mohamed Mabrouk Ismail Mohamed | L103: 1099262847 | M103: mohamed.mabrouk@themarq.com.eg | N103: Accounts Receivable | O103: Associate Accounts Receivable Manager | P103: TM4-8006 | Q103: 46153 | R103: Internal | S103: Finance
A104: 126 | C104: Customised | F104: The Influence Map | G104: Ahmed Elshiaty | I104: 3 | K104: Khadija Mohamed Ahmed Zayed | L104: 1099170090 | M104: khadija.zayed@themarq.com.eg | N104: Call Center | O104: Communication Center Representative | P104: TM4-31843 | Q104: 46153 | R104: Internal | S104: Communities & Clients Excellence
A105: 126 | C105: Customised | F105: The Influence Map | G105: Ahmed Elshiaty | I105: 3 | K105: eslam fathy abdelhamid mohamed | L105: 1090348691 | M105: eslam.fathyy@themarq.com.eg | N105: Accounts Receivable | O105: Accounts Receivable Supervisor | P105: TM4-16864 | Q105: 46153 | R105: Internal | S105: Finance
...

Sheet Sheet2

Sheet Evaluation Master Sheet
A1: Survey ID | B1: Start Time | C1: Completion Time | D1: Name | E1: Email | F1: Phone Number | G1: Topic Name | H1: Trainers | I1: Q1 - How relevant was the knowledge you gained throughout the training? | J1: Q2 - How effective were the learning activities used in this training? | K1: Q3 - How effective were the logistics (handouts, room, food, etc.) used in the training? | L1: Q4 - How would you rate the facilitator's overall performance? | M1: Q5 - How likely are you to recommend this training to a friend or teammate? | N1: Q6 - Mention any comments or suggestions to improve the overall learning experience | O1: PROMOTOR | P1: PASSIVE 1 | Q1: PASSIVE | R1: DETRACTOR | S1: Total Reponses | T1: NPS | U1: FACILITATOR PERFORMANCE | V1: ACTIVITY EFFECTIVNESS | W1: LOGISTICS EFFECTIVNESS | X1: KNOWLEDGE RELVEANCE
A2: 2 | B2: 46076.5 | C2: 46077.583 | D2: Mariam Ibrahim Mohamed Ibrahim | E2: mariam.ibrahim@themarq.com.eg | F2: 1007512970 | G2: Self Discovery Lab | H2: Ahmed Magdi | I2: 5 | J2: 5 | K2: 5 | L2: 5 | M2: 10 | O2: =IF(M2>=9,1,0) -> 1 | P2: =IF(M2>=7,1,0) -> 1 | Q2: =P2-O2 -> 0 | R2: =IF(M2<=6,1,0) -> 0 | S2: =O2+Q2+R2 -> 1 | T2: =((O2-R2)/S2) -> 1 | U2: =IF(L2>=4,1,0) -> 1 | V2: =IF(J2>=4,1,0) -> 1 | W2: =IF(K2>=4,1,0) -> 1 | X2: =IF(I2>=4,1,0) -> 1
A3: 2 | B3: 46076.5 | C3: 46077.583 | D3: Aya Khaled Naeem Elkhawaga | E3: aya.elkhawaga@themarq.com.eg | F3: 1111879328 | G3: Self Discovery Lab | H3: Ahmed Magdi | I3: 5 | J3: 5 | K3: 5 | L3: 5 | M3: 10 | O3: =IF(M3>=9,1,0) -> 1 | P3: =IF(M3>=7,1,0) -> 1 | Q3: =P3-O3 -> 0 | R3: =IF(M3<=6,1,0) -> 0 | S3: =O3+Q3+R3 -> 1 | T3: =((O3-R3)/S3) -> 1 | U3: =IF(L3>=4,1,0) -> 1 | V3: =IF(J3>=4,1,0) -> 1 | W3: =IF(K3>=4,1,0) -> 1 | X3: =IF(I3>=4,1,0) -> 1
A4: 2 | B4: 46076.5 | C4: 46077.583 | D4: Mohamed Ahmed Abdallah Ahmed Sharaf | E4: mohamed.abdullah@themarq.com.eg | F4: 1285727056 | G4: Self Discovery Lab | H4: Ahmed Magdi | I4: 5 | J4: 5 | K4: 5 | L4: 5 | M4: 10 | O4: =IF(M4>=9,1,0) -> 1 | P4: =IF(M4>=7,1,0) -> 1 | Q4: =P4-O4 -> 0 | R4: =IF(M4<=6,1,0) -> 0 | S4: =O4+Q4+R4 -> 1 | T4: =((O4-R4)/S4) -> 1 | U4: =IF(L4>=4,1,0) -> 1 | V4: =IF(J4>=4,1,0) -> 1 | W4: =IF(K4>=4,1,0) -> 1 | X4: =IF(I4>=4,1,0) -> 1
A5: 2 | B5: 46076.5 | C5: 46077.583 | D5: Eleonora Christo Paraskevas Vostanis | E5: eleonora.christo@themarq.com.eg | F5: 1001483748 | G5: Self Discovery Lab | H5: Ahmed Magdi | I5: 5 | J5: 4 | K5: 5 | L5: 5 | M5: 9 | O5: =IF(M5>=9,1,0) -> 1 | P5: =IF(M5>=7,1,0) -> 1 | Q5: =P5-O5 -> 0 | R5: =IF(M5<=6,1,0) -> 0 | S5: =O5+Q5+R5 -> 1 | T5: =((O5-R5)/S5) -> 1 | U5: =IF(L5>=4,1,0) -> 1 | V5: =IF(J5>=4,1,0) -> 1 | W5: =IF(K5>=4,1,0) -> 1 | X5: =IF(I5>=4,1,0) -> 1
A6: 2 | B6: 46097.5 | C6: 46098.583 | D6: Khadija Mohamed Ahmed Zayed | E6: khadija.zayed@themarq.com.eg | F6: 1099170090 | G6: Think Human | H6: Aya Sameh | I6: 5 | J6: 5 | K6: 5 | L6: 5 | M6: 10 | N6: nothing | O6: =IF(M6>=9,1,0) -> 1 | P6: =IF(M6>=7,1,0) -> 1 | Q6: =P6-O6 -> 0 | R6: =IF(M6<=6,1,0) -> 0 | S6: =O6+Q6+R6 -> 1 | T6: =((O6-R6)/S6) -> 1 | U6: =IF(L6>=4,1,0) -> 1 | V6: =IF(J6>=4,1,0) -> 1 | W6: =IF(K6>=4,1,0) -> 1 | X6: =IF(I6>=4,1,0) -> 1
A7: 2 | B7: 46097.5 | C7: 46098.583 | D7: Mohamed Hussein Yaqoub Mohamed | E7: mohamed.husien@themarq.com.eg | F7: 1093124080 | G7: Think Human | H7: Aya Sameh | I7: 5 | J7: 5 | K7: 5 | L7: 5 | M7: 10 | O7: =IF(M7>=9,1,0) -> 1 | P7: =IF(M7>=7,1,0) -> 1 | Q7: =P7-O7 -> 0 | R7: =IF(M7<=6,1,0) -> 0 | S7: =O7+Q7+R7 -> 1 | T7: =((O7-R7)/S7) -> 1 | U7: =IF(L7>=4,1,0) -> 1 | V7: =IF(J7>=4,1,0) -> 1 | W7: =IF(K7>=4,1,0) -> 1 | X7: =IF(I7>=4,1,0) -> 1
A8: 2 | B8: 46097.5 | C8: 46098.583 | D8: MennatAllah Yahya Mohamed Tawfik Ahmed Abdul Aziz | E8: menna.yahya@themarq.com.eg | F8: 1005397775 | G8: Think Human | H8: Aya Sameh | I8: 5 | J8: 5 | K8: 5 | L8: 5 | M8: 10 | N8: Extending the duration would allow for better coverage and understanding. | O8: =IF(M8>=9,1,0) -> 1 | P8: =IF(M8>=7,1,0) -> 1 | Q8: =P8-O8 -> 0 | R8: =IF(M8<=6,1,0) -> 0 | S8: =O8+Q8+R8 -> 1 | T8: =((O8-R8)/S8) -> 1 | U8: =IF(L8>=4,1,0) -> 1 | V8: =IF(J8>=4,1,0) -> 1 | W8: =IF(K8>=4,1,0) -> 1 | X8: =IF(I8>=4,1,0) -> 1
A9: 2 | B9: 46097.5 | C9: 46098.583 | D9: Mohamed Mabrouk Ismail Mohamed | E9: mohamed.mabrouk@themarq.com.eg | F9: 1099262847 | G9: Think Human | H9: Aya Sameh | I9: 5 | J9: 5 | K9: 5 | L9: 5 | M9: 10 | O9: =IF(M9>=9,1,0) -> 1 | P9: =IF(M9>=7,1,0) -> 1 | Q9: =P9-O9 -> 0 | R9: =IF(M9<=6,1,0) -> 0 | S9: =O9+Q9+R9 -> 1 | T9: =((O9-R9)/S9) -> 1 | U9: =IF(L9>=4,1,0) -> 1 | V9: =IF(J9>=4,1,0) -> 1 | W9: =IF(K9>=4,1,0) -> 1 | X9: =IF(I9>=4,1,0) -> 1
A10: 2 | B10: 46112.5 | C10: 46112.625 | D10: MennatAllah Yahya Mohamed Tawfik Ahmed Abdul Aziz | E10: menna.yahya@themarq.com.eg | F10: 1005397775 | G10: Parenting 101 | H10: Aya Sameh | I10: 5 | J10: 5 | K10: 5 | L10: 5 | M10: 10 | O10: =IF(M10>=9,1,0) -> 1 | P10: =IF(M10>=7,1,0) -> 1 | Q10: =P10-O10 -> 0 | R10: =IF(M10<=6,1,0) -> 0 | S10: =O10+Q10+R10 -> 1 | T10: =((O10-R10)/S10) -> 1 | U10: =IF(L10>=4,1,0) -> 1 | V10: =IF(J10>=4,1,0) -> 1 | W10: =IF(K10>=4,1,0) -> 1 | X10: =IF(I10>=4,1,0) -> 1
A11: 2 | B11: 46112.5 | C11: 46112.625 | D11: Gehad Badr El Sayed Bayoumi | E11: gehad.badr@themarq.com.eg | F11: 1277237484 | G11: Parenting 101 | H11: Aya Sameh | I11: 5 | J11: 5 | K11: 5 | L11: 5 | M11: 10 | O11: =IF(M11>=9,1,0) -> 1 | P11: =IF(M11>=7,1,0) -> 1 | Q11: =P11-O11 -> 0 | R11: =IF(M11<=6,1,0) -> 0 | S11: =O11+Q11+R11 -> 1 | T11: =((O11-R11)/S11) -> 1 | U11: =IF(L11>=4,1,0) -> 1 | V11: =IF(J11>=4,1,0) -> 1 | W11: =IF(K11>=4,1,0) -> 1 | X11: =IF(I11>=4,1,0) -> 1
A12: 2 | B12: 46112.5 | C12: 46112.625 | D12: Mohamed Mabrouk Ismail Mohamed | E12: mohamed.mabrouk@themarq.com.eg | F12: 1099262847 | G12: Parenting 101 | H12: Aya Sameh | I12: 5 | J12: 5 | K12: 5 | L12: 5 | M12: 10 | N12: Excellent thanks a lot | O12: =IF(M12>=9,1,0) -> 1 | P12: =IF(M12>=7,1,0) -> 1 | Q12: =P12-O12 -> 0 | R12: =IF(M12<=6,1,0) -> 0 | S12: =O12+Q12+R12 -> 1 | T12: =((O12-R12)/S12) -> 1 | U12: =IF(L12>=4,1,0) -> 1 | V12: =IF(J12>=4,1,0) -> 1 | W12: =IF(K12>=4,1,0) -> 1 | X12: =IF(I12>=4,1,0) -> 1
A13: 2 | B13: 46112.5 | C13: 46112.625 | D13: Nourhan yasser Hamed Elmoaz | E13: nourhan.yasser@themarq.com.eg | F13: 1000461636 | G13: Parenting 101 | H13: Aya Sameh | I13: 5 | J13: 5 | K13: 5 | L13: 5 | M13: 10 | O13: =IF(M13>=9,1,0) -> 1 | P13: =IF(M13>=7,1,0) -> 1 | Q13: =P13-O13 -> 0 | R13: =IF(M13<=6,1,0) -> 0 | S13: =O13+Q13+R13 -> 1 | T13: =((O13-R13)/S13) -> 1 | U13: =IF(L13>=4,1,0) -> 1 | V13: =IF(J13>=4,1,0) -> 1 | W13: =IF(K13>=4,1,0) -> 1 | X13: =IF(I13>=4,1,0) -> 1
A14: 2 | B14: 46112.5 | C14: 46112.625 | D14: Diana Hossam Abdelrahman Osman | E14: diana.elsehemy@themarq.com.eg | F14: 1117139927 | G14: Parenting 101 | H14: Aya Sameh | I14: 4 | J14: 5 | K14: 5 | L14: 5 | M14: 9 | O14: =IF(M14>=9,1,0) -> 1 | P14: =IF(M14>=7,1,0) -> 1 | Q14: =P14-O14 -> 0 | R14: =IF(M14<=6,1,0) -> 0 | S14: =O14+Q14+R14 -> 1 | T14: =((O14-R14)/S14) -> 1 | U14: =IF(L14>=4,1,0) -> 1 | V14: =IF(J14>=4,1,0) -> 1 | W14: =IF(K14>=4,1,0) -> 1 | X14: =IF(I14>=4,1,0) -> 1
A15: 2 | B15: 46112.5 | C15: 46112.625 | D15: Ahmed Gamal Mostafa Kamel | E15: ahmed.gamal@themarq.com.eg | F15: 1102078925 | G15: Parenting 101 | H15: Aya Sameh | I15: 5 | J15: 5 | K15: 5 | L15: 5 | M15: 10 | O15: =IF(M15>=9,1,0) -> 1 | P15: =IF(M15>=7,1,0) -> 1 | Q15: =P15-O15 -> 0 | R15: =IF(M15<=6,1,0) -> 0 | S15: =O15+Q15+R15 -> 1 | T15: =((O15-R15)/S15) -> 1 | U15: =IF(L15>=4,1,0) -> 1 | V15: =IF(J15>=4,1,0) -> 1 | W15: =IF(K15>=4,1,0) -> 1 | X15: =IF(I15>=4,1,0) -> 1
A16: 2 | B16: 46112.5 | C16: 46112.625 | D16: Aya Khaled Naeem Elkhawaga | E16: aya.elkhawaga@themarq.com.eg | F16: 1111879328 | G16: Parenting 101 | H16: Aya Sameh | I16: 5 | J16: 5 | K16: 5 | L16: 5 | M16: 10 | O16: =IF(M16>=9,1,0) -> 1 | P16: =IF(M16>=7,1,0) -> 1 | Q16: =P16-O16 -> 0 | R16: =IF(M16<=6,1,0) -> 0 | S16: =O16+Q16+R16 -> 1 | T16: =((O16-R16)/S16) -> 1 | U16: =IF(L16>=4,1,0) -> 1 | V16: =IF(J16>=4,1,0) -> 1 | W16: =IF(K16>=4,1,0) -> 1 | X16: =IF(I16>=4,1,0) -> 1
A17: 2 | B17: 46112.5 | C17: 46112.625 | D17: Shereen walaa mohamed askar | E17: shereen.walaa@themarq.com.eg | F17: 1008039820 | G17: Parenting 101 | H17: Aya Sameh | I17: 5 | J17: 5 | K17: 5 | L17: 5 | M17: 10 | O17: =IF(M17>=9,1,0) -> 1 | P17: =IF(M17>=7,1,0) -> 1 | Q17: =P17-O17 -> 0 | R17: =IF(M17<=6,1,0) -> 0 | S17: =O17+Q17+R17 -> 1 | T17: =((O17-R17)/S17) -> 1 | U17: =IF(L17>=4,1,0) -> 1 | V17: =IF(J17>=4,1,0) -> 1 | W17: =IF(K17>=4,1,0) -> 1 | X17: =IF(I17>=4,1,0) -> 1
A18: 2 | B18: 46133.479 | C18: 46134.583 | D18: Alaa Essam Mohamed Ibrahim | E18: alaa.omar@themarq.com.eg | F18: 1117559150 | G18: Master The Shift | H18: Aya Sameh | I18: 5 | J18: 5 | K18: 5 | L18: 5 | M18: 10 | O18: =IF(M18>=9,1,0) -> 1 | P18: =IF(M18>=7,1,0) -> 1 | Q18: =P18-O18 -> 0 | R18: =IF(M18<=6,1,0) -> 0 | S18: =O18+Q18+R18 -> 1 | T18: =((O18-R18)/S18) -> 1 | U18: =IF(L18>=4,1,0) -> 1 | V18: =IF(J18>=4,1,0) -> 1 | W18: =IF(K18>=4,1,0) -> 1 | X18: =IF(I18>=4,1,0) -> 1
A19: 2 | B19: 46133.479 | C19: 46134.583 | D19: Nour Eldin Fathy Mohamed Khaky | E19: nour.fathy@themarq.com.eg | F19: 1029867676 | G19: Master The Shift | H19: Aya Sameh | I19: 5 | J19: 5 | K19: 5 | L19: 5 | M19: 10 | O19: =IF(M19>=9,1,0) -> 1 | P19: =IF(M19>=7,1,0) -> 1 | Q19: =P19-O19 -> 0 | R19: =IF(M19<=6,1,0) -> 0 | S19: =O19+Q19+R19 -> 1 | T19: =((O19-R19)/S19) -> 1 | U19: =IF(L19>=4,1,0) -> 1 | V19: =IF(J19>=4,1,0) -> 1 | W19: =IF(K19>=4,1,0) -> 1 | X19: =IF(I19>=4,1,0) -> 1
A20: 2 | B20: 46133.479 | C20: 46134.583 | D20: Youssef Ehab Kamal AbdelHady Ahmed | E20: youssef.eldairy@themarq.com.eg | F20: 1094298431 | G20: Master The Shift | H20: Aya Sameh | I20: 5 | J20: 5 | K20: 5 | L20: 5 | M20: 10 | O20: =IF(M20>=9,1,0) -> 1 | P20: =IF(M20>=7,1,0) -> 1 | Q20: =P20-O20 -> 0 | R20: =IF(M20<=6,1,0) -> 0 | S20: =O20+Q20+R20 -> 1 | T20: =((O20-R20)/S20) -> 1 | U20: =IF(L20>=4,1,0) -> 1 | V20: =IF(J20>=4,1,0) -> 1 | W20: =IF(K20>=4,1,0) -> 1 | X20: =IF(I20>=4,1,0) -> 1
A21: 2 | B21: 46133.479 | C21: 46134.583 | D21: Ahmed Gamal Mostafa Kamel | E21: ahmed.gamal@themarq.com.eg | F21: 1102078925 | G21: Master The Shift | H21: Aya Sameh | I21: 4 | J21: 4 | K21: 4 | L21: 5 | M21: 8 | O21: =IF(M21>=9,1,0) -> 0 | P21: =IF(M21>=7,1,0) -> 1 | Q21: =P21-O21 -> 1 | R21: =IF(M21<=6,1,0) -> 0 | S21: =O21+Q21+R21 -> 1 | T21: =((O21-R21)/S21) -> 0 | U21: =IF(L21>=4,1,0) -> 1 | V21: =IF(J21>=4,1,0) -> 1 | W21: =IF(K21>=4,1,0) -> 1 | X21: =IF(I21>=4,1,0) -> 1
A22: 2 | B22: 2026-05-11 10:00:00 | C22: 2026-05-13 13:00:00 | D22: eslam fathy abdelhamid mohamed | E22: eslam.fathyy@themarq.com.eg | F22: 01090348691 | G22: The Influence Map | H22: Ahmed ElShiaty | I22: 5 | J22: 5 | K22: 5 | L22: 5 | M22: 10 | N22: nothing everything is awesome | O22: =IF(M22>=9,1,0) -> 1 | P22: =IF(M22>=7,1,0) -> 1 | Q22: =P22-O22 -> 0 | R22: =IF(M22<=6,1,0) -> 0 | S22: =O22+Q22+R22 -> 1 | T22: =((O22-R22)/S22) -> 1 | U22: =IF(L22>=4,1,0) -> 1 | V22: =IF(J22>=4,1,0) -> 1 | W22: =IF(K22>=4,1,0) -> 1 | X22: =IF(I22>=4,1,0) -> 1
A23: 2 | B23: 2026-05-11 10:00:00 | C23: 2026-05-13 13:00:00 | D23: Abdelrahman Mohamed Saad Ahmed | E23: abdelrahman.saad@themarq.com.eg | F23: 01150812762 | G23: The Influence Map | H23: Ahmed ElShiaty | I23: 4 | J23: 4 | K23: 4 | L23: 5 | M23: 8 | N23: very good | O23: =IF(M23>=9,1,0) -> 0 | P23: =IF(M23>=7,1,0) -> 1 | Q23: =P23-O23 -> 1 | R23: =IF(M23<=6,1,0) -> 0 | S23: =O23+Q23+R23 -> 1 | T23: =((O23-R23)/S23) -> 0 | U23: =IF(L23>=4,1,0) -> 1 | V23: =IF(J23>=4,1,0) -> 1 | W23: =IF(K23>=4,1,0) -> 1 | X23: =IF(I23>=4,1,0) -> 1
A24: 2 | B24: 2026-05-11 10:00:00 | C24: 2026-05-13 13:00:00 | D24: Mosaad Abd El hameed Mohamed Abd elhameed | E24: mosaad.abdelhameed@themarq.com.eg | F24: 01222750776 | G24: The Influence Map | H24: Ahmed ElShiaty | I24: 5 | J24: 5 | K24: 4 | L24: 4 | M24: 7 | O24: =IF(M24>=9,1,0) -> 0 | P24: =IF(M24>=7,1,0) -> 1 | Q24: =P24-O24 -> 1 | R24: =IF(M24<=6,1,0) -> 0 | S24: =O24+Q24+R24 -> 1 | T24: =((O24-R24)/S24) -> 0 | U24: =IF(L24>=4,1,0) -> 1 | V24: =IF(J24>=4,1,0) -> 1 | W24: =IF(K24>=4,1,0) -> 1 | X24: =IF(I24>=4,1,0) -> 1
A25: 2 | B25: 2026-05-11 10:00:00 | C25: 2026-05-13 13:00:00 | D25: Mahmoud Alaa Eldin Elsayed Abdelmaged | E25: mahmoud.alaa@themarq.com.eg | F25: 01147760466 | G25: The Influence Map | H25: Ahmed ElShiaty | I25: 5 | J25: 5 | K25: 5 | L25: 5 | M25: 10 | N25: very very talented team | O25: =IF(M25>=9,1,0) -> 1 | P25: =IF(M25>=7,1,0) -> 1 | Q25: =P25-O25 -> 0 | R25: =IF(M25<=6,1,0) -> 0 | S25: =O25+Q25+R25 -> 1 | T25: =((O25-R25)/S25) -> 1 | U25: =IF(L25>=4,1,0) -> 1 | V25: =IF(J25>=4,1,0) -> 1 | W25: =IF(K25>=4,1,0) -> 1 | X25: =IF(I25>=4,1,0) -> 1
A26: 2 | B26: 2026-05-11 10:00:00 | C26: 2026-05-13 13:00:00 | D26: Mostafa Ali Abdelmohsen Mohamed | E26: mostafa.ali@themarq.com.eg | F26: 01140171761 | G26: The Influence Map | H26: Ahmed ElShiaty | I26: 4 | J26: 4 | K26: 4 | L26: 4 | M26: 8 | O26: =IF(M26>=9,1,0) -> 0 | P26: =IF(M26>=7,1,0) -> 1 | Q26: =P26-O26 -> 1 | R26: =IF(M26<=6,1,0) -> 0 | S26: =O26+Q26+R26 -> 1 | T26: =((O26-R26)/S26) -> 0 | U26: =IF(L26>=4,1,0) -> 1 | V26: =IF(J26>=4,1,0) -> 1 | W26: =IF(K26>=4,1,0) -> 1 | X26: =IF(I26>=4,1,0) -> 1
A27: 2 | B27: 2026-05-11 10:00:00 | C27: 2026-05-13 13:00:00 | D27: Mahmoud Gamal Mahmoud Aboulila | E27: mahmoud.abulila@themarq.com.eg | F27: 01125565819 | G27: The Influence Map | H27: Ahmed ElShiaty | I27: 5 | J27: 5 | K27: 5 | L27: 4 | M27: 10 | O27: =IF(M27>=9,1,0) -> 1 | P27: =IF(M27>=7,1,0) -> 1 | Q27: =P27-O27 -> 0 | R27: =IF(M27<=6,1,0) -> 0 | S27: =O27+Q27+R27 -> 1 | T27: =((O27-R27)/S27) -> 1 | U27: =IF(L27>=4,1,0) -> 1 | V27: =IF(J27>=4,1,0) -> 1 | W27: =IF(K27>=4,1,0) -> 1 | X27: =IF(I27>=4,1,0) -> 1
A28: 2 | B28: 2026-05-11 10:00:00 | C28: 2026-05-13 13:00:00 | D28: Hany Refaat Abdallah Mohamed | E28: hany.refaat@themarq.com.eg | F28: 01156170952 | G28: The Influence Map | H28: Ahmed ElShiaty | I28: 5 | J28: 5 | K28: 5 | L28: 5 | M28: 10 | O28: =IF(M28>=9,1,0) -> 1 | P28: =IF(M28>=7,1,0) -> 1 | Q28: =P28-O28 -> 0 | R28: =IF(M28<=6,1,0) -> 0 | S28: =O28+Q28+R28 -> 1 | T28: =((O28-R28)/S28) -> 1 | U28: =IF(L28>=4,1,0) -> 1 | V28: =IF(J28>=4,1,0) -> 1 | W28: =IF(K28>=4,1,0) -> 1 | X28: =IF(I28>=4,1,0) -> 1
A29: 2 | B29: 2026-05-11 10:00:00 | C29: 2026-05-13 13:00:00 | D29: Gehad Badr El Sayed Bayoumi | E29: gehad.badr@themarq.com.eg | F29: 01277237484 | G29: The Influence Map | H29: Ahmed ElShiaty | I29: 5 | J29: 5 | K29: 5 | L29: 5 | M29: 10 | O29: =IF(M29>=9,1,0) -> 1 | P29: =IF(M29>=7,1,0) -> 1 | Q29: =P29-O29 -> 0 | R29: =IF(M29<=6,1,0) -> 0 | S29: =O29+Q29+R29 -> 1 | T29: =((O29-R29)/S29) -> 1 | U29: =IF(L29>=4,1,0) -> 1 | V29: =IF(J29>=4,1,0) -> 1 | W29: =IF(K29>=4,1,0) -> 1 | X29: =IF(I29>=4,1,0) -> 1
A30: 2 | B30: 2026-05-11 10:00:00 | C30: 2026-05-13 13:00:00 | D30: Khadija Mohamed Ahmed Zayed | E30: khadija.zayed@themarq.com.eg | F30: 1099170090 | G30: The Influence Map | H30: Ahmed ElShiaty | I30: 5 | J30: 5 | K30: 5 | L30: 5 | M30: 10 | O30: =IF(M30>=9,1,0) -> 1 | P30: =IF(M30>=7,1,0) -> 1 | Q30: =P30-O30 -> 0 | R30: =IF(M30<=6,1,0) -> 0 | S30: =O30+Q30+R30 -> 1 | T30: =((O30-R30)/S30) -> 1 | U30: =IF(L30>=4,1,0) -> 1 | V30: =IF(J30>=4,1,0) -> 1 | W30: =IF(K30>=4,1,0) -> 1 | X30: =IF(I30>=4,1,0) -> 1
A31: 2 | B31: 2026-05-11 10:00:00 | C31: 2026-05-13 13:00:00 | D31: Moustafa Salah Mohamed Hassan | E31: mostafa.salah@themarq.com.eg | F31: 01201082999 | G31: The Influence Map | H31: Ahmed ElShiaty | I31: 5 | J31: 5 | K31: 5 | L31: 5 | M31: 10 | O31: =IF(M31>=9,1,0) -> 1 | P31: =IF(M31>=7,1,0) -> 1 | Q31: =P31-O31 -> 0 | R31: =IF(M31<=6,1,0) -> 0 | S31: =O31+Q31+R31 -> 1 | T31: =((O31-R31)/S31) -> 1 | U31: =IF(L31>=4,1,0) -> 1 | V31: =IF(J31>=4,1,0) -> 1 | W31: =IF(K31>=4,1,0) -> 1 | X31: =IF(I31>=4,1,0) -> 1
A32: 2 | B32: 2026-05-11 10:00:00 | C32: 2026-05-13 13:00:00 | D32: MennatAllah Yahya Mohamed Tawfik Ahmed Abdul Aziz | E32: menna.yahya@themarq.com.eg | F32: 01005397775 | G32: The Influence Map | H32: Ahmed ElShiaty | I32: 5 | J32: 5 | K32: 5 | L32: 5 | M32: 10 | O32: =IF(M32>=9,1,0) -> 1 | P32: =IF(M32>=7,1,0) -> 1 | Q32: =P32-O32 -> 0 | R32: =IF(M32<=6,1,0) -> 0 | S32: =O32+Q32+R32 -> 1 | T32: =((O32-R32)/S32) -> 1 | U32: =IF(L32>=4,1,0) -> 1 | V32: =IF(J32>=4,1,0) -> 1 | W32: =IF(K32>=4,1,0) -> 1 | X32: =IF(I32>=4,1,0) -> 1
A33: 2 | B33: 2026-05-19 11:00:00 | C33: 2026-05-20 14:00:00 | D33: Magy Safwat Abdelsayed Ayyad Elbyady | E33: magy.safwat@themarq.com.eg | F33: 01224070029 | G33: The Connected Leader | H33: Ahmed Elshiaty | I33: 5 | J33: 3 | K33: 5 | L33: 5 | M33: 9 | O33: =IF(M33>=9,1,0) -> 1 | P33: =IF(M33>=7,1,0) -> 1 | Q33: =P33-O33 -> 0 | R33: =IF(M33<=6,1,0) -> 0 | S33: =O33+Q33+R33 -> 1 | T33: =((O33-R33)/S33) -> 1 | U33: =IF(L33>=4,1,0) -> 1 | V33: =IF(J33>=4,1,0) -> 0 | W33: =IF(K33>=4,1,0) -> 1 | X33: =IF(I33>=4,1,0) -> 1
A34: 2 | B34: 2026-05-19 11:00:00 | C34: 2026-05-20 14:00:00 | D34: Ahmed Medhat Sayed Baioumy el Atbany | E34: ahmed.medhat@themarq.com.eg | F34: 01285342768 | G34: The Connected Leader | H34: Ahmed Elshiaty | I34: 4 | J34: 4 | K34: 4 | L34: 5 | M34: 9 | O34: =IF(M34>=9,1,0) -> 1 | P34: =IF(M34>=7,1,0) -> 1 | Q34: =P34-O34 -> 0 | R34: =IF(M34<=6,1,0) -> 0 | S34: =O34+Q34+R34 -> 1 | T34: =((O34-R34)/S34) -> 1 | U34: =IF(L34>=4,1,0) -> 1 | V34: =IF(J34>=4,1,0) -> 1 | W34: =IF(K34>=4,1,0) -> 1 | X34: =IF(I34>=4,1,0) -> 1
A35: 2 | B35: 2026-05-19 11:00:00 | C35: 2026-05-20 14:00:00 | D35: eslam fathy abdelhamid mohamed | E35: eslam.fathyy@themarq.com.eg | F35: 01090348691 | G35: The Connected Leader | H35: Ahmed Elshiaty | I35: 4 | J35: 5 | K35: 4 | L35: 5 | M35: 10 | O35: =IF(M35>=9,1,0) -> 1 | P35: =IF(M35>=7,1,0) -> 1 | Q35: =P35-O35 -> 0 | R35: =IF(M35<=6,1,0) -> 0 | S35: =O35+Q35+R35 -> 1 | T35: =((O35-R35)/S35) -> 1 | U35: =IF(L35>=4,1,0) -> 1 | V35: =IF(J35>=4,1,0) -> 1 | W35: =IF(K35>=4,1,0) -> 1 | X35: =IF(I35>=4,1,0) -> 1
A36: 2 | B36: 2026-05-19 11:00:00 | C36: 2026-05-20 14:00:00 | D36: Ahmed kamal El Din Hassan El Khateeb | E36: ahmed.elkhateeb@themarq.com.eg | F36: 01110005077 | G36: The Connected Leader | H36: Ahmed Elshiaty | I36: 4 | J36: 5 | K36: 4 | L36: 5 | M36: 10 | O36: =IF(M36>=9,1,0) -> 1 | P36: =IF(M36>=7,1,0) -> 1 | Q36: =P36-O36 -> 0 | R36: =IF(M36<=6,1,0) -> 0 | S36: =O36+Q36+R36 -> 1 | T36: =((O36-R36)/S36) -> 1 | U36: =IF(L36>=4,1,0) -> 1 | V36: =IF(J36>=4,1,0) -> 1 | W36: =IF(K36>=4,1,0) -> 1 | X36: =IF(I36>=4,1,0) -> 1
A37: 2 | B37: 2026-05-19 11:00:00 | C37: 2026-05-20 14:00:00 | D37: Abdelrahman Ismail Abdallah Elshahat | E37: abdelrahman.ismail@themarq.com.eg | F37: 01001709593 | G37: The Connected Leader | H37: Ahmed Elshiaty | I37: 5 | J37: 5 | K37: 3 | L37: 5 | M37: 9 | O37: =IF(M37>=9,1,0) -> 1 | P37: =IF(M37>=7,1,0) -> 1 | Q37: =P37-O37 -> 0 | R37: =IF(M37<=6,1,0) -> 0 | S37: =O37+Q37+R37 -> 1 | T37: =((O37-R37)/S37) -> 1 | U37: =IF(L37>=4,1,0) -> 1 | V37: =IF(J37>=4,1,0) -> 1 | W37: =IF(K37>=4,1,0) -> 0 | X37: =IF(I37>=4,1,0) -> 1
... A45: 2 | B45: 2026-06-03 11:30:00 | C45: 2026-06-04 14:00:00 | D45: Ahmed Samir Galal Elelemy Ahmed | E45: ahmed.jalal@themarq.com.eg | F45: 01118099906 | G45: Story Craft | H45: Amr Alaa | I45: 5 | J45: 5 | K45: 5 | L45: 5 | M45: 10 | O45: =IF(M45>=9,1,0) -> 1 | P45: =IF(M45>=7,1,0) -> 1 | Q45: =P45-O45 -> 0 | R45: =IF(M45<=6,1,0) -> 0 | S45: =O45+Q45+R45 -> 1 | T45: =((O45-R45)/S45) -> 1 | U45: =IF(L45>=4,1,0) -> 1 | V45: =IF(J45>=4,1,0) -> 1 | W45: =IF(K45>=4,1,0) -> 1 | X45: =IF(I45>=4,1,0) -> 1
A46: 2 | B46: 2026-06-03 11:30:00 | C46: 2026-06-04 14:00:00 | D46: Omar Amr Mohamed Adel | E46: omar.amr@themarq.com.eg | F46: 1140535256 | G46: Story Craft | H46: Amr Alaa | I46: 4 | J46: 5 | K46: 5 | L46: 5 | M46: 10 | N46: more sessions and applications | O46: =IF(M46>=9,1,0) -> 1 | P46: =IF(M46>=7,1,0) -> 1 | Q46: =P46-O46 -> 0 | R46: =IF(M46<=6,1,0) -> 0 | S46: =O46+Q46+R46 -> 1 | T46: =((O46-R46)/S46) -> 1 | U46: =IF(L46>=4,1,0) -> 1 | V46: =IF(J46>=4,1,0) -> 1 | W46: =IF(K46>=4,1,0) -> 1 | X46: =IF(I46>=4,1,0) -> 1
A47: 2 | B47: 2026-06-03 11:30:00 | C47: 2026-06-04 14:00:00 | D47: Ahmed kamal El Din Hassan El Khateeb | E47: ahmed.elkhateeb@themarq.com.eg | F47: 01110005077 | G47: Story Craft | H47: Amr Alaa | I47: 5 | J47: 5 | K47: 5 | L47: 5 | M47: 10 | N47: thank you! | O47: =IF(M47>=9,1,0) -> 1 | P47: =IF(M47>=7,1,0) -> 1 | Q47: =P47-O47 -> 0 | R47: =IF(M47<=6,1,0) -> 0 | S47: =O47+Q47+R47 -> 1 | T47: =((O47-R47)/S47) -> 1 | U47: =IF(L47>=4,1,0) -> 1 | V47: =IF(J47>=4,1,0) -> 1 | W47: =IF(K47>=4,1,0) -> 1 | X47: =IF(I47>=4,1,0) -> 1
A48: 2 | B48: 2026-06-03 11:30:00 | C48: 2026-06-04 14:00:00 | D48: Ahmed Raouf Abdel Menaam Hanafy | E48: ahmed.raouf@themarq.com.eg | F48: 1277300584 | G48: Story Craft | H48: Amr Alaa | I48: 5 | J48: 5 | K48: 5 | L48: 5 | M48: 10 | O48: =IF(M48>=9,1,0) -> 1 | P48: =IF(M48>=7,1,0) -> 1 | Q48: =P48-O48 -> 0 | R48: =IF(M48<=6,1,0) -> 0 | S48: =O48+Q48+R48 -> 1 | T48: =((O48-R48)/S48) -> 1 | U48: =IF(L48>=4,1,0) -> 1 | V48: =IF(J48>=4,1,0) -> 1 | W48: =IF(K48>=4,1,0) -> 1 | X48: =IF(I48>=4,1,0) -> 1
A49: 2 | B49: 2026-06-03 11:30:00 | C49: 2026-06-04 14:00:00 | D49: Omar BahaaEldin Helmy Kamel | E49: omar.bahaa@themarq.com.eg | F49: 01281810056 | G49: Story Craft | H49: Amr Alaa | I49: 5 | J49: 5 | K49: 5 | L49: 5 | M49: 10 | O49: =IF(M49>=9,1,0) -> 1 | P49: =IF(M49>=7,1,0) -> 1 | Q49: =P49-O49 -> 0 | R49: =IF(M49<=6,1,0) -> 0 | S49: =O49+Q49+R49 -> 1 | T49: =((O49-R49)/S49) -> 1 | U49: =IF(L49>=4,1,0) -> 1 | V49: =IF(J49>=4,1,0) -> 1 | W49: =IF(K49>=4,1,0) -> 1 | X49: =IF(I49>=4,1,0) -> 1
A50: 2 | B50: 2026-06-03 11:30:00 | C50: 2026-06-04 14:00:00 | D50: Abdelrahman Khaled Saber Mohamed | E50: abdelrahman.mana@themarq.com.eg | F50: 01149991436 | G50: Story Craft | H50: Amr Alaa | I50: 5 | J50: 5 | K50: 5 | L50: 5 | M50: 10 | O50: =IF(M50>=9,1,0) -> 1 | P50: =IF(M50>=7,1,0) -> 1 | Q50: =P50-O50 -> 0 | R50: =IF(M50<=6,1,0) -> 0 | S50: =O50+Q50+R50 -> 1 | T50: =((O50-R50)/S50) -> 1 | U50: =IF(L50>=4,1,0) -> 1 | V50: =IF(J50>=4,1,0) -> 1 | W50: =IF(K50>=4,1,0) -> 1 | X50: =IF(I50>=4,1,0) -> 1
A51: 2 | B51: 2026-06-15 10:00:00 | C51: 2026-06-15 12:30:00 | D51: Hamed Ramadan Aliu Abdel Aal | E51: hamed.ramadan@themarq.com.eg | F51: 01020405978 | G51: Island of Seacrets-(Finance Dept) | H51: Aya Sameh | I51: 5 | J51: 5 | K51: 5 | L51: 5 | M51: 10 | O51: =IF(M51>=9,1,0) -> 1 | P51: =IF(M51>=7,1,0) -> 1 | Q51: =P51-O51 -> 0 | R51: =IF(M51<=6,1,0) -> 0 | S51: =O51+Q51+R51 -> 1 | T51: =((O51-R51)/S51) -> 1 | U51: =IF(L51>=4,1,0) -> 1 | V51: =IF(J51>=4,1,0) -> 1 | W51: =IF(K51>=4,1,0) -> 1 | X51: =IF(I51>=4,1,0) -> 1
A52: 2 | B52: 2026-06-15 10:00:00 | C52: 2026-06-15 12:30:00 | D52: Mohanad Tamer Hussein Elsayed Ibrahim | E52: mohanad.tamer@themarq.com.eg | F52: 01124339090 | G52: Island of Seacrets-(Finance Dept) | H52: Aya Sameh | I52: 5 | J52: 5 | K52: 5 | L52: 5 | M52: 10 | O52: =IF(M52>=9,1,0) -> 1 | P52: =IF(M52>=7,1,0) -> 1 | Q52: =P52-O52 -> 0 | R52: =IF(M52<=6,1,0) -> 0 | S52: =O52+Q52+R52 -> 1 | T52: =((O52-R52)/S52) -> 1 | U52: =IF(L52>=4,1,0) -> 1 | V52: =IF(J52>=4,1,0) -> 1 | W52: =IF(K52>=4,1,0) -> 1 | X52: =IF(I52>=4,1,0) -> 1
A53: 2 | B53: 2026-06-15 10:00:00 | C53: 2026-06-15 12:30:00 | D53: Hany Refaat Abdallah Mohamed | E53: hany.refaat@themarq.com.eg | F53: 01156170952 | G53: Island of Seacrets-(Finance Dept) | H53: Aya Sameh | I53: 5 | J53: 5 | K53: 5 | L53: 5 | M53: 10 | O53: =IF(M53>=9,1,0) -> 1 | P53: =IF(M53>=7,1,0) -> 1 | Q53: =P53-O53 -> 0 | R53: =IF(M53<=6,1,0) -> 0 | S53: =O53+Q53+R53 -> 1 | T53: =((O53-R53)/S53) -> 1 | U53: =IF(L53>=4,1,0) -> 1 | V53: =IF(J53>=4,1,0) -> 1 | W53: =IF(K53>=4,1,0) -> 1 | X53: =IF(I53>=4,1,0) -> 1
A54: 2 | B54: 2026-06-15 10:00:00 | C54: 2026-06-15 12:30:00 | D54: Gehad Badr El Sayed Bayoumi | E54: gehad.badr@themarq.com.eg | F54: 01277237484 | G54: Island of Seacrets-(Finance Dept) | H54: Aya Sameh | I54: 5 | J54: 5 | K54: 5 | L54: 5 | M54: 10 | O54: =IF(M54>=9,1,0) -> 1 | P54: =IF(M54>=7,1,0) -> 1 | Q54: =P54-O54 -> 0 | R54: =IF(M54<=6,1,0) -> 0 | S54: =O54+Q54+R54 -> 1 | T54: =((O54-R54)/S54) -> 1 | U54: =IF(L54>=4,1,0) -> 1 | V54: =IF(J54>=4,1,0) -> 1 | W54: =IF(K54>=4,1,0) -> 1 | X54: =IF(I54>=4,1,0) -> 1
A55: 2 | B55: 2026-06-15 10:00:00 | C55: 2026-06-15 12:30:00 | D55: Moataz Ahmed Fares Hussein Abdelnaby | E55: moataz.fares@themarq.com.eg | F55: 01003924005 | G55: Island of Seacrets-(Finance Dept) | H55: Aya Sameh | I55: 5 | J55: 5 | K55: 5 | L55: 5 | M55: 9 | N55: thanks for the good information | O55: =IF(M55>=9,1,0) -> 1 | P55: =IF(M55>=7,1,0) -> 1 | Q55: =P55-O55 -> 0 | R55: =IF(M55<=6,1,0) -> 0 | S55: =O55+Q55+R55 -> 1 | T55: =((O55-R55)/S55) -> 1 | U55: =IF(L55>=4,1,0) -> 1 | V55: =IF(J55>=4,1,0) -> 1 | W55: =IF(K55>=4,1,0) -> 1 | X55: =IF(I55>=4,1,0) -> 1
A56: 2 | B56: 2026-06-23 11:00:00 | C56: 2026-06-25 14:00:00 | D56: Ibrahim Essam Mansour Hasanen | E56: ibrahim.mansour@themarq.com.eg | F56: +201097184617 | G56: Hard Talks | H56: Amr Alaa | I56: 5 | J56: 5 | K56: 5 | L56: 5 | M56: 10 | O56: =IF(M56>=9,1,0) -> 1 | P56: =IF(M56>=7,1,0) -> 1 | Q56: =P56-O56 -> 0 | R56: =IF(M56<=6,1,0) -> 0 | S56: =O56+Q56+R56 -> 1 | T56: =((O56-R56)/S56) -> 1 | U56: =IF(L56>=4,1,0) -> 1 | V56: =IF(J56>=4,1,0) -> 1 | W56: =IF(K56>=4,1,0) -> 1 | X56: =IF(I56>=4,1,0) -> 1
A57: 2 | B57: 2026-07-06 11:00:00 | C57: 2026-07-07 14:00:00 | D57: Mostafa Ahmed Mostafa Mohamed | E57: mostafa.elabbasi@themarq.com.eg | F57: 01280180303 | G57: The Influence Map (Projects) | H57: Ahmed Elshiaty | I57: 3 | J57: 4 | K57: 5 | L57: 5 | M57: 8 | N57: All the MarQ department need this training | O57: =IF(M57>=9,1,0) -> 0 | P57: =IF(M57>=7,1,0) -> 1 | Q57: =P57-O57 -> 1 | R57: =IF(M57<=6,1,0) -> 0 | S57: =O57+Q57+R57 -> 1 | T57: =((O57-R57)/S57) -> 0 | U57: =IF(L57>=4,1,0) -> 1 | V57: =IF(J57>=4,1,0) -> 1 | W57: =IF(K57>=4,1,0) -> 1 | X57: =IF(I57>=4,1,0) -> 0
A58: 2 | B58: 2026-07-06 11:00:00 | C58: 2026-07-07 14:00:00 | D58: Maged Mostafa morsi attia | E58: maged.mostafa@themarq.com.eg | F58: 01224298898 | G58: The Influence Map (Projects) | H58: Ahmed Elshiaty | I58: 5 | J58: 5 | K58: 4 | L58: 5 | M58: 8 | O58: =IF(M58>=9,1,0) -> 0 | P58: =IF(M58>=7,1,0) -> 1 | Q58: =P58-O58 -> 1 | R58: =IF(M58<=6,1,0) -> 0 | S58: =O58+Q58+R58 -> 1 | T58: =((O58-R58)/S58) -> 0 | U58: =IF(L58>=4,1,0) -> 1 | V58: =IF(J58>=4,1,0) -> 1 | W58: =IF(K58>=4,1,0) -> 1 | X58: =IF(I58>=4,1,0) -> 1
A59: 2 | B59: 2026-07-06 11:00:00 | C59: 2026-07-07 14:00:00 | D59: Abdelaziz Ali Bakr Abdelaziz | E59: abdalaziz.saiif@themarq.com.eg | F59: 01128330367 | G59: The Influence Map (Projects) | H59: Ahmed Elshiaty | I59: 5 | J59: 5 | K59: 5 | L59: 5 | M59: 10 | O59: =IF(M59>=9,1,0) -> 1 | P59: =IF(M59>=7,1,0) -> 1 | Q59: =P59-O59 -> 0 | R59: =IF(M59<=6,1,0) -> 0 | S59: =O59+Q59+R59 -> 1 | T59: =((O59-R59)/S59) -> 1 | U59: =IF(L59>=4,1,0) -> 1 | V59: =IF(J59>=4,1,0) -> 1 | W59: =IF(K59>=4,1,0) -> 1 | X59: =IF(I59>=4,1,0) -> 1
A60: 2 | B60: 2026-07-06 11:00:00 | C60: 2026-07-07 14:00:00 | D60: Mohamed Maged Mohamed Khalil | E60: mohamed.maged@themarq.com.eg | F60: 01025684419 | G60: The Influence Map (Projects) | H60: Ahmed Elshiaty | I60: 5 | J60: 5 | K60: 5 | L60: 5 | M60: 10 | N60: thank you ♥️ | O60: =IF(M60>=9,1,0) -> 1 | P60: =IF(M60>=7,1,0) -> 1 | Q60: =P60-O60 -> 0 | R60: =IF(M60<=6,1,0) -> 0 | S60: =O60+Q60+R60 -> 1 | T60: =((O60-R60)/S60) -> 1 | U60: =IF(L60>=4,1,0) -> 1 | V60: =IF(J60>=4,1,0) -> 1 | W60: =IF(K60>=4,1,0) -> 1 | X60: =IF(I60>=4,1,0) -> 1
A61: 2 | B61: 2026-07-06 11:00:00 | C61: 2026-07-07 14:00:00 | D61: Samir Mansour Mohamed Ahmed | E61: samir.mansour@themarq.com.eg | F61: 01008893317 | G61: The Influence Map (Projects) | H61: Ahmed Elshiaty | I61: 5 | J61: 5 | K61: 5 | L61: 5 | M61: 10 | O61: =IF(M61>=9,1,0) -> 1 | P61: =IF(M61>=7,1,0) -> 1 | Q61: =P61-O61 -> 0 | R61: =IF(M61<=6,1,0) -> 0 | S61: =O61+Q61+R61 -> 1 | T61: =((O61-R61)/S61) -> 1 | U61: =IF(L61>=4,1,0) -> 1 | V61: =IF(J61>=4,1,0) -> 1 | W61: =IF(K61>=4,1,0) -> 1 | X61: =IF(I61>=4,1,0) -> 1
A62: 2 | B62: 2026-07-06 11:00:00 | C62: 2026-07-07 14:00:00 | D62: Almohsen Abdelwahab Abdelzaher Youssef | E62: elmohsen.abdelwhab@themarq.com.eg | F62: 01114860383 | G62: The Influence Map (Projects) | H62: Ahmed Elshiaty | I62: 5 | J62: 5 | K62: 5 | L62: 5 | M62: 10 | O62: =IF(M62>=9,1,0) -> 1 | P62: =IF(M62>=7,1,0) -> 1 | Q62: =P62-O62 -> 0 | R62: =IF(M62<=6,1,0) -> 0 | S62: =O62+Q62+R62 -> 1 | T62: =((O62-R62)/S62) -> 1 | U62: =IF(L62>=4,1,0) -> 1 | V62: =IF(J62>=4,1,0) -> 1 | W62: =IF(K62>=4,1,0) -> 1 | X62: =IF(I62>=4,1,0) -> 1
A63: 2 | B63: 2026-07-06 11:00:00 | C63: 2026-07-07 14:00:00 | D63: Shady Amir Ahmed Mirdan | E63: shady.amir@themarq.com.eg | F63: 01069121035 | G63: The Influence Map (Projects) | H63: Ahmed Elshiaty | I63: 5 | J63: 5 | K63: 5 | L63: 5 | M63: 10 | O63: =IF(M63>=9,1,0) -> 1 | P63: =IF(M63>=7,1,0) -> 1 | Q63: =P63-O63 -> 0 | R63: =IF(M63<=6,1,0) -> 0 | S63: =O63+Q63+R63 -> 1 | T63: =((O63-R63)/S63) -> 1 | U63: =IF(L63>=4,1,0) -> 1 | V63: =IF(J63>=4,1,0) -> 1 | W63: =IF(K63>=4,1,0) -> 1 | X63: =IF(I63>=4,1,0) -> 1
A64: 2 | B64: 2026-07-06 11:00:00 | C64: 2026-07-07 14:00:00 | D64: Mohamed Ahmed Mohamed Morsy | E64: mohamed.morsy@themarq.com.eg | F64: 01020037957 | G64: The Influence Map (Projects) | H64: Ahmed Elshiaty | I64: 4 | J64: 4 | K64: 3 | L64: 5 | M64: 9 | O64: =IF(M64>=9,1,0) -> 1 | P64: =IF(M64>=7,1,0) -> 1 | Q64: =P64-O64 -> 0 | R64: =IF(M64<=6,1,0) -> 0 | S64: =O64+Q64+R64 -> 1 | T64: =((O64-R64)/S64) -> 1 | U64: =IF(L64>=4,1,0) -> 1 | V64: =IF(J64>=4,1,0) -> 1 | W64: =IF(K64>=4,1,0) -> 0 | X64: =IF(I64>=4,1,0) -> 1
A65: 2 | B65: 2026-07-06 11:00:00 | C65: 2026-07-07 14:00:00 | D65: Ayman Mostafa Yousri Ahmed Mohamed | E65: ayman.yosri@themarq.com.eg | F65: 01008352815 | G65: The Influence Map (Projects) | H65: Ahmed Elshiaty | I65: 5 | J65: 5 | K65: 4 | L65: 4 | M65: 10 | N65: it was great | O65: =IF(M65>=9,1,0) -> 1 | P65: =IF(M65>=7,1,0) -> 1 | Q65: =P65-O65 -> 0 | R65: =IF(M65<=6,1,0) -> 0 | S65: =O65+Q65+R65 -> 1 | T65: =((O65-R65)/S65) -> 1 | U65: =IF(L65>=4,1,0) -> 1 | V65: =IF(J65>=4,1,0) -> 1 | W65: =IF(K65>=4,1,0) -> 1 | X65: =IF(I65>=4,1,0) -> 1
A66: 2 | B66: 2026-07-06 11:00:00 | C66: 2026-07-07 14:00:00 | D66: Aya Hussein Omar Ahmed | E66: aya.hussien@themarq.com.eg | F66: 01097201809 | G66: The Influence Map (Projects) | H66: Ahmed Elshiaty | I66: 5 | J66: 5 | K66: 4 | L66: 5 | M66: 9 | O66: =IF(M66>=9,1,0) -> 1 | P66: =IF(M66>=7,1,0) -> 1 | Q66: =P66-O66 -> 0 | R66: =IF(M66<=6,1,0) -> 0 | S66: =O66+Q66+R66 -> 1 | T66: =((O66-R66)/S66) -> 1 | U66: =IF(L66>=4,1,0) -> 1 | V66: =IF(J66>=4,1,0) -> 1 | W66: =IF(K66>=4,1,0) -> 1 | X66: =IF(I66>=4,1,0) -> 1
A67: 2 | B67: 2026-07-06 11:00:00 | C67: 2026-07-07 14:00:00 | D67: Mahmoud AbdElaziem Mohamed Ali | E67: mahmoud.abdelaziem@themarq.com.eg | F67: 01145329664 | G67: The Influence Map (Projects) | H67: Ahmed Elshiaty | I67: 5 | J67: 4 | K67: 3 | L67: 5 | M67: 5 | O67: =IF(M67>=9,1,0) -> 0 | P67: =IF(M67>=7,1,0) -> 0 | Q67: =P67-O67 -> 0 | R67: =IF(M67<=6,1,0) -> 1 | S67: =O67+Q67+R67 -> 1 | T67: =((O67-R67)/S67) -> -1 | U67: =IF(L67>=4,1,0) -> 1 | V67: =IF(J67>=4,1,0) -> 1 | W67: =IF(K67>=4,1,0) -> 0 | X67: =IF(I67>=4,1,0) -> 1
A68: 2 | B68: 2026-07-06 11:00:00 | C68: 2026-07-07 14:00:00 | D68: Akram Ibrahim Mohamed Ibrahim Mubarak | E68: akram.mubarak@themarq.com.eg | F68: 01001032133 | G68: The Influence Map (Projects) | H68: Ahmed Elshiaty | I68: 5 | J68: 4 | K68: 4 | L68: 5 | M68: 8 | O68: =IF(M68>=9,1,0) -> 0 | P68: =IF(M68>=7,1,0) -> 1 | Q68: =P68-O68 -> 1 | R68: =IF(M68<=6,1,0) -> 0 | S68: =O68+Q68+R68 -> 1 | T68: =((O68-R68)/S68) -> 0 | U68: =IF(L68>=4,1,0) -> 1 | V68: =IF(J68>=4,1,0) -> 1 | W68: =IF(K68>=4,1,0) -> 1 | X68: =IF(I68>=4,1,0) -> 1
A69: 2 | B69: 2026-07-06 11:00:00 | C69: 2026-07-07 14:00:00 | D69: Karim Ahmed Ghareeb elshahat | E69: karim.elshahat@themarq.com.eg | F69: 01159703568 | G69: The Influence Map (Projects) | H69: Ahmed Elshiaty | I69: 5 | J69: 5 | K69: 5 | L69: 5 | M69: 10 | O69: =IF(M69>=9,1,0) -> 1 | P69: =IF(M69>=7,1,0) -> 1 | Q69: =P69-O69 -> 0 | R69: =IF(M69<=6,1,0) -> 0 | S69: =O69+Q69+R69 -> 1 | T69: =((O69-R69)/S69) -> 1 | U69: =IF(L69>=4,1,0) -> 1 | V69: =IF(J69>=4,1,0) -> 1 | W69: =IF(K69>=4,1,0) -> 1 | X69: =IF(I69>=4,1,0) -> 1
A70: 2 | B70: 2026-07-06 11:00:00 | C70: 2026-07-07 14:00:00 | D70: Mohamed Mahmoud Ahmed ElBelawey | E70: mohamed.elbeblawy@themarq.com.eg | F70: 01114606611 | G70: The Influence Map (Projects) | H70: Ahmed Elshiaty | I70: 4 | J70: 4 | K70: 4 | L70: 5 | M70: 9 | O70: =IF(M70>=9,1,0) -> 1 | P70: =IF(M70>=7,1,0) -> 1 | Q70: =P70-O70 -> 0 | R70: =IF(M70<=6,1,0) -> 0 | S70: =O70+Q70+R70 -> 1 | T70: =((O70-R70)/S70) -> 1 | U70: =IF(L70>=4,1,0) -> 1 | V70: =IF(J70>=4,1,0) -> 1 | W70: =IF(K70>=4,1,0) -> 1 | X70: =IF(I70>=4,1,0) -> 1
A71: 2 | B71: 2026-07-06 11:00:00 | C71: 2026-07-07 14:00:00 | D71: Mohamed Abd ElHaris Mohamed AbuZeid | E71: mohamed.haris@themarq.com.eg | F71: 01280418880 | G71: The Influence Map (Projects) | H71: Ahmed Elshiaty | I71: 4 | J71: 4 | K71: 4 | L71: 5 | M71: 9 | O71: =IF(M71>=9,1,0) -> 1 | P71: =IF(M71>=7,1,0) -> 1 | Q71: =P71-O71 -> 0 | R71: =IF(M71<=6,1,0) -> 0 | S71: =O71+Q71+R71 -> 1 | T71: =((O71-R71)/S71) -> 1 | U71: =IF(L71>=4,1,0) -> 1 | V71: =IF(J71>=4,1,0) -> 1 | W71: =IF(K71>=4,1,0) -> 1 | X71: =IF(I71>=4,1,0) -> 1
A72: 2 | B72: 2026-07-06 11:00:00 | C72: 2026-07-07 14:00:00 | D72: Ahmed AlaaEldin Abdelhalim Ismail Keshk | E72: ahmed.keshk@themarq.com.eg | F72: 01015506230 | G72: The Influence Map (Projects) | H72: Ahmed Elshiaty | I72: 3 | J72: 3 | K72: 3 | L72: 4 | M72: 6 | O72: =IF(M72>=9,1,0) -> 0 | P72: =IF(M72>=7,1,0) -> 0 | Q72: =P72-O72 -> 0 | R72: =IF(M72<=6,1,0) -> 1 | S72: =O72+Q72+R72 -> 1 | T72: =((O72-R72)/S72) -> -1 | U72: =IF(L72>=4,1,0) -> 1 | V72: =IF(J72>=4,1,0) -> 0 | W72: =IF(K72>=4,1,0) -> 0 | X72: =IF(I72>=4,1,0) -> 0
A73: 2 | B73: 2026-07-06 11:00:00 | C73: 2026-07-07 14:00:00 | D73: Mohamed Osama Hassan Moussa | E73: mohamed.osama@themarq.com.eg | F73: 011113086802 | G73: The Influence Map (Projects) | H73: Ahmed Elshiaty | I73: 5 | J73: 5 | K73: 5 | L73: 5 | M73: 8 | O73: =IF(M73>=9,1,0) -> 0 | P73: =IF(M73>=7,1,0) -> 1 | Q73: =P73-O73 -> 1 | R73: =IF(M73<=6,1,0) -> 0 | S73: =O73+Q73+R73 -> 1 | T73: =((O73-R73)/S73) -> 0 | U73: =IF(L73>=4,1,0) -> 1 | V73: =IF(J73>=4,1,0) -> 1 | W73: =IF(K73>=4,1,0) -> 1 | X73: =IF(I73>=4,1,0) -> 1
A74: 2 | B74: 2026-07-06 11:00:00 | C74: 2026-07-07 14:00:00 | D74: AlShimaa Ahmed Mohamed Abdullatif | E74: alshimaa.abdullatif@themarq.com.eg | F74: 01000002740 | G74: The Influence Map (Projects) | H74: Ahmed Elshiaty | I74: 5 | J74: 5 | K74: 5 | L74: 5 | M74: 10 | O74: =IF(M74>=9,1,0) -> 1 | P74: =IF(M74>=7,1,0) -> 1 | Q74: =P74-O74 -> 0 | R74: =IF(M74<=6,1,0) -> 0 | S74: =O74+Q74+R74 -> 1 | T74: =((O74-R74)/S74) -> 1 | U74: =IF(L74>=4,1,0) -> 1 | V74: =IF(J74>=4,1,0) -> 1 | W74: =IF(K74>=4,1,0) -> 1 | X74: =IF(I74>=4,1,0) -> 1
A351: 2 | B351: 2026-08-03 11:00:00 | C351: 2026-08-04 14:00:00 | D351: Aya Hussein Omar Ahmed | E351: aya.hussien@themarq.com.eg | F351: 01097201809 | G351: inside out | H351: Amr Alaa | I351: 5 | J351: 5 | K351: 4 | L351: 5 | M351: 10 | O351: =IF(M351>=9,1,0) -> 1 | P351: =IF(M351>=7,1,0) -> 1 | Q351: =P351-O351 -> 0 | R351: =IF(M351<=6,1,0) -> 0 | S351: =O351+Q351+R351 -> 1 | T351: =((O351-R351)/S351) -> 1 | U351: =IF(L351>=4,1,0) -> 1 | V351: =IF(J351>=4,1,0) -> 1 | W351: =IF(K351>=4,1,0) -> 1 | X351: =IF(I351>=4,1,0) -> 1
A352: 2 | B352: 2026-08-03 11:00:00 | C352: 2026-08-04 14:00:00 | D352: Israa Mahmoud Elsayed Maraie | E352: israa.maraie@themarq.com.eg | F352: 01224692381 | G352: inside out | H352: Amr Alaa | I352: 4 | J352: 4 | K352: 4 | L352: 5 | M352: 9 | N352: sequence of activity is perfect....only the traits need to be explained deeper | O352: =IF(M352>=9,1,0) -> 1 | P352: =IF(M352>=7,1,0) -> 1 | Q352: =P352-O352 -> 0 | R352: =IF(M352<=6,1,0) -> 0 | S352: =O352+Q352+R352 -> 1 | T352: =((O352-R352)/S352) -> 1 | U352: =IF(L352>=4,1,0) -> 1 | V352: =IF(J352>=4,1,0) -> 1 | W352: =IF(K352>=4,1,0) -> 1 | X352: =IF(I352>=4,1,0) -> 1
A353: 2 | B353: 2026-08-03 11:00:00 | C353: 2026-08-04 14:00:00 | D353: Ayman Mostafa Yousri Ahmed Mohamed | E353: ayman.yosri@themarq.com.eg | F353: 01008352815 | G353: inside out | H353: Amr Alaa | I353: 5 | J353: 5 | K353: 2 | L353: 4 | M353: 9 | N353: the instractor was great | O353: =IF(M353>=9,1,0) -> 1 | P353: =IF(M353>=7,1,0) -> 1 | Q353: =P353-O353 -> 0 | R353: =IF(M353<=6,1,0) -> 0 | S353: =O353+Q353+R353 -> 1 | T353: =((O353-R353)/S353) -> 1 | U353: =IF(L353>=4,1,0) -> 1 | V353: =IF(J353>=4,1,0) -> 1 | W353: =IF(K353>=4,1,0) -> 0 | X353: =IF(I353>=4,1,0) -> 1
A354: 2 | B354: 2026-08-03 11:00:00 | C354: 2026-08-04 14:00:00 | D354: AlShimaa Ahmed Mohamed Abdullatif | E354: alshimaa.abdullatif@themarq.com.eg | F354: 01000002740 | G354: inside out | H354: Amr Alaa | I354: 5 | J354: 5 | K354: 5 | L354: 5 | M354: 10 | O354: =IF(M354>=9,1,0) -> 1 | P354: =IF(M354>=7,1,0) -> 1 | Q354: =P354-O354 -> 0 | R354: =IF(M354<=6,1,0) -> 0 | S354: =O354+Q354+R354 -> 1 | T354: =((O354-R354)/S354) -> 1 | U354: =IF(L354>=4,1,0) -> 1 | V354: =IF(J354>=4,1,0) -> 1 | W354: =IF(K354>=4,1,0) -> 1 | X354: =IF(I354>=4,1,0) -> 1

Sheet Linked In no
I1: Linked In above 10mins | J1: Unique in Class
B2: Inclass | C2: Linked In | D2: Uniques | F2: Inclass | G2: =B95 -> 92 | I2: Abdelrahman Ismail | J2: Abdelaziz Youssef Abo El Wafa Mohamed
A3: Inclass | B3: Abdelaziz Youssef Abo El Wafa Mohamed | C3: Shady Amir Ahmed Mirdan | D3: Abdelaziz Youssef Abo El Wafa Mohamed | F3: Linked In | G3: =C30 -> 27 | I3: Abdelrhman Amer | J3: Abdelrahman Ismail Abdallah Elshahat
A4: Inclass | B4: Abdelrahman Ismail Abdallah Elshahat | C4: Ahmed Raouf Abdel Menaam Hanafy | D4: Abdelrahman Ismail Abdallah Elshahat | F4: Uniques | G4: =D101 -> 98 | I4: Afef Rizk | J4: Abdelrahman Khaled Saber Mohamed
A5: Inclass | B5: Abdelrahman Khaled Saber Mohamed | C5: Youssef Hussien Abdelrahman Abdelmeged | D5: Abdelrahman Khaled Saber Mohamed | I5: Ahmed Elkhateeb | J5: Abdelrahman Mohamed Saad Ahmed
A6: Inclass | B6: Abdelrahman Mohamed Saad Ahmed | C6: Moustafa Salah Mohamed Hassan | D6: Abdelrahman Mohamed Saad Ahmed | I6: Ahmed Jalal | J6: Ahmad Mohamed Ahmad Mohamed Mansour
A7: Inclass | B7: Ahmad Mohamed Ahmad Mohamed Mansour | C7: Seif Mohamed Abd El Halim | D7: Ahmad Mohamed Ahmad Mohamed Mansour | I7: Ahmed Magdi | J7: Ahmed Abdel Hakim
A8: Inclass | B8: Ahmed Abdel Hakim | C8: Abdelrahman Amer Abdelrahman Ahmed | D8: Ahmed Abdel Hakim | I8: Ahmed Raouf | J8: Ahmed AlaaEldin Abdelhalim Ismail Keshk
A9: Inclass | B9: Ahmed elsayed elsayed elshiaty | C9: Amr Alaa Eldin Maged Ahmed | D9: Ahmed elsayed elsayed elshiaty | I9: Aida Fouad | J9: Ahmed elsayed elsayed elshiaty
A10: Inclass | B10: Ahmed Gamal Mostafa Kamel | C10: Israa Mahmoud Elsayed Maraie | D10: Ahmed Gamal Mostafa Kamel | I10: Amr Alaa | J10: Ahmed Gamal Mostafa Kamel
A11: Inclass | B11: Ahmed kamal El Din Hassan El Khateeb | C11: MennatAllah Yahya Mohamed Tawfik Ahmed Abdul Aziz | D11: Ahmed kamal El Din Hassan El Khateeb | I11: Amr Hany | J11: Ahmed kamal El Din Hassan El Khateeb
A12: Inclass | B12: Ahmed Khaled Kamal Ibrahim | C12: Abdelrahman Ismail Abdallah Elshahat | D12: Ahmed Khaled Kamal Ibrahim | I12: Aya Sameh | J12: Ahmed Khaled Kamal Ibrahim
A13: Inclass | B13: Ahmed Magdy Fekry Elhagaa | C13: Amr Hani Mohamed Abdel Latif | D13: Ahmed Magdy Fekry Elhagaa | I13: Eslam Fathyy | J13: Ahmed Magdy Fekry Elhagaa
A14: Inclass | B14: Ahmed Medhat Sayed Baioumy el Atbany | C14: Mohamed Hussein Yaqoub Mohamed | D14: Ahmed Medhat Sayed Baioumy el Atbany | I14: Gehad Badr | J14: Ahmed Medhat Sayed Baioumy el Atbany
A15: Inclass | B15: Ahmed mohamed AboelMagd Eldardiri | C15: Mohamed Adel mohamed khader | D15: Ahmed mohamed AboelMagd Eldardiri | I15: Hany Refaat | J15: Ahmed mohamed AboelMagd Eldardiri
A16: Inclass | B16: Ahmed Mohamed Ahmed Salem | C16: Ahmed kamal El Din Hassan El Khateeb | D16: Ahmed Mohamed Ahmed Salem | I16: Israa Marie | J16: Ahmed Mohamed Ahmed Salem
... A29: Inclass | B29: Amr Hani Mohamed Abdel Latif | C29: Mohamed Mabrouk Ismail Mohamed | D29: Amr Hani Mohamed Abdel Latif | I29: Mostafa Salah | J29: Amira Tarek Mohamed Abdelmutaal Ali El Sherkawy
A30: Inclass | B30: Amr Hussein Hassan Mohamed Ali | C30: 27 | D30: Amr Hussein Hassan Mohamed Ali | I30: Seif Mohamed | J30: Amr Alaa Eldin Maged Ahmed
A31: Inclass | B31: Aya Khaled Naeem Elkhawaga | D31: Aya Khaled Naeem Elkhawaga | I31: Shady Amir | J31: Abdelaziz Ali Bakr Abdelaziz
A32: Inclass | B32: Aya Sameh Hassan Ibrahim | D32: Aya Sameh Hassan Ibrahim | I32: Toaa Ghanem | J32: Amr Ali Abdelwahab Sobh
A33: Inclass | B33: Aya Tarek Mossad Abdelaziz | D33: Aya Tarek Mossad Abdelaziz | I33: Yousef Hussin | J33: Amr Ali Mahmoud Elhanbaly
A34: Inclass | B34: Ayman Mousa Haneen Mokbel | D34: Ayman Mousa Haneen Mokbel | J34: Amr Hani Mohamed Abdel Latif
A35: Inclass | B35: Baher Saeed Khamis Mahmoud Elshamy | D35: Baher Saeed Khamis Mahmoud Elshamy | J35: Amr Hussein Hassan Mohamed Ali
A36: Inclass | B36: Diana Hossam Abdelrahman Osman | D36: Diana Hossam Abdelrahman Osman | J36: Aya Hussein Omar Ahmed
A37: Inclass | B37: Eleonora Christo Paraskevas Vostanis | D37: Eleonora Christo Paraskevas Vostanis | J37: Aya Karim Thomas Konstantin
A38: Inclass | B38: eslam fathy abdelhamid mohamed | D38: eslam fathy abdelhamid mohamed | J38: Aya Khaled Naeem Elkhawaga
A39: Inclass | B39: Farouk Mohamed Farouk Soliman | D39: Farouk Mohamed Farouk Soliman | J39: Aya Sameh Hassan Ibrahim
A40: Inclass | B40: Gehad Badr El Sayed Bayoumi | D40: Gehad Badr El Sayed Bayoumi | J40: Aya Tarek Mossad Abdelaziz
A41: Inclass | B41: Gihan Mohamed Labib Abdelbasset Auf | D41: Gihan Mohamed Labib Abdelbasset Auf | J41: Ayman Mostafa Yousri Ahmed Mohamed
A42: Inclass | B42: Hamed Ramadan Aliu Abdel Aal | D42: Hamed Ramadan Aliu Abdel Aal | J42: Ayman Mousa Haneen Mokbel
A43: Inclass | B43: Hany Refaat Abdallah Mohamed | D43: Hany Refaat Abdallah Mohamed | J43: Baher Saeed Khamis Mahmoud Elshamy
A44: Inclass | B44: heba ashraf youssef ibrahim | D44: heba ashraf youssef ibrahim | J44: Diana Hossam Abdelrahman Osman
A45: Inclass | B45: Heba Magdy Elbialy Hashish | D45: Heba Magdy Elbialy Hashish | J45: Eleonora Christo Paraskevas Vostanis
... A94: Inclass | B94: Youssef Hussien Abdelrahman Abdelmeged | D94: Youssef Hussien Abdelrahman Abdelmeged | J94: Mostafa Ali Abdelmohsen Mohamed
B95: 92 | D95: Shady Amir Ahmed Mirdan | J95: Moustafa Salah Mohamed Hassan
D96: Seif Mohamed Abd El Halim | J96: Nadeem Nabil Ahmed Fahmy
D97: Abdelrahman Amer Abdelrahman Ahmed | J97: Noha Hassan Sabry Mohamed Ibrahim
D98: Karim Mohamed Othman Hassan | J98: Nour Eldin Fathy Mohamed Khaky
D99: Khaled Mohamed El-mesilhy Mohamed Ibrahim | J99: Nour Sherif Mohamed Hussien Abbas
D100: Atef Rezk El Sayed El Sayed El Sabbagh | J100: Nourhan yasser Hamed Elmoaz
D101: 98 | J101: Omar Amr Mohamed Adel
J102: Omar BahaaEldin Helmy Kamel
J103: Osama Abdelaziz Elsayed Salama
J104: Passant El Ghandour
J105: Passant Magdy Abdel Razek Eliwa
J106: Perihan Osama Abdelazim Sharaf
J107: Randa Mohamed Abdel Moneim Fayad
J108: Saeed Mohamed Saeed Zalabya
J109: Salah Hassan ElBanna Mohamad Abdo
J110: Sameh Mahmoud Mohamed Khamis
J111: Samir Mansour Mohamed Ahmed
J112: Sandra Atallah Fouad Benjamin
J113: Shady Amir Ahmed Mirdan
... J122: Youssef Hussien Abdelrahman Abdelmeged

Sheet Attendance Prep
A1: # | B1: Enrollments | C1: Participation PC/Cust | D1: PC/Cust (Per Topic) | E1: Customised (Dept) | F1: Program Name | G1: Trainer Name | H1: Program Duration/hrs | I1: Learning Hrs | J1: No.of sessions | K1: Name | L1: Phone Number | M1: Email | N1: Department | O1: Job Title | P1: Employee Code | Q1: Date | R1: Internal/External | S1: Sector
A2: Session ID | F2: Program Name | G2: Trainer Name | H2: Duration | K2: Name | L2: Phone Number | M2: Email | N2: Department | O2: Job Title | P2: Employee Code | Q2: Attendance Date
A3: 165 | B3: 6 | C3: Customised (Dept) | D3: Customised (Dept) | E3: Projects | F3: inside out | G3: Amr Alaa | H3: 3 | I3: 3 | J3: 2 | K3: Ayman Mostafa Yousri Ahmed Mohamed | L3: 01008352815 | M3: ayman.yosri@themarq.com.eg | N3: Tendering | O3: Associate Tendering Manager | P3: TMC-33778 | Q3: 46237 | R3: Internal | S3: Projects
A4: 165 | C4: Customised | F4: inside out | G4: Amr Alaa | I4: 3 | K4: Aya Hussein Omar Ahmed | L4: 01097201809 | M4: aya.hussien@themarq.com.eg | N4: Budgeting & Cost Control | O4: Associate Budgeting & Cost Control Manager | P4: TMC-33936 | Q4: 46237 | R4: Internal | S4: Projects
A5: 165 | C5: Customised | F5: inside out | G5: Amr Alaa | I5: 3 | K5: Maged Mostafa morsi attia | L5: 01224298898 | M5: maged.mostafa@themarq.com.eg | N5: Construction Project Management | O5: Senior Project Manager | P5: TM4-15486 | Q5: 46237 | R5: Internal | S5: Projects
A6: 165 | C6: Customised | F6: inside out | G6: Amr Alaa | I6: 3 | K6: AlShimaa Ahmed Mohamed Abdullatif | L6: 01000002740 | M6: alshimaa.abdullatif@themarq.com.eg | N6: Contracts | O6: Senior Contracts Manager | P6: TMC-33781 | Q6: 46237 | R6: Internal | S6: Projects
A7: 165 | C7: Customised | F7: inside out | G7: Amr Alaa | I7: 3 | K7: Israa Mahmoud Elsayed Maraie | L7: 01224692381 | M7: israa.maraie@themarq.com.eg | N7: Tendering | O7: Senior Tendering Manager | P7: TM4-25001 | Q7: 46237 | R7: Internal | S7: Projects
A8: 165 | C8: Customised | F8: inside out | G8: Amr Alaa | I8: 3 | K8: Ahmed AlaaEldin Abdelhalim Ismail Keshk | L8: 01015506230 | M8: ahmed.keshk@themarq.com.eg | N8: Budgeting & Cost Control | O8: Senior Budgeting & Cost Control Engineer | P8: TM4-32770 | Q8: 46237 | R8: Internal | S8: Projects
A9: 166 | C9: Customised | F9: inside out | G9: Amr Alaa | H9: 3 | I9: 3 | K9: Aya Hussein Omar Ahmed | L9: 01097201809 | M9: aya.hussien@themarq.com.eg | N9: Budgeting & Cost Control | O9: Associate Budgeting & Cost Control Manager | P9: TMC-33936 | Q9: 46240 | R9: Internal | S9: Projects
A10: 166 | C10: Customised | F10: inside out | G10: Amr Alaa | I10: 3 | K10: Maged Mostafa morsi attia | L10: 01224298898 | M10: maged.mostafa@themarq.com.eg | N10: Construction Project Management | O10: Senior Project Manager | P10: TM4-15486 | Q10: 46240 | R10: Internal | S10: Projects
A11: 166 | C11: Customised | F11: inside out | G11: Amr Alaa | I11: 3 | K11: Ayman Mostafa Yousri Ahmed Mohamed | L11: 01008352815 | M11: ayman.yosri@themarq.com.eg | N11: Tendering | O11: Associate Tendering Manager | P11: TMC-33778 | Q11: 46240 | R11: Internal | S11: Projects
A12: 166 | C12: Customised | F12: inside out | G12: Amr Alaa | I12: 3 | K12: AlShimaa Ahmed Mohamed Abdullatif | L12: 01000002740 | M12: alshimaa.abdullatif@themarq.com.eg | N12: Contracts | O12: Senior Contracts Manager | P12: TMC-33781 | Q12: 46240 | R12: Internal | S12: Projects
A13: 166 | C13: Customised | F13: inside out | G13: Amr Alaa | I13: 3 | K13: Israa Mahmoud Elsayed Maraie | L13: 01224692381 | M13: israa.maraie@themarq.com.eg | N13: Tendering | O13: Senior Tendering Manager | P13: TM4-25001 | Q13: 46240 | R13: Internal | S13: Projects

Sheet Head Count 212
A1: id | B1: full_name | C1: email | D1: mobile | E1: status | F1: company | G1: franchise | H1: sector | L1: department | M1: parent | N1: identification_id | O1: position | P1: employee_code | Q1: hire_date | R1: payscale_cluster_name | S1: payscale_cluster_code | T1: job_level_name | U1: job_level_grade | V1: allocation_company
A2: 8 | B2: Ahmed Hamdy Mohamed Abdelftah Mostafa Awaimar | C2: ahmed.hamdy@themarq.com.eg | D2: 01004379643 | E2: active | F2: The MarQ Communities | H2: Finance | I2: Credit Control | L2: Credit Control | M2: Efrayem Refaat Hanna Shalaby | N2: 28706191401617 | O2: Credit Control Director | P2: TM4-8031 | Q2: 2021-02-15 | R2: Executive Management | S2: 2 | T2: Director | U2: 17 | V2: The MarQ Communities
A3: 11 | B3: Ahmed Mohamed Adel Taha Abdelaal | C3: ahmed.adel@themarq.com.eg | D3: 01228233334 | E3: active | F3: The MarQ Communities | H3: Finance | I3: Credit Control | L3: Credit Control | M3: Ahmed Hamdy Mohamed Abdelftah Mostafa Awaimar | N3: 28911221300091 | O3: Credit Control Manager | P3: TM4-8032 | Q3: 2021-02-17 | R3: Middle Management | S3: 3 | T3: Manager | U3: 14 | V3: The MarQ Communities
A4: 14 | B4: Ahmed Sayed Abdel Satar Elsayed | C4: ahmed.abdelsatar@themarq.com.eg | D4: 01005999810 | E4: active | F4: The MarQ Communities | H4: Commercial | I4: Sales Operations | L4: Sales Operations | M4: Ayman Mohamed Refaat Ahmed | N4: 28410100105631 | O4: Sales Operations Supervisor | P4: TM4-11458 | Q4: 2022-03-16 | R4: Professional | S4: 5 | T4: Supervisor | U4: 10 | V4: The MarQ Communities
A5: 16 | B5: Alaa Essam Mohamed Ibrahim | C5: alaa.omar@themarq.com.eg | D5: 01117559150 | E5: active | F5: The MarQ Communities | H5: Development & Innovation | I5: Design Review | J5: Urban | L5: Urban | M5: Nour Eldin Fathy Mohamed Khaky | N5: 29505308800168 | O5: Urban Design Review Teamleader | P5: TM4-11401 | Q5: 2022-03-13 | R5: Supervisory Management | S5: 4 | T5: Teamleader | U5: 11 | V5: The MarQ Communities
A6: 21 | B6: Amr Ali Abdelwahab Sobh | C6: amr.ali@themarq.com.eg | D6: 01092832193 | E6: active | F6: The MarQ Communities | H6: Development & Innovation | I6: Design Review | J6: Urban | L6: Urban | M6: Ahmed Shawky Shaaban Hassan | N6: 29310011210919 | O6: Urban Design Review Section Head | P6: TM4-8047 | Q6: 2021-08-01 | R6: Supervisory Management | S6: 4 | T6: Section Head | U6: 12 | V6: The MarQ Communities
A7: 22 | B7: Amr Hani Mohamed Abdel Latif | C7: amr.hany@themarq.com.eg | D7: 01062540976 | E7: active | F7: The MarQ Communities | H7: Development & Innovation | I7: Design Management | L7: Design Management | M7: Ahmed Shawky Shaaban Hassan | N7: 29211012108354 | O7: Senior Design Management Manager | P7: TM4-8016 | Q7: 2020-09-01 | R7: Middle Management | S7: 3 | T7: Senior Manager | U7: 15 | V7: The MarQ Communities
A8: 25 | B8: Atef Rezk El Sayed El Sayed El Sabbagh | C8: atef.rizk@themarq.com.eg | D8: 01150111783 | E8: active | F8: The MarQ Communities | H8: Commercial | I8: Sales Operations | L8: Sales Operations | M8: Ayman Mohamed Refaat Ahmed | N8: 28107232101614 | O8: Sales Operations Manager | P8: TM4-8002 | Q8: 2019-09-01 | R8: Middle Management | S8: 3 | T8: Manager | U8: 14 | V8: The MarQ Communities
A9: 26 | B9: Ayman Mohamed Refaat Ahmed | C9: ayman.refaat@themarq.com.eg | D9: 01090080320 | E9: active | F9: The MarQ Communities | H9: Commercial | I9: Sales Operations | L9: Sales Operations | M9: Amr Mohamed Abdel-Hay Badr | N9: 28209018800715 | O9: Senior Sales Operations Director | P9: TM4-8001 | Q9: 2019-09-01 | R9: Executive Management | S9: 2 | T9: Senior Director | U9: 18 | V9: The MarQ Communities
A10: 27 | B10: Daiana Youssef Yehia Youssef Greiss | C10: diana.greiss@themarq.com.eg | D10: 1001096061 | E10: active | F10: The MarQ Communities | H10: Commercial | I10: Sales | L10: Sales | M10: Amr Mohamed Abdel-Hay Badr | N10: 28707070102864 | O10: Senior Sales Director | P10: TM4-3643 | Q10: 2021-08-01 | R10: Executive Management | S10: 2 | T10: Senior Director | U10: 18 | V10: The MarQ Communities
A11: 32 | B11: Gehad Badr El Sayed Bayoumi | C11: gehad.badr@themarq.com.eg | D11: 01277237484 | E11: active | F11: The MarQ Communities | H11: Finance | I11: Accounting | J11: Accounts Receivable | L11: Accounts Receivable | M11: Mohamed Mabrouk Ismail Mohamed | N11: 29601102105284 | O11: Accounts Receivable Supervisor | P11: TM4-8010 | Q11: 2020-02-17 | R11: Professional | S11: 5 | T11: Supervisor | U11: 10 | V11: The MarQ Communities
A12: 33 | B12: Hania Yehia Abdelfattah Sabry | C12: hunya.yehia@themarq.com.eg | D12: 01125997743 | E12: active | F12: The MarQ Communities | H12: Finance | I12: Credit Control | L12: Credit Control | M12: Ahmed Mohamed Adel Taha Abdelaal | N12: 30007190103381 | O12: Senior Credit Control Specialist | P12: TM4-2197 | Q12: 2021-03-15 | R12: Professional | S12: 5 | T12: Senior Specialist | U12: 9 | V12: The MarQ Communities
A13: 35 | B13: Hany Refaat Abdallah Mohamed | C13: hany.refaat@themarq.com.eg | D13: 01156170952 | E13: active | F13: The MarQ Communities | H13: Finance | I13: Accounting | J13: Accounts Receivable | L13: Accounts Receivable | M13: Mohamed Mabrouk Ismail Mohamed | N13: 28108090100433 | O13: Accounts Receivable Teamleader | P13: TM4-11403 | Q13: 2022-03-10 | R13: Supervisory Management | S13: 4 | T13: Teamleader | U13: 11 | V13: The MarQ Communities
A14: 43 | B14: Karim Mohsen Ahmed Elweshey | C14: karim.elwishy@themarq.com.eg | D14: 01111229023 | E14: active | F14: The MarQ Communities | H14: Commercial | I14: Sales Operations | J14: Contracts | L14: Contracts | M14: Ayman Mohamed Refaat Ahmed | N14: 29203318800071 | O14: Senior Contracts Specialist | P14: TM4-8034 | Q14: 2021-04-01 | R14: Professional | S14: 5 | T14: Senior Specialist | U14: 9 | V14: The MarQ Communities
A15: 45 | B15: Khaled Mohamed El-mesilhy Mohamed Ibrahim | C15: khaled.elmesilhy@themarq.com.eg | D15: 01002277836 | E15: active | F15: The MarQ Communities | H15: Commercial | I15: Sales Operations | L15: Sales Operations | M15: Mohamed DiaaElDin Ahmed Shehata ElShamy | N15: 29111070103139 | O15: Sales Operations Supervisor | P15: TM4-11497 | Q15: 2022-03-22 | R15: Professional | S15: 5 | T15: Supervisor | U15: 10 | V15: The MarQ Communities
A16: 49 | B16: Mahmoud Amr Mahmoud Kamel Rashad Tawakol | C16: mahmoud.tawakol@themarq.com.eg | D16: 01008986995 | E16: active | F16: The MarQ Communities | H16: Commercial | I16: Sales | L16: Sales | M16: Daiana Youssef Yehia Youssef Greiss | N16: 29504030103073 | O16: Senior Sales Manager | P16: TM4-1707 | Q16: 2025-11-02 | R16: Middle Management | S16: 3 | T16: Senior Manager | U16: 15 | V16: The MarQ Communities
A17: 53 | B17: Mazen Adnan Ahmed Mostafa Elshamy | C17: mazen.elshamy@themarq.com.eg | D17: 01126099391 | E17: active | F17: The MarQ Communities | H17: Commercial | I17: Sales | L17: Sales | M17: Samar Mohamed Sona-Allah Mohamed | N17: 29610120200072 | O17: Sales Manager | P17: TM4-11379 | Q17: 2022-03-01 | R17: Middle Management | S17: 3 | T17: Manager | U17: 14 | V17: The MarQ Communities
A18: 60 | B18: Mohamed Mabrouk Ismail Mohamed | C18: mohamed.mabrouk@themarq.com.eg | D18: 01099262847 | E18: active | F18: The MarQ Communities | H18: Finance | I18: Accounting | J18: Accounts Receivable | L18: Accounts Receivable | M18: Efrayem Refaat Hanna Shalaby | N18: 28903030100471 | O18: Associate Accounts Receivable Manager | P18: TM4-8006 | Q18: 2019-10-01 | R18: Supervisory Management | S18: 4 | T18: Associate Manager | U18: 13 | V18: The MarQ Communities
A19: 63 | B19: Moustafa Salah Mohamed Hassan | C19: mostafa.salah@themarq.com.eg | D19: 01201082999 | E19: active | F19: The MarQ Communities | H19: Finance | I19: Accounting | L19: Accounting | M19: Efrayem Refaat Hanna Shalaby | N19: 28706040104017 | O19: Accounting Manager | P19: TM4-8005 | Q19: 2025-05-11 | R19: Middle Management | S19: 3 | T19: Manager | U19: 14 | V19: Maxim For Real Estate Investment
A20: 68 | B20: Omar Abdel Hamid Mahmoud Mohamed Elsginy | C20: omar.elseginy@themarq.com.eg | D20: 01015151552 | E20: active | F20: The MarQ Communities | H20: Commercial | I20: Sales | L20: Sales | M20: Daiana Youssef Yehia Youssef Greiss | N20: 29404230101852 | O20: Senior Sales Manager | P20: TM4-8041 | Q20: 2021-05-23 | R20: Middle Management | S20: 3 | T20: Senior Manager | U20: 15 | V20: The MarQ Communities
A21: 73 | B21: Samar Mohamed Sona-Allah Mohamed | C21: samar.sonaallah@themarq.com.eg | D21: 01008395000 | E21: active | F21: The MarQ Communities | H21: Commercial | I21: Sales | L21: Sales | M21: Mohamed Ibrahim Ibrahim Darwiesh | N21: 29203103500068 | O21: Associate Sales Director | P21: TM4-11375 | Q21: 2022-03-01 | R21: Middle Management | S21: 3 | T21: Associate Director | U21: 16 | V21: The MarQ Communities
A22: 74 | B22: Sameh Mahmoud Mohamed Khamis | C22: sameh.mohamed@themarq.com.eg | D22: 01118629856 - 01281537420 | E22: active | F22: The MarQ Communities | H22: Finance | I22: Accounting | J22: General | L22: General | M22: Mohamed Mabrouk Ismail Mohamed | N22: 29504240101537 | O22: Executive Accountant | P22: TM4-8044 | Q22: 2021-06-21 | R22: Professional | S22: 5 | T22: Specialist | U22: 8 | V22: The MarQ Communities
A23: 75 | B23: Sara Ahmed Ezz eldin Moursy Abu elabbas | C23: sara.ezzo@themarq.com.eg | D23: 01005293911 | E23: active | F23: The MarQ Communities | H23: Commercial | I23: Sales | L23: Sales | M23: Omar Abdel Hamid Mahmoud Mohamed Elsginy | N23: 29006098800147 | O23: Senior Sales Manager | P23: TM4-11576 | Q23: 2022-04-10 | R23: Middle Management | S23: 3 | T23: Senior Manager | U23: 15 | V23: The MarQ Communities
A24: 76 | B24: Shady Ahmed Mohamed Mostafa | C24: shady.elkadry@themarq.com.eg | D24: 01155774442 | E24: active | F24: The MarQ Communities | H24: Commercial | I24: Sales | L24: Sales | M24: Sara Ahmed Ezz eldin Moursy Abu elabbas | N24: 29302070108912 | O24: Associate Sales Manager | P24: TM4-8038 | Q24: 2021-05-23 | R24: Supervisory Management | S24: 4 | T24: Associate Manager | U24: 13 | V24: The MarQ Communities
A25: 78 | B25: Sherifa Ehab Helmy Ibrahim Abuzaid | C25: sherifa.ehab@themarq.com.eg | D25: 01027781928 | E25: active | F25: The MarQ Communities | H25: Finance | I25: Credit Control | L25: Credit Control | M25: Ahmed Mohamed Adel Taha Abdelaal | N25: 29806040103302 | O25: Credit Control Supervisor | P25: TM4-10656 | Q25: 2021-11-15 | R25: Professional | S25: 5 | T25: Supervisor | U25: 10 | V25: The MarQ Communities
A26: 99 | B26: Abdelrahman Mohamed Saad Ahmed | C26: abdelrahman.saad@themarq.com.eg | D26: 01150812762 | E26: active | F26: The MarQ Communities | H26: Finance | I26: Accounting | J26: Accounts Receivable | L26: Accounts Receivable | M26: Mohamed Mabrouk Ismail Mohamed | N26: 29706030101218 | O26: Accounts Receivable Supervisor | P26: TM4-1038 | Q26: 2020-07-01 | R26: Professional | S26: 5 | T26: Supervisor | U26: 10 | V26: The MarQ Communities
A27: 100 | B27: Hamed Ramadan Aliu Abdel Aal | C27: hamed.ramadan@themarq.com.eg | D27: 01020405978 | E27: active | F27: The MarQ Communities | H27: Treasury | L27: Treasury | M27: Salma Mohamed Youssry Mohamed Abdelmoniem Serry | N27: 30009122700412 | O27: Treasury Supervisor | P27: TM4-12115 | Q27: 2022-07-01 | R27: Professional | S27: 5 | T27: Supervisor | U27: 10 | V27: The MarQ Communities
A28: 124 | B28: Aida Fouad Mohamed Kamal | C28: aida.fouad@themarq.com.eg | D28: 01143003133 | E28: active | F28: The MarQ Communities | H28: Finance | I28: Accounting | J28: General | K28: Administration | L28: Administration | M28: Efrayem Refaat Hanna Shalaby | N28: 29203022102441 | O28: Executive Finance Admin | P28: TM4-3716 | Q28: 2022-10-16 | R28: Professional | S28: 5 | T28: Specialist | U28: 8 | V28: The MarQ Communities
A29: 135 | B29: Toka Khaled Farouk Hassan Hagag | C29: toka.khaled@themarq.com.eg | D29: 01156052000 | E29: active | F29: The MarQ Communities | G29: The Address Holding | H29: Human Resources | I29: HR Business Partner | J29: HR Operations | L29: HR Operations | M29: Salma Amr Mohamed Shafiek | N29: 30008170104647 | O29: HR Operations Supervisor | P29: TM4-12707 | Q29: 2024-03-17 | R29: Professional | S29: 5 | T29: Supervisor | U29: 10 | V29: The MarQ Communities
A30: 152 | B30: Aya Karim Thomas Konstantin | C30: aya.vayoniti@themarq.com.eg | D30: 01001051508 | E30: active | F30: The MarQ Communities | H30: Development & Innovation | I30: Research & Development | L30: Research & Development | M30: Omar Anas Abdel Fattah Lasheen | N30: 29309280108103 | O30: Research & Development Manager | P30: TM4-13037 | Q30: 2022-12-15 | R30: Middle Management | S30: 3 | T30: Manager | U30: 14 | V30: The MarQ Communities
A31: 172 | B31: Karim Ahmed Ghareeb elshahat | C31: karim.elshahat@themarq.com.eg | D31: 01159703568 | E31: active | F31: The MarQ Communities | H31: Projects | I31: Document Control | L31: Document Control | M31: Mohamed Elsayed Shamata Abdelbaky | N31: 29701260101339 | O31: Senior Document Controller | P31: TM4-13168 | Q31: 2023-01-15 | R31: Professional | S31: 5 | T31: Senior Specialist | U31: 9 | V31: The MarQ Communities
A32: 176 | B32: Mostafa Ahmed Mostafa Mohamed | C32: mostafa.elabbasi@themarq.com.eg | D32: 01280180303 | E32: active | F32: The MarQ Communities | H32: Projects | I32: Construction Management | L32: Construction Management | M32: Mohamed Elsayed Shamata Abdelbaky | N32: 28109060100397 | O32: Project Director | P32: TM4-13203 | Q32: 2023-01-15 | R32: Executive Management | S32: 2 | T32: Director | U32: 17 | V32: The MarQ Communities
A33: 186 | B33: Nour Eldin Fathy Mohamed Khaky | C33: nour.fathy@themarq.com.eg | D33: 01029867676 | E33: active | F33: The MarQ Communities | H33: Development & Innovation | I33: Design Review | J33: Urban | L33: Urban | M33: Ahmed Shawky Shaaban Hassan | N33: 29204200103916 | O33: Associate Urban Design Review Manager | P33: TM4-13328 | Q33: 2023-02-01 | R33: Supervisory Management | S33: 4 | T33: Associate Manager | U33: 13 | V33: The MarQ Communities
A34: 187 | B34: Reem Fawzy Ibrahim Soliman | C34: reem.elhalawany@themarq.com.eg | D34: 010026117621 | E34: active | F34: The MarQ Communities | H34: Development & Innovation | I34: Development | L34: Development | M34: Omar Anas Abdel Fattah Lasheen | N34: 29001160101704 | O34: Senior Development Manager | P34: TM4-13207 | Q34: 2023-02-01 | R34: Middle Management | S34: 3 | T34: Senior Manager | U34: 15 | V34: The MarQ Communities
A35: 226 | B35: Maria Maged Kamal Halim | C35: maria.halim@themarq.com.eg | D35: 01283932707 | E35: active | F35: The MarQ Communities | H35: Development & Innovation | I35: Development | L35: Development | M35: Perihan Osama Abdelazim Sharaf | N35: 29702020101869 | O35: Development Section Head | P35: TM4-11556 | Q35: 2022-04-10 | R35: Supervisory Management | S35: 4 | T35: Section Head | U35: 12 | V35: The MarQ Communities
A36: 228 | B36: Hosny Magdy Hosny Abdel Baqi | C36: hosny.magdy@themarq.com.eg | D36: 01113108000 | E36: active | F36: The MarQ Communities | H36: Commercial | I36: Sales | L36: Sales | M36: Samar Mohamed Sona-Allah Mohamed | N36: 28605212102851 | O36: Senior Property Consultant | P36: TM4-1405 | Q36: 2023-06-04 | R36: Professional | S36: 5 | T36: Senior Specialist | U36: 9 | V36: The MarQ Communities
A37: 231 | B37: Ahmed Elhussini Abdelwahed Ahmed | C37: ahmed.elhussini@themarq.com.eg | D37: 01030369917 | E37: active | F37: The MarQ Communities | H37: Communities & Clients Excellence | I37: Business Support | L37: Business Support | M37: Yasmine Marzouk Sayed mohamed | N37: 27812090104094 | O37: Senior Business Support Specialist | P37: TM4-15424 | Q37: 2023-06-15 | R37: Professional | S37: 5 | T37: Senior Specialist | U37: 9 | V37: The MarQ Communities
A38: 233 | B38: Mohamed DiaaElDin Ahmed Shehata ElShamy | C38: mohamed.diaa@themarq.com.eg | D38: 01002751606 | E38: active | F38: The MarQ Communities | H38: Commercial | I38: Sales Operations | L38: Sales Operations | M38: Ayman Mohamed Refaat Ahmed | N38: 28807110101593 | O38: Sales Operations Section Head | P38: TM4-15410 | Q38: 2023-06-15 | R38: Supervisory Management | S38: 4 | T38: Section Head | U38: 12 | V38: The MarQ Communities
A39: 234 | B39: Tarnem Mohamed Mohamed El sherbini | C39: tarneem.mohamed@themarq.com.eg | D39: 01027390399 | E39: active | F39: The MarQ Communities | H39: Commercial | I39: Sales | L39: Sales | M39: Mazen Adnan Ahmed Mostafa Elshamy | N39: 28911180300048 | O39: Sales Supervisor | P39: TM4-1255 | Q39: 2025-11-09 | R39: Professional | S39: 5 | T39: Supervisor | U39: 10 | V39: The MarQ Communities
A40: 237 | B40: Maged Mostafa morsi attia | C40: maged.mostafa@themarq.com.eg | D40: 01224298898 | E40: active | F40: The MarQ Communities | H40: Projects | I40: Construction Management | J40: Construction Project Management | L40: Construction Project Management | M40: Mostafa Ahmed Mostafa Mohamed | N40: 28301188800675 | O40: Senior Project Manager | P40: TM4-15486 | Q40: 2023-07-09 | R40: Middle Management | S40: 3 | T40: Senior Manager | U40: 15 | V40: The MarQ Communities
A41: 239 | B41: Mennat Allah ihab Mohammed hanafy | C41: menna.ihab@themarq.com.eg | D41: 01016911128 | E41: active | F41: The MarQ Communities | H41: Commercial | I41: Sales | L41: Sales | M41: Shady Ahmed Mohamed Mostafa | N41: 29304140102308 | O41: Sales Supervisor | P41: TM4-15605 | Q41: 2023-07-09 | R41: Professional | S41: 5 | T41: Supervisor | U41: 10 | V41: The MarQ Communities
A42: 242 | B42: Yasmine Marzouk Sayed mohamed | C42: yasmine.marzouk@themarq.com.eg | D42: 01111858403 | E42: active | F42: The MarQ Communities | H42: Communities & Clients Excellence | I42: Client Relations & Community Experience | J42: Clients Relations | L42: Clients Relations | M42: Abdelrahman Eid Abdelgaffar Abdullah | N42: 29004012100323 | O42: Clients Relations Manager | P42: TM4-15492 | Q42: 2023-07-09 | R42: Middle Management | S42: 3 | T42: Manager | U42: 14 | V42: The MarQ Communities
A43: 245 | B43: Karim ayman ahmed helmy | C43: karim.ayman@themarq.com.eg | D43: 01119961995 | E43: active | F43: The MarQ Communities | H43: Finance | I43: Credit Control | L43: Credit Control | M43: Ahmed Hamdy Mohamed Abdelftah Mostafa Awaimar | N43: 29501028800272 | O43: Credit Control Supervisor | P43: TM4-15717 | Q43: 2023-07-17 | R43: Professional | S43: 5 | T43: Supervisor | U43: 10 | V43: The MarQ Communities
A44: 258 | B44: Farah Alaa Mohammed Menshawy | C44: farah.elmenshawi@themarq.com.eg | D44: 1000509917 | E44: active | F44: The MarQ Communities | H44: Commercial | I44: Sales | L44: Sales | M44: Mazen Adnan Ahmed Mostafa Elshamy | N44: 29307092101981 | O44: Sales Supervisor | P44: TM4-9029 | Q44: 2021-01-31 | R44: Professional | S44: 5 | T44: Supervisor | U44: 10 | V44: The MarQ Communities
A45: 265 | B45: eslam fathy abdelhamid mohamed | C45: eslam.fathyy@themarq.com.eg | D45: 01090348691 | E45: active | F45: The MarQ Communities | H45: Finance | I45: Accounting | J45: Accounts Receivable | L45: Accounts Receivable | M45: Mohamed Mabrouk Ismail Mohamed | N45: 29409150101675 | O45: Accounts Receivable Supervisor | P45: TM4-16864 | Q45: 2023-10-01 | R45: Professional | S45: 5 | T45: Supervisor | U45: 10 | V45: The MarQ Communities
A46: 273 | B46: Mohamed Shehata Kamel Abdelghany | C46: mohameed.shehata@themarq.com.eg | D46: 01064076531 | E46: active | F46: The MarQ Communities | H46: Projects | I46: Construction Management | J46: Construction Project Management | K46: Site Supervision | L46: Site Supervision | M46: Mohamed Mahmoud Ahmed ElBelawey | N46: 28406052300471 | O46: Site Supervisor II | P46: TM4-17265 | Q46: 2023-11-05 | R46: Basic | S46: 6 | T46: Junior Specialist - Worker Senior supervisor | U46: 7 | V46: The MarQ Communities
A47: 279 | B47: Abdelaziz Ali Bakr Abdelaziz | C47: abdalaziz.saiif@themarq.com.eg | D47: 01128330367 | E47: active | F47: The MarQ Communities | H47: Projects | I47: Construction Management | J47: Construction Project Management | K47: Construction Document Control | L47: Construction Document Control | M47: Maged Mostafa morsi attia | N47: 29910108800777 | O47: Executive Construction Document Controller | P47: TM4-17750 | Q47: 2023-12-03 | R47: Professional | S47: 5 | T47: Specialist | U47: 8 | V47: The MarQ Communities
A48: 288 | B48: Ahmed kamal El Din Hassan El Khateeb | C48: ahmed.elkhateeb@themarq.com.eg | D48: 01110005077 | E48: active | F48: The MarQ Communities | H48: Commercial | I48: Sales | L48: Sales | M48: Mazen Adnan Ahmed Mostafa Elshamy | N48: 29405088800051 | O48: Associate Sales Manager | P48: TM4-3227 | Q48: 2023-12-10 | R48: Supervisory Management | S48: 4 | T48: Associate Manager | U48: 13 | V48: The MarQ Communities
A49: 289 | B49: Assem Adel Abdelaziz Amin Seheem | C49: aasem.sehim@themarq.com.eg | D49: 1146677789 | E49: active | F49: The MarQ Communities | H49: Commercial | I49: Sales | L49: Sales | M49: Mazen Adnan Ahmed Mostafa Elshamy | N49: 29804220103871 | O49: Senior Property Consultant | P49: TM4-12659 | Q49: 2022-10-16 | R49: Professional | S49: 5 | T49: Senior Specialist | U49: 9 | V49: The MarQ Communities
A50: 292 | B50: Mohamed Osama Hassan Moussa | C50: mohamed.osama@themarq.com.eg | D50: 011113086802 | E50: active | F50: The MarQ Communities | H50: Projects | I50: Construction Management | J50: Construction Project Management | L50: Construction Project Management | M50: Mostafa Ahmed Mostafa Mohamed | N50: 28909252105372 | O50: Associate Project Manager | P50: TM4-17920 | Q50: 2024-01-01 | R50: Supervisory Management | S50: 4 | T50: Associate Manager | U50: 13 | V50: The MarQ Communities
A51: 295 | B51: MennatAllah Yahya Mohamed Tawfik Ahmed Abdul Aziz | C51: menna.yahya@themarq.com.eg | D51: 01005397775 | E51: active | F51: The MarQ Communities | H51: Commercial | I51: Business Development | L51: Business Development | M51: Amr Mohamed Abdel-Hay Badr | N51: 28608310101366 | O51: Business Development Director | P51: TM4-15460 | Q51: 2023-07-04 | R51: Executive Management | S51: 2 | T51: Director | U51: 17 | V51: The MarQ Communities
A52: 296 | B52: Randa Mohamed Abdel Moneim Fayad | C52: randa.fayad@themarq.com.eg | D52: 01001070827 | E52: active | F52: The MarQ Communities | H52: Development & Innovation | I52: Development Pricing | L52: Development Pricing | M52: Omar Anas Abdel Fattah Lasheen | N52: 29108010103449 | O52: Senior Development Pricing Manager | P52: TM4-8027 | Q52: 2021-01-12 | R52: Middle Management | S52: 3 | T52: Senior Manager | U52: 15 | V52: The MarQ Communities
A53: 297 | B53: Heba Magdy Elbialy Hashish | C53: heba.hashish@themarq.com.eg | D53: 01005669889 | E53: active | F53: The MarQ Communities | H53: Commercial | I53: Business Development | L53: Business Development | M53: MennatAllah Yahya Mohamed Tawfik Ahmed Abdul Aziz | N53: 28901241200526 | O53: Business Development Manager | P53: TM4-17254 | Q53: 2023-11-01 | R53: Middle Management | S53: 3 | T53: Manager | U53: 14 | V53: The MarQ Communities
A54: 299 | B54: Lana Hany Mohamed Kamal Afifi | C54: lana.afifi@themarq.com.eg | D54: 01111005349 | E54: active | F54: The MarQ Communities | H54: Development & Innovation | I54: Development Pricing | L54: Development Pricing | M54: Randa Mohamed Abdel Moneim Fayad | N54: 30002021311828 | O54: Development Pricing Supervisor | P54: TM4-17255 | Q54: 2023-11-01 | R54: Professional | S54: 5 | T54: Supervisor | U54: 10 | V54: The MarQ Communities
A55: 300 | B55: Ahmed Medhat Sayed Baioumy el Atbany | C55: ahmed.medhat@themarq.com.eg | D55: 01285342768 | E55: active | F55: The MarQ Communities | H55: Investment | L55: Investment | M55: Efrayem Refaat Hanna Shalaby | N55: 29002222102733 | O55: Senior Investment Manager | P55: TM4-8036 | Q55: 2021-05-06 | R55: Middle Management | S55: 3 | T55: Senior Manager | U55: 15 | V55: The MarQ Communities
A56: 301 | B56: Ahmed Raouf Abdel Menaam Hanafy | C56: ahmed.raouf@themarq.com.eg | D56: 1277300584 | E56: active | F56: The MarQ Communities | H56: Commercial | I56: Business Development | L56: Business Development | M56: MennatAllah Yahya Mohamed Tawfik Ahmed Abdul Aziz | N56: 28507150107213 | O56: Associate Business Development Manager | P56: TM4-9062 | Q56: 2021-08-22 | R56: Supervisory Management | S56: 4 | T56: Associate Manager | U56: 13 | V56: The MarQ Communities
A57: 303 | B57: Eleonora Christo Paraskevas Vostanis | C57: eleonora.christo@themarq.com.eg | D57: 01001483748 | E57: active | F57: The MarQ Communities | H57: Marketing & PR | I57: Brand Strategy | J57: Content Writing | L57: Content Writing | M57: Noha Hassan Sabry Mohamed Ibrahim | N57: 30002140100061 | O57: Junior Content Writer | P57: TM4-16669 | Q57: 2023-09-14 | R57: Basic | S57: 6 | T57: Junior Specialist - Worker Senior supervisor | U57: 7 | V57: The MarQ Communities
A58: 307 | B58: Mahmoud Samy Mohamed El Meligy | C58: mahmoud.samy@themarq.com.eg | D58: 01274772894 | E58: active | F58: The MarQ Communities | H58: Commercial | I58: Sales | L58: Sales | M58: Shady Ahmed Mohamed Mostafa | N58: 29304052102519 | O58: Sales Supervisor | P58: TM4-1883 | Q58: 2025-09-01 | R58: Professional | S58: 5 | T58: Supervisor | U58: 10 | V58: The MarQ Communities
A59: 312 | B59: Mohab Ahmed Mohamed Amin | C59: mohab.amin@themarq.com.eg | D59: 01001018738 | E59: active | F59: The MarQ Communities | H59: Development & Innovation | I59: Development | L59: Development | M59: Reem Fawzy Ibrahim Soliman | N59: 29304138800154 | O59: Development Manager | P59: TM4-13357 | Q59: 2023-02-01 | R59: Middle Management | S59: 3 | T59: Manager | U59: 14 | V59: The MarQ Communities
A60: 316 | B60: Moustafa Mohamed Mohamed El Assal | C60: mostafa.elassal@themarq.com.eg | D60: 1000774065 | E60: active | F60: The MarQ Communities | H60: CEO Office | L60: CEO Office | M60: Amr Mohamed Abdel-Hay Badr | N60: 28805020103314 | O60: Deputy CEO | P60: TM4-9005 | Q60: 2019-09-01 | R60: Top Management | S60: 1 | T60: CEOs -Board Member | U60: 21 | V60: The MarQ Communities
A61: 319 | B61: Omar Anas Abdel Fattah Lasheen | C61: omar.lasheen@themarq.com.eg | D61: 1008485582 | E61: active | F61: The MarQ Communities | H61: CEO Office | L61: CEO Office | M61: Amr Mohamed Abdel-Hay Badr | N61: 29205050103811 | O61: Deputy CEO | P61: TM4-9004 | Q61: 2021-01-01 | R61: Top Management | S61: 1 | T61: CEOs -Board Member | U61: 21 | V61: The MarQ Communities
A62: 320 | B62: Perihan Osama Abdelazim Sharaf | C62: perihan.sharaf@themarq.com.eg | D62: 01227800419 | E62: active | F62: The MarQ Communities | H62: Development & Innovation | I62: Development | L62: Development | M62: Omar Anas Abdel Fattah Lasheen | N62: 29409302104446 | O62: Senior Development Manager | P62: TM4-16011 | Q62: 2025-05-05 | R62: Middle Management | S62: 3 | T62: Senior Manager | U62: 15 | V62: The MarQ Communities
A63: 323 | B63: Sandra Atallah Fouad Benjamin | C63: sandra.benjamin@themarq.com.eg | D63: 1274985641 | E63: active | F63: The MarQ Communities | H63: Development & Innovation | I63: Innovation & Product Development | L63: Innovation & Product Development | M63: Omar Anas Abdel Fattah Lasheen | N63: 29807270103561 | O63: Innovation & Product Development Manager | P63: TM4-9022 | Q63: 2020-07-06 | R63: Middle Management | S63: 3 | T63: Manager | U63: 14 | V63: The MarQ Communities
A64: 352 | B64: Mohamed Nezar Ibrahim Abou Elfetouh | C64: mohamed.nezar@themarq.com.eg | D64: 01234525900 | E64: active | F64: The MarQ Communities | H64: Communities & Clients Excellence | I64: Community Operations | L64: Community Operations | M64: Amr Mohamed Abdel-Hay Badr | N64: 28911202100897 | O64: Senior Community Operations Director | P64: TM4-18456 | Q64: 2024-02-01 | R64: Executive Management | S64: 2 | T64: Senior Director | U64: 18 | V64: The MarQ Communities
A65: 359 | B65: Fady Fayek Fouad Rezk | C65: fady.rezk@themarq.com.eg | D65: 01284939672 | E65: active | F65: The MarQ Communities | H65: Commercial | I65: Sales | L65: Sales | M65: Mazen Adnan Ahmed Mostafa Elshamy | N65: 29709282101333 | O65: Senior Property Consultant | P65: TM4-12201 | Q65: 2024-02-11 | R65: Professional | S65: 5 | T65: Senior Specialist | U65: 9 | V65: The MarQ Communities
A66: 376 | B66: Samir Mansour Mohamed Ahmed | C66: samir.mansour@themarq.com.eg | D66: 01008893317 | E66: active | F66: The MarQ Communities | H66: Projects | I66: Document Control | L66: Document Control | M66: Mohamed Elsayed Shamata Abdelbaky | N66: 28705211400853 | O66: Document Control Manager | P66: TM4-18696 | Q66: 2024-02-05 | R66: Middle Management | S66: 3 | T66: Manager | U66: 14 | V66: The MarQ Communities
A67: 377 | B67: Shady Amir Ahmed Mirdan | C67: shady.amir@themarq.com.eg | D67: 01069121035 | E67: active | F67: The MarQ Communities | H67: Projects | I67: Construction Management | J67: Construction Project Management | K67: Site Supervision | L67: Site Supervision | M67: Maged Mostafa morsi attia | N67: 27610060300156 | O67: Site Supervisor III | P67: TM4-18704 | Q67: 2024-02-06 | R67: Professional | S67: 5 | T67: Specialist | U67: 8 | V67: The MarQ Communities
A68: 378 | B68: Waleed Mohamed Hassan Ali | C68: walid.mohamed@themarq.com.eg | D68: 01000289776 | E68: active | F68: The MarQ Communities | H68: Communities & Clients Excellence | I68: Community Safety & Security | L68: Community Safety & Security | M68: Baher Saeed Khamis Mahmoud Elshamy | N68: 27312061200073 | O68: Security Manager | P68: TM4-18958 | Q68: 2024-02-15 | R68: Professional | S68: 5 | T68: Senior Specialist | U68: 9 | V68: The MarQ Communities
A69: 452 | B69: Abdelhameed Mahmoud Abdelhameed Saleh | C69: a.saleh@themarq.com.eg | D69: 01005325045 | E69: active | F69: The MarQ Communities | H69: Internal Audit | L69: Internal Audit | M69: Amr Mohamed Abdel-Hay Badr | N69: 27105252102513 | O69: Chief Internal Audit Officer / Board Member | P69: TM4-11423 | Q69: 2022-03-10 | R69: Top Management | S69: 1 | T69: Chief Officer | U69: 20 | V69: The MarQ Communities
A70: 721 | B70: Ahmed Mohamed Mohamed Salem | C70: ahmed.nafie@themarq.com.eg | D70: 01000198526 | E70: active | F70: The MarQ Communities | H70: Corporate Operational Excellence | L70: Corporate Operational Excellence | M70: Moustafa Mohamed Mohamed El Assal | N70: 29008100100134 | O70: Corporate Operational Excellence Director | P70: TM4-12308 | Q70: 2022-09-04 | R70: Executive Management | S70: 2 | T70: Director | U70: 17 | V70: The MarQ Communities
A71: 802 | B71: Ahmed elsayed elsayed elshiaty | C71: ahmed.elshiaty@themarq.com.eg | D71: 01006856836 | E71: active | F71: The MarQ Communities | H71: Human Resources | I71: Learning & Development | L71: Learning & Development | M71: Sylvia Nabih Doss Abd Allah | N71: 28608011608012 | O71: Learning & Development Director | P71: TM4-17746 | Q71: 2023-12-03 | R71: Executive Management | S71: 2 | T71: Director | U71: 17 | V71: The MarQ Communities
A72: 904 | B72: Amira Tarek Mohamed Abdelmutaal Ali El Sherkawy | C72: amira.tareq@themarq.com.eg | D72: 01005353396 | E72: active | F72: The MarQ Communities | H72: Commercial | I72: Sales | L72: Sales | M72: Mahmoud Amr Mahmoud Kamel Rashad Tawakol | N72: 29601251200125 | O72: Senior Property Consultant | P72: TM4-15065 | Q72: 2025-11-02 | R72: Professional | S72: 5 | T72: Senior Specialist | U72: 9 | V72: The MarQ Communities
A73: 927 | B73: Amr Mohamed Abdel-Hay Badr | C73: amr.badr@themarq.com.eg | D73: 1007607215 | E73: active | F73: The MarQ Communities | H73: CEO Office | L73: CEO Office | M73: Donia Helal | N73: 28510148800379 | O73: CEO | P73: TM4-9001 | Q73: 2016-03-01 | R73: Top Management | S73: 1 | T73: CEOs -Board Member | U73: 21 | V73: The MarQ Communities
A74: 1008 | B74: Aya Mohamed Gamal ELdin Elshemy | C74: aya.elshemy@themarq.com.eg | D74: 01032929299 | E74: active | F74: The MarQ Communities | H74: Commercial | I74: Business Support | L74: Business Support | M74: Amr Mohamed Abdel-Hay Badr | N74: 29212090102288 | O74: Business Support Manager | P74: TM4-2040 | Q74: 2023-07-09 | R74: Middle Management | S74: 3 | T74: Manager | U74: 14 | V74: The MarQ Communities
A75: 1138 | B75: Efrayem Refaat Hanna Shalaby | C75: efrayem.refaat@themarq.com.eg | D75: 01287373523 | E75: active | F75: The MarQ Communities | H75: Investment | L75: Investment | M75: Amr Mohamed Abdel-Hay Badr | N75: 29110222500612 | O75: Chief Investment Officer | P75: TM4-14538 | Q75: 2023-03-05 | R75: Top Management | S75: 1 | T75: Chief Officer | U75: 20 | V75: The MarQ Communities
A76: 1888 | B76: Mayar Yasser Abdel Razek Ibrahim | C76: mayar.yasser@themarq.com.eg | D76: 01098452794 | E76: active | F76: The MarQ Communities | H76: Development & Innovation | I76: Research & Development | L76: Research & Development | M76: Aya Karim Thomas Konstantin | N76: 30006030104725 | O76: Senior Research & Development Specialist | P76: TM4-1069 | Q76: 2023-09-27 | R76: Professional | S76: 5 | T76: Senior Specialist | U76: 9 | V76: The MarQ Communities
A77: 1987 | B77: Meriam Atef Labib Asaad | C77: meriam.atef@themarq.com.eg | D77: 01211498779 | E77: active | F77: The MarQ Communities | H77: Commercial | I77: Sales | L77: Sales | M77: Ahmed Shawky Abdo El Bastawisy El Sahy | N77: 30011050105462 | O77: Property Consultant | P77: TM4-19013 | Q77: 2025-09-01 | R77: Professional | S77: 5 | T77: Specialist | U77: 8 | V77: The MarQ Communities
A78: 2500 | B78: Nariman Nabil Shohdy Zakria | C78: nariman.nabil@themarq.com.eg | D78: 01111148998 | E78: active | F78: The MarQ Communities | H78: Human Resources | I78: Learning & Development | J78: Employer Branding | L78: Employer Branding | M78: Ahmed elsayed elsayed elshiaty | N78: 29805260103145 | O78: Employer Branding Section Head | P78: TM4-17892 | Q78: 2024-01-08 | R78: Supervisory Management | S78: 4 | T78: Section Head | U78: 12 | V78: The MarQ Communities
A79: 2503 | B79: Nayera Ibrahim ElShabrawy Ibrahim | C79: nayera.elshabrawy@themarq.com.eg | D79: 01226299986 | E79: active | F79: The MarQ Communities | H79: Marketing & PR | I79: Brand Strategy | L79: Brand Strategy | M79: Soha Sabry Aziz Nakola | N79: 28610270104248 | O79: Senior Marketing Manager | P79: TM4-9045 | Q79: 2021-06-01 | R79: Middle Management | S79: 3 | T79: Senior Manager | U79: 15 | V79: The MarQ Communities
A80: 2588 | B80: Nourhan yasser Hamed Elmoaz | C80: nourhan.yasser@themarq.com.eg | D80: 01000461636 | E80: active | F80: The MarQ Communities | H80: Commercial | I80: Business Development | L80: Business Development | M80: MennatAllah Yahya Mohamed Tawfik Ahmed Abdul Aziz | N80: 29304011708763 | O80: Business Development Supervisor | P80: TM4-12569 | Q80: 2022-10-02 | R80: Professional | S80: 5 | T80: Supervisor | U80: 10 | V80: The MarQ Communities
A81: 2692 | B81: Passant Magdy Abdel Razek Eliwa | C81: passant.magdy@themarq.com.eg | D81: 01099691693 | E81: active | F81: The MarQ Communities | H81: Human Resources | I81: Organization Development & Talent Management | L81: Organization Development & Talent Management | M81: Sylvia Nabih Doss Abd Allah | N81: 29101290102448 | O81: OD & Talent Management Director | P81: TM4-14720 | Q81: 2023-04-02 | R81: Executive Management | S81: 2 | T81: Director | U81: 17 | V81: The MarQ Communities
A82: 3100 | B82: Sylvia Nabih Doss Abd Allah | C82: sylvia.doss@themarq.com.eg | D82: 01226181018 | E82: active | F82: The MarQ Communities | H82: Human Resources | L82: Human Resources | M82: Amr Mohamed Abdel-Hay Badr | N82: 27402070100501 | O82: Chief Human Resources Officer | P82: TM4-11719 | Q82: 2022-05-15 | R82: Top Management | S82: 1 | T82: Chief Officer | U82: 20 | V82: The MarQ Communities
A83: 3354 | B83: heba ashraf youssef ibrahim | C83: heba.ashraf@themarq.com.eg | D83: 01204105555 | E83: active | F83: The MarQ Communities | H83: Marketing & PR | I83: Brand Strategy | L83: Brand Strategy | M83: Mirna Mamdouh Zaki Andrawes | N83: 30104040103885 | O83: Senior Marketing Specialist | P83: TM4-16641 | Q83: 2023-09-14 | R83: Professional | S83: 5 | T83: Senior Specialist | U83: 9 | V83: The MarQ Communities
A84: 3444 | B84: Diana Hossam Abdelrahman Osman | C84: diana.elsehemy@themarq.com.eg | D84: 01117139927 | E84: active | F84: The MarQ Communities | H84: Development & Innovation | I84: Design Management | L84: Design Management | M84: Ahmed Shawky Shaaban Hassan | N84: 29410160101183 | O84: Design Management Section Head | P84: TM4-19302 | Q84: 2024-03-10 | R84: Supervisory Management | S84: 4 | T84: Section Head | U84: 12 | V84: The MarQ Communities
A85: 3479 | B85: Hania Ahmed Abdelmoez Ahmed | C85: hania.moez@themarq.com.eg | D85: 01111233006 | E85: active | F85: The MarQ Communities | H85: Marketing & PR | I85: Brand Strategy | J85: Graphic Design | L85: Graphic Design | M85: Noha Hassan Sabry Mohamed Ibrahim | N85: 29911150105546 | O85: Senior Graphic designer | P85: TM4-19332 | Q85: 2024-03-10 | R85: Professional | S85: 5 | T85: Senior Specialist | U85: 9 | V85: The MarQ Communities
A86: 3483 | B86: Ibrahim Abdelaziz Osama Ibrahim Hafez | C86: ibrahim.hafez@themarq.com.eg | D86: 01125796378 | E86: active | F86: The MarQ Communities | H86: Commercial | I86: Sales Operations | L86: Sales Operations | M86: Atef Rezk El Sayed El Sayed El Sabbagh | N86: 29612230104152 | O86: Executive Sales Operations Specialist | P86: TM4-19296 | Q86: 2024-03-10 | R86: Professional | S86: 5 | T86: Specialist | U86: 8 | V86: The MarQ Communities
A87: 3512 | B87: Mohamed Ahmed Ibrahim Youssef | C87: m.youssef@themarq.com.eg | E87: active | F87: The MarQ Communities | H87: Communities & Clients Excellence | I87: Community Operations | J87: Community Engineering | K87: Communication & Administration | L87: Communication & Administration | M87: Mohamed Nezar Ibrahim Abou Elfetouh | N87: 28905040102513 | O87: Associate Communication & Administration Manager | P87: TM4-19270 | Q87: 2024-03-01 | R87: Supervisory Management | S87: 4 | T87: Associate Manager | U87: 13 | V87: The MarQ Communities
A88: 3770 | B88: Abdelhakim Mohamed Ali Nasser | C88: abdelhakiem.mohamed@themarq.com.eg | D88: 01062227790 | E88: active | F88: The MarQ Communities | H88: Communities & Clients Excellence | I88: Community Operations | J88: Facility Management | K88: Community MEP | L88: Community MEP | M88: Mohamed Magdy Elsaeed Elfiky | N88: 26702052701735 | O88: Senior Community MEP Supervisor | P88: TM4-19571 | Q88: 2024-03-05 | R88: Basic | S88: 6 | T88: Junior Specialist - Worker Senior supervisor | U88: 7 | V88: The MarQ Communities
A89: 3772 | B89: Abdelrahman Amer Abdelrahman Ahmed | C89: abdelrhman.amer@themarq.com.eg | D89: 01067880457 | E89: active | F89: The MarQ Communities | H89: Communities & Clients Excellence | I89: Client Relations & Community Experience | J89: Clients Relations | L89: Clients Relations | M89: Seif Mohamed Abd El Halim | N89: 29602210101259 | O89: Executive Clients Relations Specialist | P89: TM4-19766 | Q89: 2025-04-17 | R89: Professional | S89: 5 | T89: Specialist | U89: 8 | V89: The MarQ Communities
A90: 3941 | B90: Nabil Hamed Metwaly Mohamed | C90: nabil.elshabany@themarq.com.eg | D90: 01092727849 | E90: active | F90: The MarQ Communities | H90: Communities & Clients Excellence | I90: Community Operations | J90: Community Engineering | L90: Community Engineering | M90: Mohamed Ahmed Ibrahim Youssef | N90: 29105101100273 | O90: Community Engineering Teamleader | P90: TM4-19739 | Q90: 2025-05-11 | R90: Supervisory Management | S90: 4 | T90: Teamleader | U90: 11 | V90: The MarQ Communities
A91: 4028 | B91: Mohamed Abdelfattah Saeed Abdelmaged | C91: mohamed.abdelfattah@themarq.com.eg | D91: 01150981043 | E91: active | F91: The MarQ Communities | H91: Communities & Clients Excellence | I91: Client Relations & Community Experience | J91: Community Experience | K91: Community Quality Control | L91: Community Quality Control | M91: Ahmed Osama Roshdy Abdelgawad | N91: 29810180100572 | O91: Senior Community Quality Control Specialist | P91: TM4-19875 | Q91: 2024-04-17 | R91: Professional | S91: 5 | T91: Senior Specialist | U91: 9 | V91: The MarQ Communities
A92: 4098 | B92: Mostafa Ali Abdelmohsen Mohamed | C92: mostafa.ali@themarq.com.eg | D92: 01140171761 | E92: active | F92: The MarQ Communities | G92: The Address Holding | H92: Finance | I92: Accounting | J92: General | L92: General | M92: Efrayem Refaat Hanna Shalaby | N92: 29709270102318 | O92: Executive Accountant | P92: TM4-19906 | Q92: 2024-05-01 | R92: Professional | S92: 5 | T92: Specialist | U92: 8 | V92: Maxim For Real Estate Investment
A93: 4247 | B93: Gihan Mohamed Labib Abdelbasset Auf | C93: gihan.auf@themarq.com.eg | D93: 01152488862 | E93: active | F93: The MarQ Communities | H93: Marketing & PR | I93: Brand Strategy | L93: Brand Strategy | M93: Nayera Ibrahim ElShabrawy Ibrahim | N93: 29511180101245 | O93: Associate Marketing Manager | P93: TM4-20298 | Q93: 2024-05-15 | R93: Supervisory Management | S93: 4 | T93: Associate Manager | U93: 13 | V93: The MarQ Communities
A94: 4321 | B94: Mohamed Fawzy Ragab Ali | C94: mohamed.fawzy@themarq.com.eg | D94: 01001545653 | E94: active | F94: The MarQ Communities | H94: Communities & Clients Excellence | I94: Communication Center | L94: Communication Center | M94: Moustafa Mohamed Mohamed El Assal | N94: 28701011421176 | O94: Communication Center Director | P94: TM4-20070 | Q94: 2024-05-01 | R94: Executive Management | S94: 2 | T94: Director | U94: 17 | V94: The MarQ Communities
A95: 4353 | B95: Mostafa Fahim Hamdy Ellaithy | C95: mostafa.m.ellaithy@themarq.com.eg | D95: 01002528283 | E95: active | F95: The MarQ Communities | H95: Development & Innovation | I95: Design Review | J95: MEP | L95: MEP | M95: Ahmed Shawky Shaaban Hassan | N95: 29005142103355 | O95: MEP Design Review Section Head | P95: TM4-20208 | Q95: 2024-05-01 | R95: Supervisory Management | S95: 4 | T95: Section Head | U95: 12 | V95: The MarQ Communities
A96: 4414 | B96: Sondos Abdelaziz Mohamed Abdelaziz | C96: sondos.abdelaziz@themarq.com.eg | D96: 01100797081 | E96: active | F96: The MarQ Communities | H96: Marketing & PR | I96: Brand Strategy | J96: Graphic Design | L96: Graphic Design | M96: Noha Hassan Sabry Mohamed Ibrahim | N96: 29807282103664 | O96: Senior Graphic designer | P96: TM4-20303 | Q96: 2024-05-19 | R96: Professional | S96: 5 | T96: Senior Specialist | U96: 9 | V96: The MarQ Communities
A97: 4471 | B97: Baher Saeed Khamis Mahmoud Elshamy | C97: baher.elshamy@themarq.com.eg | D97: 01028333413 | E97: active | F97: The MarQ Communities | H97: Communities & Clients Excellence | I97: Community Safety & Security | L97: Community Safety & Security | M97: Moustafa Mohamed Mohamed El Assal | N97: 27912010111693 | O97: Senior Community Safety & Security Director | P97: TM4-20296 | Q97: 2024-05-01 | R97: Executive Management | S97: 2 | T97: Senior Director | U97: 18 | V97: The MarQ Communities
A98: 4600 | B98: Ahmed Yasser Salah Mohamed | C98: ahmed.salah@themarq.com.eg | D98: 01118839985 | E98: active | F98: The MarQ Communities | H98: Commercial | I98: Sales | L98: Sales | M98: Ahmed Shawky Abdo El Bastawisy El Sahy | N98: 30009010104795 | O98: Senior Property Consultant | P98: TM4-20639 | Q98: 2025-09-01 | R98: Professional | S98: 5 | T98: Senior Specialist | U98: 9 | V98: The MarQ Communities
A99: 4681 | B99: Mohamed Magdy Elsaeed Elfiky | C99: mohamed.magdy@themarq.com.eg | D99: 01015526623 | E99: active | F99: The MarQ Communities | H99: Communities & Clients Excellence | I99: Community Operations | J99: Facility Management | K99: Community MEP | L99: Community MEP | M99: Ayman Mousa Haneen Mokbel | N99: 29601288800459 | O99: Community MEP Section Head | P99: TM4-20642 | Q99: 2024-06-01 | R99: Supervisory Management | S99: 4 | T99: Section Head | U99: 12 | V99: The MarQ Communities
A100: 4815 | B100: Ahmed Magdy Fekry Elhagaa | C100: a.magdi@themarq.com.eg | D100: 01024642618 | E100: active | F100: The MarQ Communities | H100: Human Resources | I100: Learning & Development | L100: Learning & Development | M100: Ahmed elsayed elsayed elshiaty | N100: 28801301700278 | O100: Learning & Development Manager | P100: TM4-21123 | Q100: 2024-07-02 | R100: Middle Management | S100: 3 | T100: Manager | U100: 14 | V100: The MarQ Communities
...

Sheet HC Email 1st
A1: id | B1: email | C1: full_name | D1: mobile | E1: status | F1: company | G1: franchise | H1: sector | L1: department | M1: parent | N1: identification_id | O1: position | P1: employee_code | Q1: hire_date | R1: payscale_cluster_name | S1: payscale_cluster_code | T1: job_level_name | U1: job_level_grade | V1: allocation_company
A2: 8 | B2: ahmed.hamdy@themarq.com.eg | C2: Ahmed Hamdy Mohamed Abdelftah Mostafa Awaimar | D2: 01004379643 | E2: active | F2: The MarQ Communities | H2: Finance | I2: Credit Control | L2: Credit Control | M2: Efrayem Refaat Hanna Shalaby | N2: 28706191401617 | O2: Credit Control Director | P2: TM4-8031 | Q2: 2021-02-15 | R2: Executive Management | S2: 2 | T2: Director | U2: 17 | V2: The MarQ Communities
A3: 11 | B3: ahmed.adel@themarq.com.eg | C3: Ahmed Mohamed Adel Taha Abdelaal | D3: 01228233334 | E3: active | F3: The MarQ Communities | H3: Finance | I3: Credit Control | L3: Credit Control | M3: Ahmed Hamdy Mohamed Abdelftah Mostafa Awaimar | N3: 28911221300091 | O3: Credit Control Manager | P3: TM4-8032 | Q3: 2021-02-17 | R3: Middle Management | S3: 3 | T3: Manager | U3: 14 | V3: The MarQ Communities
A4: 14 | B4: ahmed.abdelsatar@themarq.com.eg | C4: Ahmed Sayed Abdel Satar Elsayed | D4: 01005999810 | E4: active | F4: The MarQ Communities | H4: Commercial | I4: Sales Operations | L4: Sales Operations | M4: Ayman Mohamed Refaat Ahmed | N4: 28410100105631 | O4: Sales Operations Supervisor | P4: TM4-11458 | Q4: 2022-03-16 | R4: Professional | S4: 5 | T4: Supervisor | U4: 10 | V4: The MarQ Communities
A5: 16 | B5: alaa.omar@themarq.com.eg | C5: Alaa Essam Mohamed Ibrahim | D5: 01117559150 | E5: active | F5: The MarQ Communities | H5: Development & Innovation | I5: Design Review | J5: Urban | L5: Urban | M5: Nour Eldin Fathy Mohamed Khaky | N5: 29505308800168 | O5: Urban Design Review Teamleader | P5: TM4-11401 | Q5: 2022-03-13 | R5: Supervisory Management | S5: 4 | T5: Teamleader | U5: 11 | V5: The MarQ Communities
A6: 21 | B6: amr.ali@themarq.com.eg | C6: Amr Ali Abdelwahab Sobh | D6: 01092832193 | E6: active | F6: The MarQ Communities | H6: Development & Innovation | I6: Design Review | J6: Urban | L6: Urban | M6: Ahmed Shawky Shaaban Hassan | N6: 29310011210919 | O6: Urban Design Review Section Head | P6: TM4-8047 | Q6: 2021-08-01 | R6: Supervisory Management | S6: 4 | T6: Section Head | U6: 12 | V6: The MarQ Communities
A7: 22 | B7: amr.hany@themarq.com.eg | C7: Amr Hani Mohamed Abdel Latif | D7: 01062540976 | E7: active | F7: The MarQ Communities | H7: Development & Innovation | I7: Design Management | L7: Design Management | M7: Ahmed Shawky Shaaban Hassan | N7: 29211012108354 | O7: Senior Design Management Manager | P7: TM4-8016 | Q7: 2020-09-01 | R7: Middle Management | S7: 3 | T7: Senior Manager | U7: 15 | V7: The MarQ Communities
A8: 25 | B8: atef.rizk@themarq.com.eg | C8: Atef Rezk El Sayed El Sayed El Sabbagh | D8: 01150111783 | E8: active | F8: The MarQ Communities | H8: Commercial | I8: Sales Operations | L8: Sales Operations | M8: Ayman Mohamed Refaat Ahmed | N8: 28107232101614 | O8: Sales Operations Manager | P8: TM4-8002 | Q8: 2019-09-01 | R8: Middle Management | S8: 3 | T8: Manager | U8: 14 | V8: The MarQ Communities
A9: 26 | B9: ayman.refaat@themarq.com.eg | C9: Ayman Mohamed Refaat Ahmed | D9: 01090080320 | E9: active | F9: The MarQ Communities | H9: Commercial | I9: Sales Operations | L9: Sales Operations | M9: Amr Mohamed Abdel-Hay Badr | N9: 28209018800715 | O9: Senior Sales Operations Director | P9: TM4-8001 | Q9: 2019-09-01 | R9: Executive Management | S9: 2 | T9: Senior Director | U9: 18 | V9: The MarQ Communities
A10: 27 | B10: diana.greiss@themarq.com.eg | C10: Daiana Youssef Yehia Youssef Greiss | D10: 1001096061 | E10: active | F10: The MarQ Communities | H10: Commercial | I10: Sales | L10: Sales | M10: Amr Mohamed Abdel-Hay Badr | N10: 28707070102864 | O10: Senior Sales Director | P10: TM4-3643 | Q10: 2021-08-01 | R10: Executive Management | S10: 2 | T10: Senior Director | U10: 18 | V10: The MarQ Communities
A11: 32 | B11: gehad.badr@themarq.com.eg | C11: Gehad Badr El Sayed Bayoumi | D11: 01277237484 | E11: active | F11: The MarQ Communities | H11: Finance | I11: Accounting | J11: Accounts Receivable | L11: Accounts Receivable | M11: Mohamed Mabrouk Ismail Mohamed | N11: 29601102105284 | O11: Accounts Receivable Supervisor | P11: TM4-8010 | Q11: 2020-02-17 | R11: Professional | S11: 5 | T11: Supervisor | U11: 10 | V11: The MarQ Communities
A12: 33 | B12: hunya.yehia@themarq.com.eg | C12: Hania Yehia Abdelfattah Sabry | D12: 01125997743 | E12: active | F12: The MarQ Communities | H12: Finance | I12: Credit Control | L12: Credit Control | M12: Ahmed Mohamed Adel Taha Abdelaal | N12: 30007190103381 | O12: Senior Credit Control Specialist | P12: TM4-2197 | Q12: 2021-03-15 | R12: Professional | S12: 5 | T12: Senior Specialist | U12: 9 | V12: The MarQ Communities
A13: 35 | B13: hany.refaat@themarq.com.eg | C13: Hany Refaat Abdallah Mohamed | D13: 01156170952 | E13: active | F13: The MarQ Communities | H13: Finance | I13: Accounting | J13: Accounts Receivable | L13: Accounts Receivable | M13: Mohamed Mabrouk Ismail Mohamed | N13: 28108090100433 | O13: Accounts Receivable Teamleader | P13: TM4-11403 | Q13: 2022-03-10 | R13: Supervisory Management | S13: 4 | T13: Teamleader | U13: 11 | V13: The MarQ Communities
A14: 43 | B14: karim.elwishy@themarq.com.eg | C14: Karim Mohsen Ahmed Elweshey | D14: 01111229023 | E14: active | F14: The MarQ Communities | H14: Commercial | I14: Sales Operations | J14: Contracts | L14: Contracts | M14: Ayman Mohamed Refaat Ahmed | N14: 29203318800071 | O14: Senior Contracts Specialist | P14: TM4-8034 | Q14: 2021-04-01 | R14: Professional | S14: 5 | T14: Senior Specialist | U14: 9 | V14: The MarQ Communities
A15: 45 | B15: khaled.elmesilhy@themarq.com.eg | C15: Khaled Mohamed El-mesilhy Mohamed Ibrahim | D15: 01002277836 | E15: active | F15: The MarQ Communities | H15: Commercial | I15: Sales Operations | L15: Sales Operations | M15: Mohamed DiaaElDin Ahmed Shehata ElShamy | N15: 29111070103139 | O15: Sales Operations Supervisor | P15: TM4-11497 | Q15: 2022-03-22 | R15: Professional | S15: 5 | T15: Supervisor | U15: 10 | V15: The MarQ Communities
A16: 49 | B16: mahmoud.tawakol@themarq.com.eg | C16: Mahmoud Amr Mahmoud Kamel Rashad Tawakol | D16: 01008986995 | E16: active | F16: The MarQ Communities | H16: Commercial | I16: Sales | L16: Sales | M16: Daiana Youssef Yehia Youssef Greiss | N16: 29504030103073 | O16: Senior Sales Manager | P16: TM4-1707 | Q16: 2025-11-02 | R16: Middle Management | S16: 3 | T16: Senior Manager | U16: 15 | V16: The MarQ Communities
A17: 53 | B17: mazen.elshamy@themarq.com.eg | C17: Mazen Adnan Ahmed Mostafa Elshamy | D17: 01126099391 | E17: active | F17: The MarQ Communities | H17: Commercial | I17: Sales | L17: Sales | M17: Samar Mohamed Sona-Allah Mohamed | N17: 29610120200072 | O17: Sales Manager | P17: TM4-11379 | Q17: 2022-03-01 | R17: Middle Management | S17: 3 | T17: Manager | U17: 14 | V17: The MarQ Communities
A18: 60 | B18: mohamed.mabrouk@themarq.com.eg | C18: Mohamed Mabrouk Ismail Mohamed | D18: 01099262847 | E18: active | F18: The MarQ Communities | H18: Finance | I18: Accounting | J18: Accounts Receivable | L18: Accounts Receivable | M18: Efrayem Refaat Hanna Shalaby | N18: 28903030100471 | O18: Associate Accounts Receivable Manager | P18: TM4-8006 | Q18: 2019-10-01 | R18: Supervisory Management | S18: 4 | T18: Associate Manager | U18: 13 | V18: The MarQ Communities
A19: 63 | B19: mostafa.salah@themarq.com.eg | C19: Moustafa Salah Mohamed Hassan | D19: 01201082999 | E19: active | F19: The MarQ Communities | H19: Finance | I19: Accounting | L19: Accounting | M19: Efrayem Refaat Hanna Shalaby | N19: 28706040104017 | O19: Accounting Manager | P19: TM4-8005 | Q19: 2025-05-11 | R19: Middle Management | S19: 3 | T19: Manager | U19: 14 | V19: Maxim For Real Estate Investment
A20: 68 | B20: omar.elseginy@themarq.com.eg | C20: Omar Abdel Hamid Mahmoud Mohamed Elsginy | D20: 01015151552 | E20: active | F20: The MarQ Communities | H20: Commercial | I20: Sales | L20: Sales | M20: Daiana Youssef Yehia Youssef Greiss | N20: 29404230101852 | O20: Senior Sales Manager | P20: TM4-8041 | Q20: 2021-05-23 | R20: Middle Management | S20: 3 | T20: Senior Manager | U20: 15 | V20: The MarQ Communities
A21: 73 | B21: samar.sonaallah@themarq.com.eg | C21: Samar Mohamed Sona-Allah Mohamed | D21: 01008395000 | E21: active | F21: The MarQ Communities | H21: Commercial | I21: Sales | L21: Sales | M21: Mohamed Ibrahim Ibrahim Darwiesh | N21: 29203103500068 | O21: Associate Sales Director | P21: TM4-11375 | Q21: 2022-03-01 | R21: Middle Management | S21: 3 | T21: Associate Director | U21: 16 | V21: The MarQ Communities
A22: 74 | B22: sameh.mohamed@themarq.com.eg | C22: Sameh Mahmoud Mohamed Khamis | D22: 01118629856 - 01281537420 | E22: active | F22: The MarQ Communities | H22: Finance | I22: Accounting | J22: General | L22: General | M22: Mohamed Mabrouk Ismail Mohamed | N22: 29504240101537 | O22: Executive Accountant | P22: TM4-8044 | Q22: 2021-06-21 | R22: Professional | S22: 5 | T22: Specialist | U22: 8 | V22: The MarQ Communities
A23: 75 | B23: sara.ezzo@themarq.com.eg | C23: Sara Ahmed Ezz eldin Moursy Abu elabbas | D23: 01005293911 | E23: active | F23: The MarQ Communities | H23: Commercial | I23: Sales | L23: Sales | M23: Omar Abdel Hamid Mahmoud Mohamed Elsginy | N23: 29006098800147 | O23: Senior Sales Manager | P23: TM4-11576 | Q23: 2022-04-10 | R23: Middle Management | S23: 3 | T23: Senior Manager | U23: 15 | V23: The MarQ Communities
A24: 76 | B24: shady.elkadry@themarq.com.eg | C24: Shady Ahmed Mohamed Mostafa | D24: 01155774442 | E24: active | F24: The MarQ Communities | H24: Commercial | I24: Sales | L24: Sales | M24: Sara Ahmed Ezz eldin Moursy Abu elabbas | N24: 29302070108912 | O24: Associate Sales Manager | P24: TM4-8038 | Q24: 2021-05-23 | R24: Supervisory Management | S24: 4 | T24: Associate Manager | U24: 13 | V24: The MarQ Communities
A25: 78 | B25: sherifa.ehab@themarq.com.eg | C25: Sherifa Ehab Helmy Ibrahim Abuzaid | D25: 01027781928 | E25: active | F25: The MarQ Communities | H25: Finance | I25: Credit Control | L25: Credit Control | M25: Ahmed Mohamed Adel Taha Abdelaal | N25: 29806040103302 | O25: Credit Control Supervisor | P25: TM4-10656 | Q25: 2021-11-15 | R25: Professional | S25: 5 | T25: Supervisor | U25: 10 | V25: The MarQ Communities
A26: 99 | B26: abdelrahman.saad@themarq.com.eg | C26: Abdelrahman Mohamed Saad Ahmed | D26: 01150812762 | E26: active | F26: The MarQ Communities | H26: Finance | I26: Accounting | J26: Accounts Receivable | L26: Accounts Receivable | M26: Mohamed Mabrouk Ismail Mohamed | N26: 29706030101218 | O26: Accounts Receivable Supervisor | P26: TM4-1038 | Q26: 2020-07-01 | R26: Professional | S26: 5 | T26: Supervisor | U26: 10 | V26: The MarQ Communities
A27: 100 | B27: hamed.ramadan@themarq.com.eg | C27: Hamed Ramadan Aliu Abdel Aal | D27: 01020405978 | E27: active | F27: The MarQ Communities | H27: Treasury | L27: Treasury | M27: Salma Mohamed Youssry Mohamed Abdelmoniem Serry | N27: 30009122700412 | O27: Treasury Supervisor | P27: TM4-12115 | Q27: 2022-07-01 | R27: Professional | S27: 5 | T27: Supervisor | U27: 10 | V27: The MarQ Communities
A28: 124 | B28: aida.fouad@themarq.com.eg | C28: Aida Fouad Mohamed Kamal | D28: 01143003133 | E28: active | F28: The MarQ Communities | H28: Finance | I28: Accounting | J28: General | K28: Administration | L28: Administration | M28: Efrayem Refaat Hanna Shalaby | N28: 29203022102441 | O28: Executive Finance Admin | P28: TM4-3716 | Q28: 2022-10-16 | R28: Professional | S28: 5 | T28: Specialist | U28: 8 | V28: The MarQ Communities
A29: 135 | B29: toka.khaled@themarq.com.eg | C29: Toka Khaled Farouk Hassan Hagag | D29: 01156052000 | E29: active | F29: The MarQ Communities | G29: The Address Holding | H29: Human Resources | I29: HR Business Partner | J29: HR Operations | L29: HR Operations | M29: Salma Amr Mohamed Shafiek | N29: 30008170104647 | O29: HR Operations Supervisor | P29: TM4-12707 | Q29: 2024-03-17 | R29: Professional | S29: 5 | T29: Supervisor | U29: 10 | V29: The MarQ Communities
A30: 152 | B30: aya.vayoniti@themarq.com.eg | C30: Aya Karim Thomas Konstantin | D30: 01001051508 | E30: active | F30: The MarQ Communities | H30: Development & Innovation | I30: Research & Development | L30: Research & Development | M30: Omar Anas Abdel Fattah Lasheen | N30: 29309280108103 | O30: Research & Development Manager | P30: TM4-13037 | Q30: 2022-12-15 | R30: Middle Management | S30: 3 | T30: Manager | U30: 14 | V30: The MarQ Communities
A31: 172 | B31: karim.elshahat@themarq.com.eg | C31: Karim Ahmed Ghareeb elshahat | D31: 01159703568 | E31: active | F31: The MarQ Communities | H31: Projects | I31: Document Control | L31: Document Control | M31: Mohamed Elsayed Shamata Abdelbaky | N31: 29701260101339 | O31: Senior Document Controller | P31: TM4-13168 | Q31: 2023-01-15 | R31: Professional | S31: 5 | T31: Senior Specialist | U31: 9 | V31: The MarQ Communities
A32: 176 | B32: mostafa.elabbasi@themarq.com.eg | C32: Mostafa Ahmed Mostafa Mohamed | D32: 01280180303 | E32: active | F32: The MarQ Communities | H32: Projects | I32: Construction Management | L32: Construction Management | M32: Mohamed Elsayed Shamata Abdelbaky | N32: 28109060100397 | O32: Project Director | P32: TM4-13203 | Q32: 2023-01-15 | R32: Executive Management | S32: 2 | T32: Director | U32: 17 | V32: The MarQ Communities
A33: 186 | B33: nour.fathy@themarq.com.eg | C33: Nour Eldin Fathy Mohamed Khaky | D33: 01029867676 | E33: active | F33: The MarQ Communities | H33: Development & Innovation | I33: Design Review | J33: Urban | L33: Urban | M33: Ahmed Shawky Shaaban Hassan | N33: 29204200103916 | O33: Associate Urban Design Review Manager | P33: TM4-13328 | Q33: 2023-02-01 | R33: Supervisory Management | S33: 4 | T33: Associate Manager | U33: 13 | V33: The MarQ Communities
A34: 187 | B34: reem.elhalawany@themarq.com.eg | C34: Reem Fawzy Ibrahim Soliman | D34: 010026117621 | E34: active | F34: The MarQ Communities | H34: Development & Innovation | I34: Development | L34: Development | M34: Omar Anas Abdel Fattah Lasheen | N34: 29001160101704 | O34: Senior Development Manager | P34: TM4-13207 | Q34: 2023-02-01 | R34: Middle Management | S34: 3 | T34: Senior Manager | U34: 15 | V34: The MarQ Communities
A35: 226 | B35: maria.halim@themarq.com.eg | C35: Maria Maged Kamal Halim | D35: 01283932707 | E35: active | F35: The MarQ Communities | H35: Development & Innovation | I35: Development | L35: Development | M35: Perihan Osama Abdelazim Sharaf | N35: 29702020101869 | O35: Development Section Head | P35: TM4-11556 | Q35: 2022-04-10 | R35: Supervisory Management | S35: 4 | T35: Section Head | U35: 12 | V35: The MarQ Communities
A36: 228 | B36: hosny.magdy@themarq.com.eg | C36: Hosny Magdy Hosny Abdel Baqi | D36: 01113108000 | E36: active | F36: The MarQ Communities | H36: Commercial | I36: Sales | L36: Sales | M36: Samar Mohamed Sona-Allah Mohamed | N36: 28605212102851 | O36: Senior Property Consultant | P36: TM4-1405 | Q36: 2023-06-04 | R36: Professional | S36: 5 | T36: Senior Specialist | U36: 9 | V36: The MarQ Communities
A37: 231 | B37: ahmed.elhussini@themarq.com.eg | C37: Ahmed Elhussini Abdelwahed Ahmed | D37: 01030369917 | E37: active | F37: The MarQ Communities | H37: Communities & Clients Excellence | I37: Business Support | L37: Business Support | M37: Yasmine Marzouk Sayed mohamed | N37: 27812090104094 | O37: Senior Business Support Specialist | P37: TM4-15424 | Q37: 2023-06-15 | R37: Professional | S37: 5 | T37: Senior Specialist | U37: 9 | V37: The MarQ Communities
A38: 233 | B38: mohamed.diaa@themarq.com.eg | C38: Mohamed DiaaElDin Ahmed Shehata ElShamy | D38: 01002751606 | E38: active | F38: The MarQ Communities | H38: Commercial | I38: Sales Operations | L38: Sales Operations | M38: Ayman Mohamed Refaat Ahmed | N38: 28807110101593 | O38: Sales Operations Section Head | P38: TM4-15410 | Q38: 2023-06-15 | R38: Supervisory Management | S38: 4 | T38: Section Head | U38: 12 | V38: The MarQ Communities
A39: 234 | B39: tarneem.mohamed@themarq.com.eg | C39: Tarnem Mohamed Mohamed El sherbini | D39: 01027390399 | E39: active | F39: The MarQ Communities | H39: Commercial | I39: Sales | L39: Sales | M39: Mazen Adnan Ahmed Mostafa Elshamy | N39: 28911180300048 | O39: Sales Supervisor | P39: TM4-1255 | Q39: 2025-11-09 | R39: Professional | S39: 5 | T39: Supervisor | U39: 10 | V39: The MarQ Communities
A40: 237 | B40: maged.mostafa@themarq.com.eg | C40: Maged Mostafa morsi attia | D40: 01224298898 | E40: active | F40: The MarQ Communities | H40: Projects | I40: Construction Management | J40: Construction Project Management | L40: Construction Project Management | M40: Mostafa Ahmed Mostafa Mohamed | N40: 28301188800675 | O40: Senior Project Manager | P40: TM4-15486 | Q40: 2023-07-09 | R40: Middle Management | S40: 3 | T40: Senior Manager | U40: 15 | V40: The MarQ Communities
A41: 239 | B41: menna.ihab@themarq.com.eg | C41: Mennat Allah ihab Mohammed hanafy | D41: 01016911128 | E41: active | F41: The MarQ Communities | H41: Commercial | I41: Sales | L41: Sales | M41: Shady Ahmed Mohamed Mostafa | N41: 29304140102308 | O41: Sales Supervisor | P41: TM4-15605 | Q41: 2023-07-09 | R41: Professional | S41: 5 | T41: Supervisor | U41: 10 | V41: The MarQ Communities
A42: 242 | B42: yasmine.marzouk@themarq.com.eg | C42: Yasmine Marzouk Sayed mohamed | D42: 01111858403 | E42: active | F42: The MarQ Communities | H42: Communities & Clients Excellence | I42: Client Relations & Community Experience | J42: Clients Relations | L42: Clients Relations | M42: Abdelrahman Eid Abdelgaffar Abdullah | N42: 29004012100323 | O42: Clients Relations Manager | P42: TM4-15492 | Q42: 2023-07-09 | R42: Middle Management | S42: 3 | T42: Manager | U42: 14 | V42: The MarQ Communities
A43: 245 | B43: karim.ayman@themarq.com.eg | C43: Karim ayman ahmed helmy | D43: 01119961995 | E43: active | F43: The MarQ Communities | H43: Finance | I43: Credit Control | L43: Credit Control | M43: Ahmed Hamdy Mohamed Abdelftah Mostafa Awaimar | N43: 29501028800272 | O43: Credit Control Supervisor | P43: TM4-15717 | Q43: 2023-07-17 | R43: Professional | S43: 5 | T43: Supervisor | U43: 10 | V43: The MarQ Communities
A44: 258 | B44: farah.elmenshawi@themarq.com.eg | C44: Farah Alaa Mohammed Menshawy | D44: 1000509917 | E44: active | F44: The MarQ Communities | H44: Commercial | I44: Sales | L44: Sales | M44: Mazen Adnan Ahmed Mostafa Elshamy | N44: 29307092101981 | O44: Sales Supervisor | P44: TM4-9029 | Q44: 2021-01-31 | R44: Professional | S44: 5 | T44: Supervisor | U44: 10 | V44: The MarQ Communities
A45: 265 | B45: eslam.fathyy@themarq.com.eg | C45: eslam fathy abdelhamid mohamed | D45: 01090348691 | E45: active | F45: The MarQ Communities | H45: Finance | I45: Accounting | J45: Accounts Receivable | L45: Accounts Receivable | M45: Mohamed Mabrouk Ismail Mohamed | N45: 29409150101675 | O45: Accounts Receivable Supervisor | P45: TM4-16864 | Q45: 2023-10-01 | R45: Professional | S45: 5 | T45: Supervisor | U45: 10 | V45: The MarQ Communities
A46: 273 | B46: mohameed.shehata@themarq.com.eg | C46: Mohamed Shehata Kamel Abdelghany | D46: 01064076531 | E46: active | F46: The MarQ Communities | H46: Projects | I46: Construction Management | J46: Construction Project Management | K46: Site Supervision | L46: Site Supervision | M46: Mohamed Mahmoud Ahmed ElBelawey | N46: 28406052300471 | O46: Site Supervisor II | P46: TM4-17265 | Q46: 2023-11-05 | R46: Basic | S46: 6 | T46: Junior Specialist - Worker Senior supervisor | U46: 7 | V46: The MarQ Communities
A47: 279 | B47: abdalaziz.saiif@themarq.com.eg | C47: Abdelaziz Ali Bakr Abdelaziz | D47: 01128330367 | E47: active | F47: The MarQ Communities | H47: Projects | I47: Construction Management | J47: Construction Project Management | K47: Construction Document Control | L47: Construction Document Control | M47: Maged Mostafa morsi attia | N47: 29910108800777 | O47: Executive Construction Document Controller | P47: TM4-17750 | Q47: 2023-12-03 | R47: Professional | S47: 5 | T47: Specialist | U47: 8 | V47: The MarQ Communities
A48: 288 | B48: ahmed.elkhateeb@themarq.com.eg | C48: Ahmed kamal El Din Hassan El Khateeb | D48: 01110005077 | E48: active | F48: The MarQ Communities | H48: Commercial | I48: Sales | L48: Sales | M48: Mazen Adnan Ahmed Mostafa Elshamy | N48: 29405088800051 | O48: Associate Sales Manager | P48: TM4-3227 | Q48: 2023-12-10 | R48: Supervisory Management | S48: 4 | T48: Associate Manager | U48: 13 | V48: The MarQ Communities
A49: 289 | B49: aasem.sehim@themarq.com.eg | C49: Assem Adel Abdelaziz Amin Seheem | D49: 1146677789 | E49: active | F49: The MarQ Communities | H49: Commercial | I49: Sales | L49: Sales | M49: Mazen Adnan Ahmed Mostafa Elshamy | N49: 29804220103871 | O49: Senior Property Consultant | P49: TM4-12659 | Q49: 2022-10-16 | R49: Professional | S49: 5 | T49: Senior Specialist | U49: 9 | V49: The MarQ Communities
A50: 292 | B50: mohamed.osama@themarq.com.eg | C50: Mohamed Osama Hassan Moussa | D50: 011113086802 | E50: active | F50: The MarQ Communities | H50: Projects | I50: Construction Management | J50: Construction Project Management | L50: Construction Project Management | M50: Mostafa Ahmed Mostafa Mohamed | N50: 28909252105372 | O50: Associate Project Manager | P50: TM4-17920 | Q50: 2024-01-01 | R50: Supervisory Management | S50: 4 | T50: Associate Manager | U50: 13 | V50: The MarQ Communities
A51: 295 | B51: menna.yahya@themarq.com.eg | C51: MennatAllah Yahya Mohamed Tawfik Ahmed Abdul Aziz | D51: 01005397775 | E51: active | F51: The MarQ Communities | H51: Commercial | I51: Business Development | L51: Business Development | M51: Amr Mohamed Abdel-Hay Badr | N51: 28608310101366 | O51: Business Development Director | P51: TM4-15460 | Q51: 2023-07-04 | R51: Executive Management | S51: 2 | T51: Director | U51: 17 | V51: The MarQ Communities
A52: 296 | B52: randa.fayad@themarq.com.eg | C52: Randa Mohamed Abdel Moneim Fayad | D52: 01001070827 | E52: active | F52: The MarQ Communities | H52: Development & Innovation | I52: Development Pricing | L52: Development Pricing | M52: Omar Anas Abdel Fattah Lasheen | N52: 29108010103449 | O52: Senior Development Pricing Manager | P52: TM4-8027 | Q52: 2021-01-12 | R52: Middle Management | S52: 3 | T52: Senior Manager | U52: 15 | V52: The MarQ Communities
A53: 297 | B53: heba.hashish@themarq.com.eg | C53: Heba Magdy Elbialy Hashish | D53: 01005669889 | E53: active | F53: The MarQ Communities | H53: Commercial | I53: Business Development | L53: Business Development | M53: MennatAllah Yahya Mohamed Tawfik Ahmed Abdul Aziz | N53: 28901241200526 | O53: Business Development Manager | P53: TM4-17254 | Q53: 2023-11-01 | R53: Middle Management | S53: 3 | T53: Manager | U53: 14 | V53: The MarQ Communities
A54: 299 | B54: lana.afifi@themarq.com.eg | C54: Lana Hany Mohamed Kamal Afifi | D54: 01111005349 | E54: active | F54: The MarQ Communities | H54: Development & Innovation | I54: Development Pricing | L54: Development Pricing | M54: Randa Mohamed Abdel Moneim Fayad | N54: 30002021311828 | O54: Development Pricing Supervisor | P54: TM4-17255 | Q54: 2023-11-01 | R54: Professional | S54: 5 | T54: Supervisor | U54: 10 | V54: The MarQ Communities
A55: 300 | B55: ahmed.medhat@themarq.com.eg | C55: Ahmed Medhat Sayed Baioumy el Atbany | D55: 01285342768 | E55: active | F55: The MarQ Communities | H55: Investment | L55: Investment | M55: Efrayem Refaat Hanna Shalaby | N55: 29002222102733 | O55: Senior Investment Manager | P55: TM4-8036 | Q55: 2021-05-06 | R55: Middle Management | S55: 3 | T55: Senior Manager | U55: 15 | V55: The MarQ Communities
A56: 301 | B56: ahmed.raouf@themarq.com.eg | C56: Ahmed Raouf Abdel Menaam Hanafy | D56: 1277300584 | E56: active | F56: The MarQ Communities | H56: Commercial | I56: Business Development | L56: Business Development | M56: MennatAllah Yahya Mohamed Tawfik Ahmed Abdul Aziz | N56: 28507150107213 | O56: Associate Business Development Manager | P56: TM4-9062 | Q56: 2021-08-22 | R56: Supervisory Management | S56: 4 | T56: Associate Manager | U56: 13 | V56: The MarQ Communities
A57: 303 | B57: eleonora.christo@themarq.com.eg | C57: Eleonora Christo Paraskevas Vostanis | D57: 01001483748 | E57: active | F57: The MarQ Communities | H57: Marketing & PR | I57: Brand Strategy | J57: Content Writing | L57: Content Writing | M57: Noha Hassan Sabry Mohamed Ibrahim | N57: 30002140100061 | O57: Junior Content Writer | P57: TM4-16669 | Q57: 2023-09-14 | R57: Basic | S57: 6 | T57: Junior Specialist - Worker Senior supervisor | U57: 7 | V57: The MarQ Communities
A58: 307 | B58: mahmoud.samy@themarq.com.eg | C58: Mahmoud Samy Mohamed El Meligy | D58: 01274772894 | E58: active | F58: The MarQ Communities | H58: Commercial | I58: Sales | L58: Sales | M58: Shady Ahmed Mohamed Mostafa | N58: 29304052102519 | O58: Sales Supervisor | P58: TM4-1883 | Q58: 2025-09-01 | R58: Professional | S58: 5 | T58: Supervisor | U58: 10 | V58: The MarQ Communities
A59: 312 | B59: mohab.amin@themarq.com.eg | C59: Mohab Ahmed Mohamed Amin | D59: 01001018738 | E59: active | F59: The MarQ Communities | H59: Development & Innovation | I59: Development | L59: Development | M59: Reem Fawzy Ibrahim Soliman | N59: 29304138800154 | O59: Development Manager | P59: TM4-13357 | Q59: 2023-02-01 | R59: Middle Management | S59: 3 | T59: Manager | U59: 14 | V59: The MarQ Communities
A60: 316 | B60: mostafa.elassal@themarq.com.eg | C60: Moustafa Mohamed Mohamed El Assal | D60: 1000774065 | E60: active | F60: The MarQ Communities | H60: CEO Office | L60: CEO Office | M60: Amr Mohamed Abdel-Hay Badr | N60: 28805020103314 | O60: Deputy CEO | P60: TM4-9005 | Q60: 2019-09-01 | R60: Top Management | S60: 1 | T60: CEOs -Board Member | U60: 21 | V60: The MarQ Communities
A61: 319 | B61: omar.lasheen@themarq.com.eg | C61: Omar Anas Abdel Fattah Lasheen | D61: 1008485582 | E61: active | F61: The MarQ Communities | H61: CEO Office | L61: CEO Office | M61: Amr Mohamed Abdel-Hay Badr | N61: 29205050103811 | O61: Deputy CEO | P61: TM4-9004 | Q61: 2021-01-01 | R61: Top Management | S61: 1 | T61: CEOs -Board Member | U61: 21 | V61: The MarQ Communities
A62: 320 | B62: perihan.sharaf@themarq.com.eg | C62: Perihan Osama Abdelazim Sharaf | D62: 01227800419 | E62: active | F62: The MarQ Communities | H62: Development & Innovation | I62: Development | L62: Development | M62: Omar Anas Abdel Fattah Lasheen | N62: 29409302104446 | O62: Senior Development Manager | P62: TM4-16011 | Q62: 2025-05-05 | R62: Middle Management | S62: 3 | T62: Senior Manager | U62: 15 | V62: The MarQ Communities
A63: 323 | B63: sandra.benjamin@themarq.com.eg | C63: Sandra Atallah Fouad Benjamin | D63: 1274985641 | E63: active | F63: The MarQ Communities | H63: Development & Innovation | I63: Innovation & Product Development | L63: Innovation & Product Development | M63: Omar Anas Abdel Fattah Lasheen | N63: 29807270103561 | O63: Innovation & Product Development Manager | P63: TM4-9022 | Q63: 2020-07-06 | R63: Middle Management | S63: 3 | T63: Manager | U63: 14 | V63: The MarQ Communities
A64: 352 | B64: mohamed.nezar@themarq.com.eg | C64: Mohamed Nezar Ibrahim Abou Elfetouh | D64: 01234525900 | E64: active | F64: The MarQ Communities | H64: Communities & Clients Excellence | I64: Community Operations | L64: Community Operations | M64: Amr Mohamed Abdel-Hay Badr | N64: 28911202100897 | O64: Senior Community Operations Director | P64: TM4-18456 | Q64: 2024-02-01 | R64: Executive Management | S64: 2 | T64: Senior Director | U64: 18 | V64: The MarQ Communities
A65: 359 | B65: fady.rezk@themarq.com.eg | C65: Fady Fayek Fouad Rezk | D65: 01284939672 | E65: active | F65: The MarQ Communities | H65: Commercial | I65: Sales | L65: Sales | M65: Mazen Adnan Ahmed Mostafa Elshamy | N65: 29709282101333 | O65: Senior Property Consultant | P65: TM4-12201 | Q65: 2024-02-11 | R65: Professional | S65: 5 | T65: Senior Specialist | U65: 9 | V65: The MarQ Communities
A66: 376 | B66: samir.mansour@themarq.com.eg | C66: Samir Mansour Mohamed Ahmed | D66: 01008893317 | E66: active | F66: The MarQ Communities | H66: Projects | I66: Document Control | L66: Document Control | M66: Mohamed Elsayed Shamata Abdelbaky | N66: 28705211400853 | O66: Document Control Manager | P66: TM4-18696 | Q66: 2024-02-05 | R66: Middle Management | S66: 3 | T66: Manager | U66: 14 | V66: The MarQ Communities
A67: 377 | B67: shady.amir@themarq.com.eg | C67: Shady Amir Ahmed Mirdan | D67: 01069121035 | E67: active | F67: The MarQ Communities | H67: Projects | I67: Construction Management | J67: Construction Project Management | K67: Site Supervision | L67: Site Supervision | M67: Maged Mostafa morsi attia | N67: 27610060300156 | O67: Site Supervisor III | P67: TM4-18704 | Q67: 2024-02-06 | R67: Professional | S67: 5 | T67: Specialist | U67: 8 | V67: The MarQ Communities
A68: 378 | B68: walid.mohamed@themarq.com.eg | C68: Waleed Mohamed Hassan Ali | D68: 01000289776 | E68: active | F68: The MarQ Communities | H68: Communities & Clients Excellence | I68: Community Safety & Security | L68: Community Safety & Security | M68: Baher Saeed Khamis Mahmoud Elshamy | N68: 27312061200073 | O68: Security Manager | P68: TM4-18958 | Q68: 2024-02-15 | R68: Professional | S68: 5 | T68: Senior Specialist | U68: 9 | V68: The MarQ Communities
A69: 452 | B69: a.saleh@themarq.com.eg | C69: Abdelhameed Mahmoud Abdelhameed Saleh | D69: 01005325045 | E69: active | F69: The MarQ Communities | H69: Internal Audit | L69: Internal Audit | M69: Amr Mohamed Abdel-Hay Badr | N69: 27105252102513 | O69: Chief Internal Audit Officer / Board Member | P69: TM4-11423 | Q69: 2022-03-10 | R69: Top Management | S69: 1 | T69: Chief Officer | U69: 20 | V69: The MarQ Communities
A70: 721 | B70: ahmed.nafie@themarq.com.eg | C70: Ahmed Mohamed Mohamed Salem | D70: 01000198526 | E70: active | F70: The MarQ Communities | H70: Corporate Operational Excellence | L70: Corporate Operational Excellence | M70: Moustafa Mohamed Mohamed El Assal | N70: 29008100100134 | O70: Corporate Operational Excellence Director | P70: TM4-12308 | Q70: 2022-09-04 | R70: Executive Management | S70: 2 | T70: Director | U70: 17 | V70: The MarQ Communities
A71: 802 | B71: ahmed.elshiaty@themarq.com.eg | C71: Ahmed elsayed elsayed elshiaty | D71: 01006856836 | E71: active | F71: The MarQ Communities | H71: Human Resources | I71: Learning & Development | L71: Learning & Development | M71: Sylvia Nabih Doss Abd Allah | N71: 28608011608012 | O71: Learning & Development Director | P71: TM4-17746 | Q71: 2023-12-03 | R71: Executive Management | S71: 2 | T71: Director | U71: 17 | V71: The MarQ Communities
A72: 904 | B72: amira.tareq@themarq.com.eg | C72: Amira Tarek Mohamed Abdelmutaal Ali El Sherkawy | D72: 01005353396 | E72: active | F72: The MarQ Communities | H72: Commercial | I72: Sales | L72: Sales | M72: Mahmoud Amr Mahmoud Kamel Rashad Tawakol | N72: 29601251200125 | O72: Senior Property Consultant | P72: TM4-15065 | Q72: 2025-11-02 | R72: Professional | S72: 5 | T72: Senior Specialist | U72: 9 | V72: The MarQ Communities
A73: 927 | B73: amr.badr@themarq.com.eg | C73: Amr Mohamed Abdel-Hay Badr | D73: 1007607215 | E73: active | F73: The MarQ Communities | H73: CEO Office | L73: CEO Office | M73: Donia Helal | N73: 28510148800379 | O73: CEO | P73: TM4-9001 | Q73: 2016-03-01 | R73: Top Management | S73: 1 | T73: CEOs -Board Member | U73: 21 | V73: The MarQ Communities
A74: 1008 | B74: aya.elshemy@themarq.com.eg | C74: Aya Mohamed Gamal ELdin Elshemy | D74: 01032929299 | E74: active | F74: The MarQ Communities | H74: Commercial | I74: Business Support | L74: Business Support | M74: Amr Mohamed Abdel-Hay Badr | N74: 29212090102288 | O74: Business Support Manager | P74: TM4-2040 | Q74: 2023-07-09 | R74: Middle Management | S74: 3 | T74: Manager | U74: 14 | V74: The MarQ Communities
A75: 1138 | B75: efrayem.refaat@themarq.com.eg | C75: Efrayem Refaat Hanna Shalaby | D75: 01287373523 | E75: active | F75: The MarQ Communities | H75: Investment | L75: Investment | M75: Amr Mohamed Abdel-Hay Badr | N75: 29110222500612 | O75: Chief Investment Officer | P75: TM4-14538 | Q75: 2023-03-05 | R75: Top Management | S75: 1 | T75: Chief Officer | U75: 20 | V75: The MarQ Communities
A76: 1888 | B76: mayar.yasser@themarq.com.eg | C76: Mayar Yasser Abdel Razek Ibrahim | D76: 01098452794 | E76: active | F76: The MarQ Communities | H76: Development & Innovation | I76: Research & Development | L76: Research & Development | M76: Aya Karim Thomas Konstantin | N76: 30006030104725 | O76: Senior Research & Development Specialist | P76: TM4-1069 | Q76: 2023-09-27 | R76: Professional | S76: 5 | T76: Senior Specialist | U76: 9 | V76: The MarQ Communities
A77: 1987 | B77: meriam.atef@themarq.com.eg | C77: Meriam Atef Labib Asaad | D77: 01211498779 | E77: active | F77: The MarQ Communities | H77: Commercial | I77: Sales | L77: Sales | M77: Ahmed Shawky Abdo El Bastawisy El Sahy | N77: 30011050105462 | O77: Property Consultant | P77: TM4-19013 | Q77: 2025-09-01 | R77: Professional | S77: 5 | T77: Specialist | U77: 8 | V77: The MarQ Communities
A78: 2500 | B78: nariman.nabil@themarq.com.eg | C78: Nariman Nabil Shohdy Zakria | D78: 01111148998 | E78: active | F78: The MarQ Communities | H78: Human Resources | I78: Learning & Development | J78: Employer Branding | L78: Employer Branding | M78: Ahmed elsayed elsayed elshiaty | N78: 29805260103145 | O78: Employer Branding Section Head | P78: TM4-17892 | Q78: 2024-01-08 | R78: Supervisory Management | S78: 4 | T78: Section Head | U78: 12 | V78: The MarQ Communities
A79: 2503 | B79: nayera.elshabrawy@themarq.com.eg | C79: Nayera Ibrahim ElShabrawy Ibrahim | D79: 01226299986 | E79: active | F79: The MarQ Communities | H79: Marketing & PR | I79: Brand Strategy | L79: Brand Strategy | M79: Soha Sabry Aziz Nakola | N79: 28610270104248 | O79: Senior Marketing Manager | P79: TM4-9045 | Q79: 2021-06-01 | R79: Middle Management | S79: 3 | T79: Senior Manager | U79: 15 | V79: The MarQ Communities
A80: 2588 | B80: nourhan.yasser@themarq.com.eg | C80: Nourhan yasser Hamed Elmoaz | D80: 01000461636 | E80: active | F80: The MarQ Communities | H80: Commercial | I80: Business Development | L80: Business Development | M80: MennatAllah Yahya Mohamed Tawfik Ahmed Abdul Aziz | N80: 29304011708763 | O80: Business Development Supervisor | P80: TM4-12569 | Q80: 2022-10-02 | R80: Professional | S80: 5 | T80: Supervisor | U80: 10 | V80: The MarQ Communities
A81: 2692 | B81: passant.magdy@themarq.com.eg | C81: Passant Magdy Abdel Razek Eliwa | D81: 01099691693 | E81: active | F81: The MarQ Communities | H81: Human Resources | I81: Organization Development & Talent Management | L81: Organization Development & Talent Management | M81: Sylvia Nabih Doss Abd Allah | N81: 29101290102448 | O81: OD & Talent Management Director | P81: TM4-14720 | Q81: 2023-04-02 | R81: Executive Management | S81: 2 | T81: Director | U81: 17 | V81: The MarQ Communities
A82: 3100 | B82: sylvia.doss@themarq.com.eg | C82: Sylvia Nabih Doss Abd Allah | D82: 01226181018 | E82: active | F82: The MarQ Communities | H82: Human Resources | L82: Human Resources | M82: Amr Mohamed Abdel-Hay Badr | N82: 27402070100501 | O82: Chief Human Resources Officer | P82: TM4-11719 | Q82: 2022-05-15 | R82: Top Management | S82: 1 | T82: Chief Officer | U82: 20 | V82: The MarQ Communities
A83: 3354 | B83: heba.ashraf@themarq.com.eg | C83: heba ashraf youssef ibrahim | D83: 01204105555 | E83: active | F83: The MarQ Communities | H83: Marketing & PR | I83: Brand Strategy | L83: Brand Strategy | M83: Mirna Mamdouh Zaki Andrawes | N83: 30104040103885 | O83: Senior Marketing Specialist | P83: TM4-16641 | Q83: 2023-09-14 | R83: Professional | S83: 5 | T83: Senior Specialist | U83: 9 | V83: The MarQ Communities
A84: 3444 | B84: diana.elsehemy@themarq.com.eg | C84: Diana Hossam Abdelrahman Osman | D84: 01117139927 | E84: active | F84: The MarQ Communities | H84: Development & Innovation | I84: Design Management | L84: Design Management | M84: Ahmed Shawky Shaaban Hassan | N84: 29410160101183 | O84: Design Management Section Head | P84: TM4-19302 | Q84: 2024-03-10 | R84: Supervisory Management | S84: 4 | T84: Section Head | U84: 12 | V84: The MarQ Communities
A85: 3479 | B85: hania.moez@themarq.com.eg | C85: Hania Ahmed Abdelmoez Ahmed | D85: 01111233006 | E85: active | F85: The MarQ Communities | H85: Marketing & PR | I85: Brand Strategy | J85: Graphic Design | L85: Graphic Design | M85: Noha Hassan Sabry Mohamed Ibrahim | N85: 29911150105546 | O85: Senior Graphic designer | P85: TM4-19332 | Q85: 2024-03-10 | R85: Professional | S85: 5 | T85: Senior Specialist | U85: 9 | V85: The MarQ Communities
A86: 3483 | B86: ibrahim.hafez@themarq.com.eg | C86: Ibrahim Abdelaziz Osama Ibrahim Hafez | D86: 01125796378 | E86: active | F86: The MarQ Communities | H86: Commercial | I86: Sales Operations | L86: Sales Operations | M86: Atef Rezk El Sayed El Sayed El Sabbagh | N86: 29612230104152 | O86: Executive Sales Operations Specialist | P86: TM4-19296 | Q86: 2024-03-10 | R86: Professional | S86: 5 | T86: Specialist | U86: 8 | V86: The MarQ Communities
A87: 3512 | B87: m.youssef@themarq.com.eg | C87: Mohamed Ahmed Ibrahim Youssef | E87: active | F87: The MarQ Communities | H87: Communities & Clients Excellence | I87: Community Operations | J87: Community Engineering | K87: Communication & Administration | L87: Communication & Administration | M87: Mohamed Nezar Ibrahim Abou Elfetouh | N87: 28905040102513 | O87: Associate Communication & Administration Manager | P87: TM4-19270 | Q87: 2024-03-01 | R87: Supervisory Management | S87: 4 | T87: Associate Manager | U87: 13 | V87: The MarQ Communities
A88: 3770 | B88: abdelhakiem.mohamed@themarq.com.eg | C88: Abdelhakim Mohamed Ali Nasser | D88: 01062227790 | E88: active | F88: The MarQ Communities | H88: Communities & Clients Excellence | I88: Community Operations | J88: Facility Management | K88: Community MEP | L88: Community MEP | M88: Mohamed Magdy Elsaeed Elfiky | N88: 26702052701735 | O88: Senior Community MEP Supervisor | P88: TM4-19571 | Q88: 2024-03-05 | R88: Basic | S88: 6 | T88: Junior Specialist - Worker Senior supervisor | U88: 7 | V88: The MarQ Communities
A89: 3772 | B89: abdelrhman.amer@themarq.com.eg | C89: Abdelrahman Amer Abdelrahman Ahmed | D89: 01067880457 | E89: active | F89: The MarQ Communities | H89: Communities & Clients Excellence | I89: Client Relations & Community Experience | J89: Clients Relations | L89: Clients Relations | M89: Seif Mohamed Abd El Halim | N89: 29602210101259 | O89: Executive Clients Relations Specialist | P89: TM4-19766 | Q89: 2025-04-17 | R89: Professional | S89: 5 | T89: Specialist | U89: 8 | V89: The MarQ Communities
A90: 3941 | B90: nabil.elshabany@themarq.com.eg | C90: Nabil Hamed Metwaly Mohamed | D90: 01092727849 | E90: active | F90: The MarQ Communities | H90: Communities & Clients Excellence | I90: Community Operations | J90: Community Engineering | L90: Community Engineering | M90: Mohamed Ahmed Ibrahim Youssef | N90: 29105101100273 | O90: Community Engineering Teamleader | P90: TM4-19739 | Q90: 2025-05-11 | R90: Supervisory Management | S90: 4 | T90: Teamleader | U90: 11 | V90: The MarQ Communities
A91: 4028 | B91: mohamed.abdelfattah@themarq.com.eg | C91: Mohamed Abdelfattah Saeed Abdelmaged | D91: 01150981043 | E91: active | F91: The MarQ Communities | H91: Communities & Clients Excellence | I91: Client Relations & Community Experience | J91: Community Experience | K91: Community Quality Control | L91: Community Quality Control | M91: Ahmed Osama Roshdy Abdelgawad | N91: 29810180100572 | O91: Senior Community Quality Control Specialist | P91: TM4-19875 | Q91: 2024-04-17 | R91: Professional | S91: 5 | T91: Senior Specialist | U91: 9 | V91: The MarQ Communities
A92: 4098 | B92: mostafa.ali@themarq.com.eg | C92: Mostafa Ali Abdelmohsen Mohamed | D92: 01140171761 | E92: active | F92: The MarQ Communities | G92: The Address Holding | H92: Finance | I92: Accounting | J92: General | L92: General | M92: Efrayem Refaat Hanna Shalaby | N92: 29709270102318 | O92: Executive Accountant | P92: TM4-19906 | Q92: 2024-05-01 | R92: Professional | S92: 5 | T92: Specialist | U92: 8 | V92: Maxim For Real Estate Investment
A93: 4247 | B93: gihan.auf@themarq.com.eg | C93: Gihan Mohamed Labib Abdelbasset Auf | D93: 01152488862 | E93: active | F93: The MarQ Communities | H93: Marketing & PR | I93: Brand Strategy | L93: Brand Strategy | M93: Nayera Ibrahim ElShabrawy Ibrahim | N93: 29511180101245 | O93: Associate Marketing Manager | P93: TM4-20298 | Q93: 2024-05-15 | R93: Supervisory Management | S93: 4 | T93: Associate Manager | U93: 13 | V93: The MarQ Communities
A94: 4321 | B94: mohamed.fawzy@themarq.com.eg | C94: Mohamed Fawzy Ragab Ali | D94: 01001545653 | E94: active | F94: The MarQ Communities | H94: Communities & Clients Excellence | I94: Communication Center | L94: Communication Center | M94: Moustafa Mohamed Mohamed El Assal | N94: 28701011421176 | O94: Communication Center Director | P94: TM4-20070 | Q94: 2024-05-01 | R94: Executive Management | S94: 2 | T94: Director | U94: 17 | V94: The MarQ Communities
A95: 4353 | B95: mostafa.m.ellaithy@themarq.com.eg | C95: Mostafa Fahim Hamdy Ellaithy | D95: 01002528283 | E95: active | F95: The MarQ Communities | H95: Development & Innovation | I95: Design Review | J95: MEP | L95: MEP | M95: Ahmed Shawky Shaaban Hassan | N95: 29005142103355 | O95: MEP Design Review Section Head | P95: TM4-20208 | Q95: 2024-05-01 | R95: Supervisory Management | S95: 4 | T95: Section Head | U95: 12 | V95: The MarQ Communities
A96: 4414 | B96: sondos.abdelaziz@themarq.com.eg | C96: Sondos Abdelaziz Mohamed Abdelaziz | D96: 01100797081 | E96: active | F96: The MarQ Communities | H96: Marketing & PR | I96: Brand Strategy | J96: Graphic Design | L96: Graphic Design | M96: Noha Hassan Sabry Mohamed Ibrahim | N96: 29807282103664 | O96: Senior Graphic designer | P96: TM4-20303 | Q96: 2024-05-19 | R96: Professional | S96: 5 | T96: Senior Specialist | U96: 9 | V96: The MarQ Communities
A97: 4471 | B97: baher.elshamy@themarq.com.eg | C97: Baher Saeed Khamis Mahmoud Elshamy | D97: 01028333413 | E97: active | F97: The MarQ Communities | H97: Communities & Clients Excellence | I97: Community Safety & Security | L97: Community Safety & Security | M97: Moustafa Mohamed Mohamed El Assal | N97: 27912010111693 | O97: Senior Community Safety & Security Director | P97: TM4-20296 | Q97: 2024-05-01 | R97: Executive Management | S97: 2 | T97: Senior Director | U97: 18 | V97: The MarQ Communities
A98: 4600 | B98: ahmed.salah@themarq.com.eg | C98: Ahmed Yasser Salah Mohamed | D98: 01118839985 | E98: active | F98: The MarQ Communities | H98: Commercial | I98: Sales | L98: Sales | M98: Ahmed Shawky Abdo El Bastawisy El Sahy | N98: 30009010104795 | O98: Senior Property Consultant | P98: TM4-20639 | Q98: 2025-09-01 | R98: Professional | S98: 5 | T98: Senior Specialist | U98: 9 | V98: The MarQ Communities
A99: 4681 | B99: mohamed.magdy@themarq.com.eg | C99: Mohamed Magdy Elsaeed Elfiky | D99: 01015526623 | E99: active | F99: The MarQ Communities | H99: Communities & Clients Excellence | I99: Community Operations | J99: Facility Management | K99: Community MEP | L99: Community MEP | M99: Ayman Mousa Haneen Mokbel | N99: 29601288800459 | O99: Community MEP Section Head | P99: TM4-20642 | Q99: 2024-06-01 | R99: Supervisory Management | S99: 4 | T99: Section Head | U99: 12 | V99: The MarQ Communities
A100: 4815 | B100: a.magdi@themarq.com.eg | C100: Ahmed Magdy Fekry Elhagaa | D100: 01024642618 | E100: active | F100: The MarQ Communities | H100: Human Resources | I100: Learning & Development | L100: Learning & Development | M100: Ahmed elsayed elsayed elshiaty | N100: 28801301700278 | O100: Learning & Development Manager | P100: TM4-21123 | Q100: 2024-07-02 | R100: Middle Management | S100: 3 | T100: Manager | U100: 14 | V100: The MarQ Communities
...

Sheet Calc
B1: Attended | C1: Head Count (212) | D1: Didn’t attend yet | E1: Sector
B2: Amr Hussein Hassan Mohamed Ali | C2: Toka Khaled Farouk Hassan Hagag | D2: Amr Mohamed Abdel-Hay Badr | E2: CEO Office
B3: Osama Abdelaziz Elsayed Salama | C3: Nourhan yasser Hamed Elmoaz | D3: Moustafa Mohamed Mohamed El Assal | E3: CEO Office
B4: Sondos Abdelaziz Mohamed Abdelaziz | C4: Mohamed Ahmed Ibrahim Youssef | D4: Omar Anas Abdel Fattah Lasheen | E4: CEO Office
B5: Moataz Ahmed Fares Hussein Abdelnaby | C5: Mohab Ahmed Mohamed Amin | D5: Marwa Gamal Eldin Elsayed Eissa Elsisy | E5: CEO Office
B6: Mohamed Ahmed Abdallah Ahmed Sharaf | C6: Mohamed Nezar Ibrahim Abou Elfetouh | D6: Mennatullah Hassan Elshabrawy Mohamed Ali | E6: CEO Office
B7: Ahmed Khaled Kamal Ibrahim | C7: Gehad Badr El Sayed Bayoumi | D7: Ahmed Amgad Mohammed Ezzat Ali Eltaweel | E7: Commercial
B8: Ahmed Medhat Sayed Baioumy el Atbany | C8: Hany Refaat Abdallah Mohamed | D8: Ahmed Essam mohamed zayed | E8: Commercial
B9: Ahmed Samir Galal Elelemy Ahmed | C9: Moustafa Salah Mohamed Hassan | D9: Ahmed Mohamed Naguib Abdelhakim Abdelhakim Farag | E9: Commercial
B10: Alaa Essam Mohamed Ibrahim | C10: Sara Ahmed Ezz eldin Moursy Abu elabbas | D10: Ahmed Sayed Abdel Satar Elsayed | E10: Commercial
B11: Amr Alaa Eldin Maged Ahmed | C11: Sherifa Ehab Helmy Ibrahim Abuzaid | D11: Ahmed Taha Nagdy Ibrahim | E11: Commercial
B12: Amr Ali Abdelwahab Sobh | C12: Abdelrahman Mohamed Saad Ahmed | D12: Ahmed Tarek Ahmed Refaat Abdelmawla | E12: Commercial
... B107: Alaa Eldin Medhat Ibrahim Hendi | C107: Mohamed Fawzy Ragab Ali | D107: Salma Mohamed Youssry Mohamed Abdelmoniem Serry | E107: Treasury
B108: Aya Karim Thomas Konstantin | C108: Youssef Hussien Abdelrahman Abdelmeged
B109: Abdelaziz Ali Bakr Abdelaziz | C109: Ahmed Osama Roshdy Abdelgawad
B110: Ahmed AlaaEldin Abdelhalim Ismail Keshk | C110: Adel Abdelfattah Elmeselhy Hassan
B111: Akram Ibrahim Mohamed Ibrahim Mubarak | C111: Mohamed Adel mohamed khader
B112: Almohsen Abdelwahab Abdelzaher Youssef | C112: Salah Hassan ElBanna Mohamad Abdo
B113: AlShimaa Ahmed Mohamed Abdullatif | C113: Mariam Ibrahim Mohamed Ibrahim
B114: Aya Hussein Omar Ahmed | C114: Ahmed Essam mohamed zayed
B115: Ayman Mostafa Yousri Ahmed Mohamed | C115: Akram Ibrahim Mohamed Ibrahim Mubarak
B116: Mahmoud AbdElaziem Mohamed Ali | C116: Ahmed Mohsen Ahmed Hassan
B117: Mohamed Maged Mohamed Khalil | C117: Ahmed Abdelfatah Saied Abdelmeged Asaker
B118: Mohamed Mahmoud Ahmed ElBelawey | C118: Shaza Hassan Ahmed Sherif
B119: Mohamed Osama Hassan Moussa | C119: Mosaad Abd El hameed Mohamed Abd elhameed
... B123: Grand Total | C123: Ahmed Mohamed Ahmed Salem
C124: Moataz Ahmed Fares Hussein Abdelnaby
C125: Salma Mohamed Youssry Mohamed Abdelmoniem Serry
C126: Mohamed Maged Mohamed Khalil
C127: Mohamed Mahmoud Ahmed ElBelawey
C128: Israa Mahmoud Elsayed Maraie
C129: Toaa Abdelrahman Abdallah Ghanem
C130: Abdelaziz Youssef Abo El Wafa Mohamed
C131: Remon Magdy Mounir Gerges
C132: Abdelfatah Abdelmoniem Abdelraouf Elsayd
C133: Mohamed Mahmoud Eid Mohamed
C134: Habiba Sadek Mohamed AlSayed
C135: Mohamed Abed Salama Ghanem
... C213: Moatazbellah Sabry Elsayed Abdo Mohamed
